Workbook
Name __APW_RESTORE_DATA1__: #REF!,#REF!,#REF!,#REF!
Name __APW_RESTORE_DATA3__: #REF!,#REF!,#REF!,#REF!
Name __APW_RESTORE_DATA4__: #REF!,#REF!
Name __FDS_HYPERLINK_TOGGLE_STATE__: "ON"
Name __FDS_UNIQUE_RANGE_ID_GENERATOR_COUNTER: 1
Name __FDS_USED_FOR_REUSING_RANGE_IDS_RECYCLE: {140,139,138,137,140,139,138,137,140,139,138,137}
Name _bdm.42389e681bad43adaa92dc72edb78440.edm: '[2]Historical valuation Multiples'!$1:$1048576
Name _bdm.4cc6c3f7212b453aa7db026c9e53fa0e.edm: '[2]Earnings Table'!$1:$1048576
Name _bdm.6fbf9c4f0dfc456e8dfb33e508fe1b40.edm: '[2]Charts for Note'!$1:$1048576
Name _bdm.817768c024224af6840c4b9c6ec6e80b.edm: '[2]Price Target Multiples'!$1:$1048576
Name _bdm.844cbf4eafa1411d893b76b79490fb19.edm: '[2]UBS v Street'!$1:$1048576
Name _bdm.959033ce93554545be1932573be82348.edm: '[2]Outsourcing Financial Impli'!$1:$1048576
Name _bdm.db941b998fa14c118b971d482d2cce12.edm: '[2]Preso Summ'!$1:$1048576
Name _bdm.ec17c843a116485d98ff55d7d231e185.edm: [2]Valuation!$1:$1048576
Name _Model_Path: "S:\SEMICONDUCTOR\USSemiconductor\Companies\INTC\INTC MASTER_lockedforwire_2.22.2023.xlsx"
Name AAPLindex: '[2]Business Analysis'!$129:$129
Name Accounts_Receivable: '[2]CUS Image'!$145:$145
Name adf: {#N/A,#N/A,FALSE,"earnings"}
Name Adjusted_EBIT: '[2]CUS Image'!$8:$8
Name Adjusted_Effective_Tax_Rate: '[2]CUS Image'!$70:$70
Name AIndex: '[2]Business Analysis'!$127:$127
Name AJHFkjDGHF: {"Annual_Income",#N/A,FALSE,"Report Page";"Balance_Cash_Flow",#N/A,FALSE,"Report Page";"Quarterly_Income",#N/A,FALSE,"Report Page"}
Name annual: {#N/A,#N/A,FALSE,"earnings"}
Name annual1: {#N/A,#N/A,FALSE,"earnings"}
Name annual2: {#N/A,#N/A,FALSE,"earnings"}
Name aretn: {#N/A,#N/A,FALSE,"earnings"}
Name asdf: {#N/A,#N/A,FALSE,"earnings"}
Name Avg_Curr_Stock_Price_For_Period_EPS: '[2]CUS Image'!$399:$399
Name Avg_Diluted_Shares_For_Diluted_EPS: '[2]CUS Image'!$120:$120
Name BAAMDDTUnitShare: '[2]Business Analysis'!$284:$284
Name BAAMDMPUDTSales: '[2]Business Analysis'!$282:$282
Name BAAMDMPUDTUnits: '[2]Business Analysis'!$273:$273
Name BAAMDMPUNBSales: '[2]Business Analysis'!$301:$301
Name BAAMDMPUNBUnits: '[2]Business Analysis'!$294:$294
Name BAAMDMPUSales: '[2]Business Analysis'!$230:$230
Name BAAMDMPUServerSales: '[2]Business Analysis'!$347:$347
Name BAAMDMPUServerUnits: '[2]Business Analysis'!$339:$339
Name BAAMDMPUUnits: '[2]Business Analysis'!$968:$968
Name BAAMDUnitShare: '[2]Business Analysis'!$214:$214
Name BACapex: '[2]Business Analysis'!$697:$697
Name BACFO: '[2]Business Analysis'!$696:$696
Name BACOGS: '[2]Business Analysis'!$759:$759
Name BADA: '[2]Business Analysis'!$695:$695
Name BADates: '[2]Business Analysis'!$204:$204
Name BAEBIT: '[2]Business Analysis'!$460:$460
Name BAIndex: '[2]Business Analysis'!$1:$1
Name BAINTCMPUDTSales: '[2]Business Analysis'!$281:$281
Name BAINTCMPUDTUnits: '[2]Business Analysis'!$270:$270
Name BAINTCMPUNBSales: '[2]Business Analysis'!$299:$299
Name BAINTCMPUNBUnits: '[2]Business Analysis'!$291:$291
Name BAINTCMPUSales: '[2]Business Analysis'!$229:$229
Name BAINTCMPUServerSales: '[2]Business Analysis'!$345:$345
Name BAINTCMPUServerUnits: '[2]Business Analysis'!$338:$338
Name BAINTCMPUUnits: '[2]Business Analysis'!$967:$967
Name BAInv: '[2]Business Analysis'!$679:$679
Name BAITNCQAvgSharePrice: '[2]Business Analysis'!$483:$483
Name BANI: '[2]Business Analysis'!$692:$692
Name BAOpex: '[2]Business Analysis'!$464:$464
Name BARev: '[2]Business Analysis'!$446:$446
Name BASOE: '[2]Business Analysis'!$489:$489

Sheet __FDSCACHE__
B1: This sheet contains FactSet XML data for use with this workbook's =FDS codes. Modifying the worksheet's contents may damage the workbook's =FDS functionality.

Sheet VA-Disclaimer

Sheet Disclaimer

Sheet IS
A1: 1 | B1: =A1+1 -> 2 | CB1: 12-month Target | CC1: 22.5 | CE1: FCF Yield | CG1: =(CF!BZ27+CF!BZ33)/(IS!CC2*IS!BZ78) -> #NAME? | DP1: =SUM(DO327:DP327)/SUM(DJ327:DK327)-1 -> 0.02014977 | DW1: =DW12 -> 19978 | DY1: =DY11 -> 19673 | EI1: =425/2 -> 212.5
CB2: Current Price | CC2: =_xll.FDS("INTC","p") -> #NAME? | CE2: Dividend Yield = | CG2: =4*CA75/CC2 -> #NAME? | CX2: =SUM(CW12:CX12)/CY12 -> 0.53073796 | DC2: =SUM(DB12:DC12)/DD12 -> 0.54049692 | DH2: =SUM(DG12:DH12)/DI12 -> 0.5290228 | DM2: =SUM(DL12:DM12)/DN12 -> 0.53381888 | DP2: =100*10*0.25 -> 250 | DR2: =SUM(DQ12:DR12)/DS12 -> 0.54747447 | DW2: =SUM(DV12:DW12)/DX12 -> 0.4920056 | DY2: =DY12 -> 18566 | DZ2: =DZ12 -> 18533 | EA2: =EA12 -> 18087 | EB2: =EB12 -> 19532 | EC2: =EC12 -> 74718 | ED2: =ED12 -> 18353 | EE2: =EE12 -> 15321 | EF2: =EF12 -> 15338 | EG2: =SUM(EF12:EG12)/EH12 -> 0.46594982 | EH2: =EH12 -> 63054 | EI2: =EI12 -> #ERROR! | EJ2: =1-EL2 -> #ERROR! | EL2: =SUM(EK12:EL12)/EM12 -> #ERROR! | EM2: =EM12 -> #ERROR! | EQ2: =SUM(EP12:EQ12)/ER12 -> #ERROR! | ER2: =ER12 -> #ERROR! | EV2: =SUM(EU12:EV12)/EW12 -> #ERROR! | EW2: =EW12 -> #ERROR! | FA2: =SUM(EZ12:FA12)/FB12 -> #ERROR! | FB2: =FB12 -> #ERROR! | FF2: =SUM(FE12:FF12)/FG12 -> #ERROR! | FG2: =FG12 -> #ERROR!
A3: 1 | B3: =A3+1 -> 2 | C3: =B3+1 -> 3 | D3: =C3+1 -> 4 | E3: =D3+1 -> 5 | F3: =E3+1 -> 6 | G3: =F3+1 -> 7 | H3: =G3+1 -> 8 | I3: =H3+1 -> 9 | ... FG3: =FF3+1 -> 163
B4: Intel Corporation | DI4: 3yr | DJ4: =AVERAGE(DJ13,DE13,CZ13) -> -0.076292848 | DK4: =AVERAGE(DK13,DF13,DA13) -> 0.011373578 | DL4: =AVERAGE(DL13,DG13,DB13) -> 0.12984493 | DM4: =AVERAGE(DM13,DH13,DC13) -> 0.022449254 | DO4: =AVERAGE(DO13,DJ13,DE13) -> -0.097798054 | DP4: =AVERAGE(DP13,DK13,DF13) -> 0.027061407 | DQ4: =AVERAGE(DQ13,DL13,DG13) -> 0.12877399 | DR4: =AVERAGE(DR13,DM13,DH13) -> 0.027558073 | DS4: =DS12/DN12-1 -> 0.015766147 | DT4: =AVERAGE(DT13,DO13,DJ13) -> -0.071958283 | DU4: =AVERAGE(DU13,DP13,DK13) -> 0.026123727 | DV4: =AVERAGE(DV13,DQ13,DL13) -> 0.07390898 | DW4: =AVERAGE(DW13,DR13,DM13) -> 0.038808142 | DX4: =DX12/DS12-1 -> 0.082012089 | DY4: =AVERAGE(DY13,DT13,DO13) -> -0.076224739 | DZ4: =AVERAGE(DZ13,DU13,DP13) -> 0.0069412631 | EA4: =AVERAGE(EA13,DV13,DQ13) -> 0.022633706 | EB4: =AVERAGE(EB13,DW13,DR13) -> 0.074240371 | EC4: =EC12/DX12-1 -> -0.040440752 | ED4: =AVERAGE(ED13,DY13,DT13) -> -0.049964405 | EE4: =AVERAGE(EE13,DZ13,DU13) -> -0.057341805 | EF4: =AVERAGE(EF13,EA13,DV13) -> -0.031222424 | EG4: =AVERAGE(EG13,EB13,DW13) -> 0.028374839 | EH4: =EH12/EC12-1 -> -0.15610696 | EI4: =AVERAGE(EI13,ED13,DY13) -> #ERROR! | EJ4: =AVERAGE(EJ13,EE13,DZ13) -> #ERROR! | EK4: =AVERAGE(EK13,EF13,EA13) -> #ERROR! | EL4: =AVERAGE(EL13,EG13,EB13) -> #ERROR! | EM4: =EM12/EH12-1 -> #ERROR! | EN4: =AVERAGE(EN13,EI13,ED13) -> #ERROR! | EO4: =AVERAGE(EO13,EJ13,EE13) -> #ERROR! | EP4: =AVERAGE(EP13,EK13,EF13) -> #ERROR! | EQ4: =AVERAGE(EQ13,EL13,EG13) -> #ERROR! | ER4: =ER12/EM12-1 -> #ERROR! | ES4: =AVERAGE(ES13,EN13,EI13) -> #ERROR! | ET4: =AVERAGE(ET13,EO13,EJ13) -> #ERROR! | EU4: =AVERAGE(EU13,EP13,EK13) -> #ERROR! | EV4: =AVERAGE(EV13,EQ13,EL13) -> #ERROR! | EW4: =EW12/ER12-1 -> #ERROR! | EX4: =AVERAGE(EX13,ES13,EN13) -> #ERROR! | EY4: =AVERAGE(EY13,ET13,EO13) -> #ERROR! | EZ4: =AVERAGE(EZ13,EU13,EP13) -> #ERROR! | FA4: =AVERAGE(FA13,EV13,EQ13) -> #ERROR! | FB4: =FB12/EW12-1 -> #ERROR! | FC4: =AVERAGE(FC13,EX13,ES13) -> #ERROR! | FD4: =AVERAGE(FD13,EY13,ET13) -> #ERROR! | FE4: =AVERAGE(FE13,EZ13,EU13) -> #ERROR! | FF4: =AVERAGE(FF13,FA13,EV13) -> #ERROR! | FG4: =FG12/FB12-1 -> #ERROR!
B5: Income Statement | Q5: =Q19/N19-1 -> 0.11703634 | V5: =V19/S19-1 -> -0.0071360609 | AA5: =AA19/X19-1 -> 0.11579539 | AF5: =AF19/AC19-1 -> 0.031066823 | AK5: =AK19/AH19-1 -> 0.036408978 | AP5: =AP19/AM19-1 -> -0.030379747 | BB5: =(BB19-CF!BB20)/BB12 -> 0.35145414 | BC5: =(BC19-CF!BC20)/BC12 -> 0.41952803 | BD5: =(BD19-CF!BD20)/BD12 -> 0.38402563 | BE5: =(BE19-CF!BE20)/BE12 -> 0.36207964 | BG5: =(BG19-CF!BG20)/BG12 -> 0.36534117 | BH5: =(BH19-CF!BH20)/BH12 -> 0.36463134 | BI5: =(BI19-CF!BI20)/BI12 -> 0.30336967 | BJ5: =(BJ19-CF!BJ20)/BJ12 -> 0.31357356 | DI5: 5yr | DN5: =DN362/DN12 -> 0.060792118 | DO5: =AVERAGE(DJ13,DE13,CZ13,CU13,DO13) -> -0.099961311 | DP5: =AVERAGE(DK13,DF13,DA13,CV13,DP13) -> 0.018831434 | DQ5: =AVERAGE(DL13,DG13,DB13,CW13,DQ13) -> 0.12969227 | DR5: =AVERAGE(DM13,DH13,DC13,CX13,DR13) -> 0.030297756 | DS5: =DS362/DS12 -> 0.060612798 | DT5: =AVERAGE(DO13,DJ13,DE13,CZ13,DT13) -> -0.077375003 | DU5: =AVERAGE(DP13,DK13,DF13,DA13,DU13) -> 0.011344393 | DV5: =AVERAGE(DQ13,DL13,DG13,DB13,DV13) -> 0.096300216 | DW5: =AVERAGE(DR13,DM13,DH13,DC13,DW13) -> 0.042035448 | DX5: =DX362/DX12 -> 0.068809637 | DY5: =AVERAGE(DT13,DO13,DJ13,DE13,DY13) -> -0.076584979 | DZ5: =AVERAGE(DU13,DP13,DK13,DF13,DZ13) -> 0.014872681 | EA5: =AVERAGE(DV13,DQ13,DL13,DG13,EA13) -> 0.058309023 | EB5: =AVERAGE(DW13,DR13,DM13,DH13,EB13) -> 0.050458952 | EC5: =EC362/EC12 -> 0.057630022 | ED5: =AVERAGE(DY13,DT13,DO13,DJ13,ED13) -> -0.069383016 | EE5: =AVERAGE(DZ13,DU13,DP13,DK13,EE13) -> -0.017722172 | EF5: =AVERAGE(EA13,DV13,DQ13,DL13,EF13) -> 0.039754269 | EG5: =AVERAGE(EB13,DW13,DR13,DM13,EG13) -> 0.022364008 | EH5: =EH362/EH12 -> 0 | EI5: =AVERAGE(ED13,DY13,DT13,DO13,EI13) -> #ERROR! | EJ5: =AVERAGE(EE13,DZ13,DU13,DP13,EJ13) -> #ERROR! | EK5: =AVERAGE(EF13,EA13,DV13,DQ13,EK13) -> #ERROR! | EL5: =AVERAGE(EG13,EB13,DW13,DR13,EL13) -> #ERROR! | EM5: =EM362/EM12 -> #ERROR! | EN5: =AVERAGE(EI13,ED13,DY13,DT13,EN13) -> #ERROR! | EO5: =AVERAGE(EJ13,EE13,DZ13,DU13,EO13) -> #ERROR! | EP5: =AVERAGE(EK13,EF13,EA13,DV13,EP13) -> #ERROR! | EQ5: =AVERAGE(EL13,EG13,EB13,DW13,EQ13) -> #ERROR! | ER5: =ER362/ER12 -> #ERROR! | ES5: =AVERAGE(EN13,EI13,ED13,DY13,ES13) -> #ERROR! | ET5: =AVERAGE(EO13,EJ13,EE13,DZ13,ET13) -> #ERROR! | EU5: =AVERAGE(EP13,EK13,EF13,EA13,EU13) -> #ERROR! | EV5: =AVERAGE(EQ13,EL13,EG13,EB13,EV13) -> #ERROR! | EW5: =EW362/EW12 -> #ERROR! | EX5: =AVERAGE(ES13,EN13,EI13,ED13,EX13) -> #ERROR! | EY5: =AVERAGE(ET13,EO13,EJ13,EE13,EY13) -> #ERROR! | EZ5: =AVERAGE(EU13,EP13,EK13,EF13,EZ13) -> #ERROR! | FA5: =AVERAGE(EV13,EQ13,EL13,EG13,FA13) -> #ERROR! | FB5: =FB362/FB12 -> #ERROR! | FC5: =AVERAGE(EX13,ES13,EN13,EI13,FC13) -> #ERROR! | FD5: =AVERAGE(EY13,ET13,EO13,EJ13,FD13) -> #ERROR! | FE5: =AVERAGE(EZ13,EU13,EP13,EK13,FE13) -> #ERROR! | FF5: =AVERAGE(FA13,EV13,EQ13,EL13,FF13) -> #ERROR! | FG5: =FG362/FG12 -> #ERROR!
B6: FY ends December 31 | D6: ="FY"&YEAR(G7) -> FY1996 | I6: ="FY"&YEAR(L7) -> FY1997 | N6: ="FY"&YEAR(Q7) -> FY1998 | S6: ="FY"&YEAR(V7) -> FY1999 | X6: ="FY"&YEAR(AA7) -> FY2000 | AC6: ="FY"&YEAR(AF7) -> FY2001 | AH6: ="FY"&YEAR(AK7) -> FY2002 | AM6: ="FY"&YEAR(AP7) -> FY2003 | AR6: ="FY"&YEAR(AU7) -> FY2004 | AW6: ="FY"&YEAR(AZ7) -> FY2005 | BB6: ="FY"&YEAR(BE7) -> FY2006 | BG6: ="FY"&YEAR(BJ7) -> FY2007 | BL6: ="FY"&YEAR(BO7) -> FY2008 | BQ6: ="FY"&YEAR(BT7) -> FY2009 | BV6: ="FY"&YEAR(BY7) -> FY2010 | CA6: ="FY"&YEAR(CD7) -> FY2011 | CF6: ="FY"&YEAR(CI7) -> FY2012 | CK6: ="FY"&YEAR(CN7) -> FY2013 | CP6: ="FY"&YEAR(CS7) -> FY2014 | CU6: ="FY"&YEAR(CX7) -> FY2015 | CZ6: ="FY"&YEAR(DC7) -> FY2016 | DE6: ="FY"&YEAR(DH7) -> FY2017 | DJ6: ="FY"&YEAR(DM7) -> FY2018 | DO6: ="FY"&YEAR(DR7) -> FY2019 | DT6: ="FY"&YEAR(DW7) -> FY2020 | DY6: ="FY"&YEAR(EB7) -> FY2021 | ED6: ="FY"&YEAR(EG7) -> FY2022 | EI6: ="FY"&YEAR(EL7) -> FY2023 | EN6: ="FY"&YEAR(EQ7) -> FY2024 | ES6: ="FY"&YEAR(EV7) -> FY2025 | EX6: ="FY"&YEAR(FA7) -> FY2026 | FC6: ="FY"&YEAR(FF7) -> FY2027
B7: ($ in millions, except EPS) | D7: 35154 | E7: 35246 | F7: 35338 | G7: 35430 | H7: =YEAR(G7)&IF(YEAR(G7)>YEAR(TODAY()),"E",IF(AND(YEAR(G7)=YEAR(TODAY()),MONTH(G7)>MONTH(TODAY())),"E",IF(AND(YEAR(G7)=YEAR(TODAY()),MONTH(G7)=MONTH(TODAY()),DAY(G7)<30),"E",""))) -> 1996 | I7: 35519 | J7: 35611 | K7: 35703 | L7: 35795 | M7: =YEAR(L7)&IF(YEAR(L7)>YEAR(TODAY()),"E",IF(AND(YEAR(L7)=YEAR(TODAY()),MONTH(L7)>MONTH(TODAY())),"E",IF(AND(YEAR(L7)=YEAR(TODAY()),MONTH(L7)=MONTH(TODAY()),DAY(L7)<30),"E",""))) -> 1997 | N7: 35884 | O7: 35976 | P7: 36068 | Q7: 36160 | R7: =YEAR(Q7)&IF(YEAR(Q7)>YEAR(TODAY()),"E",IF(AND(YEAR(Q7)=YEAR(TODAY()),MONTH(Q7)>MONTH(TODAY())),"E",IF(AND(YEAR(Q7)=YEAR(TODAY()),MONTH(Q7)=MONTH(TODAY()),DAY(Q7)<30),"E",""))) -> 1998 | S7: =N7+365 -> 36249 | T7: =O7+365 -> 36341 | U7: =P7+365 -> 36433 | V7: =Q7+365 -> 36525 | W7: =YEAR(V7)&IF(YEAR(V7)>YEAR(TODAY()),"E",IF(AND(YEAR(V7)=YEAR(TODAY()),MONTH(V7)>MONTH(TODAY())),"E",IF(AND(YEAR(V7)=YEAR(TODAY()),MONTH(V7)=MONTH(TODAY()),DAY(V7)<30),"E",""))) -> 1999 | X7: =S7+365 -> 36614 | Y7: =T7+365 -> 36706 | Z7: =U7+365 -> 36798 | AA7: =V7+365 -> 36890 | AB7: =YEAR(AA7)&IF(YEAR(AA7)>YEAR(TODAY()),"E",IF(AND(YEAR(AA7)=YEAR(TODAY()),MONTH(AA7)>MONTH(TODAY())),"E",IF(AND(YEAR(AA7)=YEAR(TODAY()),MONTH(AA7)=MONTH(TODAY()),DAY(AA7)<30),"E",""))) -> 2000 | AC7: =X7+365 -> 36979 | AD7: =Y7+365 -> 37071 | AE7: =Z7+365 -> 37163 | AF7: =AA7+365 -> 37255 | AG7: =YEAR(AF7)&IF(YEAR(AF7)>YEAR(TODAY()),"E",IF(AND(YEAR(AF7)=YEAR(TODAY()),MONTH(AF7)>MONTH(TODAY())),"E",IF(AND(YEAR(AF7)=YEAR(TODAY()),MONTH(AF7)=MONTH(TODAY()),DAY(AF7)<30),"E",""))) -> 2001 | AH7: =AC7+365 -> 37344 | AI7: =AD7+365 -> 37436 | AJ7: =AE7+365 -> 37528 | AK7: 37619 | AL7: =YEAR(AK7)&IF(YEAR(AK7)>YEAR(TODAY()),"E",IF(AND(YEAR(AK7)=YEAR(TODAY()),MONTH(AK7)>MONTH(TODAY())),"E",IF(AND(YEAR(AK7)=YEAR(TODAY()),MONTH(AK7)=MONTH(TODAY()),DAY(AK7)<30),"E",""))) -> 2002 | AM7: =AH7+365 -> 37709 | AN7: =AI7+365 -> 37801 | AO7: =AJ7+365 -> 37893 | AP7: =AK7+365 -> 37984 | AQ7: =YEAR(AP7)&IF(YEAR(AP7)>YEAR(TODAY()),"E",IF(AND(YEAR(AP7)=YEAR(TODAY()),MONTH(AP7)>MONTH(TODAY())),"E",IF(AND(YEAR(AP7)=YEAR(TODAY()),MONTH(AP7)=MONTH(TODAY()),DAY(AP7)<30),"E",""))) -> 2003 | AR7: =AM7+365 -> 38074 | AS7: =AN7+365 -> 38166 | AT7: =AO7+365 -> 38258 | AU7: =AP7+365 -> 38349 | AV7: =YEAR(AU7)&IF(YEAR(AU7)>YEAR(TODAY()),"E",IF(AND(YEAR(AU7)=YEAR(TODAY()),MONTH(AU7)>MONTH(TODAY())),"E",IF(AND(YEAR(AU7)=YEAR(TODAY()),MONTH(AU7)=MONTH(TODAY()),DAY(AU7)<30),"E",""))) -> 2004 | AW7: =AR7+365 -> 38439 | AX7: =AS7+365 -> 38531 | AY7: =AT7+365 -> 38623 | AZ7: =AU7+365 -> 38714 | BA7: =YEAR(AZ7)&IF(YEAR(AZ7)>YEAR(TODAY()),"E",IF(AND(YEAR(AZ7)=YEAR(TODAY()),MONTH(AZ7)>MONTH(TODAY())),"E",IF(AND(YEAR(AZ7)=YEAR(TODAY()),MONTH(AZ7)=MONTH(TODAY()),DAY(AZ7)<30),"E",""))) -> 2005 | BB7: =AW7+365 -> 38804 | BC7: =AX7+365 -> 38896 | BD7: =AY7+365 -> 38988 | BE7: =AZ7+365 -> 39079 | BF7: =YEAR(BE7)&IF(YEAR(BE7)>YEAR(TODAY()),"E",IF(AND(YEAR(BE7)=YEAR(TODAY()),MONTH(BE7)>MONTH(TODAY())),"E",IF(AND(YEAR(BE7)=YEAR(TODAY()),MONTH(BE7)=MONTH(TODAY()),DAY(BE7)<30),"E",""))) -> 2006 | BG7: =BB7+365 -> 39169 | BH7: =BC7+365 -> 39261 | BI7: =BD7+365 -> 39353 | BJ7: =BE7+365 -> 39444 | BK7: =YEAR(BJ7)&IF(YEAR(BJ7)>YEAR(TODAY()),"E",IF(AND(YEAR(BJ7)=YEAR(TODAY()),MONTH(BJ7)>MONTH(TODAY())),"E",IF(AND(YEAR(BJ7)=YEAR(TODAY()),MONTH(BJ7)=MONTH(TODAY()),DAY(BJ7)<30),"E",""))) -> 2007 | BL7: =BG7+365 -> 39534 | BM7: =BH7+365 -> 39626 | BN7: =BI7+365 -> 39718 | BO7: =BJ7+365 -> 39809 | BP7: =YEAR(BO7)&IF(YEAR(BO7)>YEAR(TODAY()),"E",IF(AND(YEAR(BO7)=YEAR(TODAY()),MONTH(BO7)>MONTH(TODAY())),"E",IF(AND(YEAR(BO7)=YEAR(TODAY()),MONTH(BO7)=MONTH(TODAY()),DAY(BO7)<30),"E",""))) -> 2008 | BQ7: =BL7+365 -> 39899 | BR7: =BM7+365 -> 39991 | BS7: =BN7+365 -> 40083 | BT7: =BO7+365 -> 40174 | BU7: =YEAR(BT7)&IF(YEAR(BT7)>YEAR(TODAY()),"E",IF(AND(YEAR(BT7)=YEAR(TODAY()),MONTH(BT7)>MONTH(TODAY())),"E",IF(AND(YEAR(BT7)=YEAR(TODAY()),MONTH(BT7)=MONTH(TODAY()),DAY(BT7)<30),"E",""))) -> 2009 | BV7: =BQ7+365 -> 40264 | BW7: =BR7+365 -> 40356 | BX7: =BS7+365 -> 40448 | BY7: =BT7+365 -> 40539 | BZ7: =YEAR(BY7)&IF(YEAR(BY7)>YEAR(TODAY()),"E",IF(AND(YEAR(BY7)=YEAR(TODAY()),MONTH(BY7)>MONTH(TODAY())),"E",IF(AND(YEAR(BY7)=YEAR(TODAY()),MONTH(BY7)=MONTH(TODAY()),DAY(BY7)<30),"E",""))) -> 2010 | CA7: =BV7+365 -> 40629 | CB7: =BW7+365 -> 40721 | CC7: =BX7+365 -> 40813 | CD7: =BY7+365 -> 40904 | CE7: =YEAR(CD7)&IF(YEAR(CD7)>YEAR(TODAY()),"E",IF(AND(YEAR(CD7)=YEAR(TODAY()),MONTH(CD7)>MONTH(TODAY())),"E",IF(AND(YEAR(CD7)=YEAR(TODAY()),MONTH(CD7)=MONTH(TODAY()),DAY(CD7)<30),"E",""))) -> 2011 | CF7: =CA7+365 -> 40994 | CG7: =CB7+365 -> 41086 | CH7: =CC7+365 -> 41178 | CI7: =CD7+365 -> 41269 | CJ7: =YEAR(CI7)&IF(YEAR(CI7)>YEAR(TODAY()),"E",IF(AND(YEAR(CI7)=YEAR(TODAY()),MONTH(CI7)>MONTH(TODAY())),"E",IF(AND(YEAR(CI7)=YEAR(TODAY()),MONTH(CI7)=MONTH(TODAY()),DAY(CI7)<30),"E",""))) -> 2012 | CK7: =CF7+365 -> 41359 | CL7: =CG7+365 -> 41451 | CM7: =CH7+365 -> 41543 | CN7: =CI7+365 -> 41634 | CO7: =YEAR(CN7)&IF(YEAR(CN7)>YEAR(TODAY()),"E",IF(AND(YEAR(CN7)=YEAR(TODAY()),MONTH(CN7)>MONTH(TODAY())),"E",IF(AND(YEAR(CN7)=YEAR(TODAY()),MONTH(CN7)=MONTH(TODAY()),DAY(CN7)<30),"E",""))) -> 2013 | CP7: =CK7+365 -> 41724 | CQ7: =CL7+365 -> 41816 | CR7: =CM7+365 -> 41908 | CS7: =CN7+365 -> 41999 | CT7: =YEAR(CS7)&IF(YEAR(CS7)>YEAR(TODAY()),"E",IF(AND(YEAR(CS7)=YEAR(TODAY()),MONTH(CS7)>MONTH(TODAY())),"E",IF(AND(YEAR(CS7)=YEAR(TODAY()),MONTH(CS7)=MONTH(TODAY()),DAY(CS7)<30),"E",""))) -> 2014 | CU7: =CP7+365 -> 42089 | CV7: =CQ7+365 -> 42181 | CW7: =CR7+365 -> 42273 | CX7: =CS7+365 -> 42364 | CY7: =YEAR(CX7)&IF(YEAR(CX7)>YEAR(TODAY()),"E",IF(AND(YEAR(CX7)=YEAR(TODAY()),MONTH(CX7)>MONTH(TODAY())),"E",IF(AND(YEAR(CX7)=YEAR(TODAY()),MONTH(CX7)=MONTH(TODAY()),DAY(CX7)<30),"E",""))) -> 2015 | CZ7: =CU7+365 -> 42454 | DA7: =CV7+365 -> 42546 | DB7: =CW7+365 -> 42638 | DC7: =CX7+365 -> 42729 | DD7: =YEAR(DC7)&IF(YEAR(DC7)>YEAR(TODAY()),"E",IF(AND(YEAR(DC7)=YEAR(TODAY()),MONTH(DC7)>MONTH(TODAY())),"E",IF(AND(YEAR(DC7)=YEAR(TODAY()),MONTH(DC7)=MONTH(TODAY()),DAY(DC7)<30),"E",""))) -> 2016 | DE7: =CZ7+365 -> 42819 | DF7: =DA7+365 -> 42911 | DG7: =DB7+365 -> 43003 | DH7: =DC7+365 -> 43094 | DI7: =YEAR(DH7)&IF(YEAR(DH7)>YEAR(TODAY()),"E",IF(AND(YEAR(DH7)=YEAR(TODAY()),MONTH(DH7)>MONTH(TODAY())),"E",IF(AND(YEAR(DH7)=YEAR(TODAY()),MONTH(DH7)=MONTH(TODAY()),DAY(DH7)<30),"E",""))) -> 2017 | DJ7: =DE7+365 -> 43184 | DK7: =DF7+365 -> 43276 | DL7: =DG7+365 -> 43368 | DM7: =DH7+365 -> 43459 | DN7: =YEAR(DM7)&IF(YEAR(DM7)>YEAR(TODAY()),"E",IF(AND(YEAR(DM7)=YEAR(TODAY()),MONTH(DM7)>MONTH(TODAY())),"E",IF(AND(YEAR(DM7)=YEAR(TODAY()),MONTH(DM7)=MONTH(TODAY()),DAY(DM7)<30),"E",""))) -> 2018 | DO7: =DJ7+365 -> 43549 | DP7: =DK7+365 -> 43641 | DQ7: =DL7+365 -> 43733 | DR7: =DM7+365 -> 43824 | DS7: =YEAR(DR7)&IF(YEAR(DR7)>YEAR(TODAY()),"E",IF(AND(YEAR(DR7)=YEAR(TODAY()),MONTH(DR7)>MONTH(TODAY())),"E",IF(AND(YEAR(DR7)=YEAR(TODAY()),MONTH(DR7)=MONTH(TODAY()),DAY(DR7)<30),"E",""))) -> 2019 | DT7: =DO7+365 -> 43914 | DU7: =DP7+365 -> 44006 | DV7: =DQ7+365 -> 44098 | DW7: =DR7+365 -> 44189 | DX7: =YEAR(DW7)&IF(YEAR(DW7)>YEAR(TODAY()),"E",IF(AND(YEAR(DW7)=YEAR(TODAY()),MONTH(DW7)>MONTH(TODAY())),"E",IF(AND(YEAR(DW7)=YEAR(TODAY()),MONTH(DW7)=MONTH(TODAY()),DAY(DW7)<30),"E",""))) -> 2020 | DY7: =DT7+365 -> 44279 | DZ7: =DU7+365 -> 44371 | EA7: =DV7+365 -> 44463 | EB7: =DW7+365 -> 44554 | EC7: =YEAR(EB7)&IF(YEAR(EB7)>YEAR(TODAY()),"E",IF(AND(YEAR(EB7)=YEAR(TODAY()),MONTH(EB7)>MONTH(TODAY())),"E",IF(AND(YEAR(EB7)=YEAR(TODAY()),MONTH(EB7)=MONTH(TODAY()),DAY(EB7)<30),"E",""))) -> 2021 | ED7: =DY7+365 -> 44644 | EE7: =DZ7+365 -> 44736 | EF7: =EA7+365 -> 44828 | EG7: =EB7+365 -> 44919 | EH7: =YEAR(EG7)&IF(YEAR(EG7)>YEAR(TODAY()),"E",IF(AND(YEAR(EG7)=YEAR(TODAY()),MONTH(EG7)>MONTH(TODAY())),"E",IF(AND(YEAR(EG7)=YEAR(TODAY()),MONTH(EG7)=MONTH(TODAY()),DAY(EG7)<30),"E",""))) -> 2022 | EI7: =ED7+365 -> 45009 | EJ7: =EE7+365 -> 45101 | EK7: =EF7+365 -> 45193 | EL7: =EG7+365 -> 45284 | EM7: =YEAR(EL7)&IF(YEAR(EL7)>YEAR(TODAY()),"E",IF(AND(YEAR(EL7)=YEAR(TODAY()),MONTH(EL7)>MONTH(TODAY())),"E",IF(AND(YEAR(EL7)=YEAR(TODAY()),MONTH(EL7)=MONTH(TODAY()),DAY(EL7)<30),"E",""))) -> 2023 | EN7: =EI7+365 -> 45374 | EO7: =EJ7+365 -> 45466 | EP7: =EK7+365 -> 45558 | EQ7: =EL7+365 -> 45649 | ER7: =YEAR(EQ7)&IF(YEAR(EQ7)>YEAR(TODAY()),"E",IF(AND(YEAR(EQ7)=YEAR(TODAY()),MONTH(EQ7)>MONTH(TODAY())),"E",IF(AND(YEAR(EQ7)=YEAR(TODAY()),MONTH(EQ7)=MONTH(TODAY()),DAY(EQ7)<30),"E",""))) -> 2024 | ES7: =EN7+365 -> 45739 | ET7: =EO7+365 -> 45831 | EU7: =EP7+365 -> 45923 | EV7: =EQ7+365 -> 46014 | EW7: =YEAR(EV7)&IF(YEAR(EV7)>YEAR(TODAY()),"E",IF(AND(YEAR(EV7)=YEAR(TODAY()),MONTH(EV7)>MONTH(TODAY())),"E",IF(AND(YEAR(EV7)=YEAR(TODAY()),MONTH(EV7)=MONTH(TODAY()),DAY(EV7)<30),"E",""))) -> 2025 | EX7: =ES7+365 -> 46104 | EY7: =ET7+365 -> 46196 | EZ7: =EU7+365 -> 46288 | FA7: =EV7+365 -> 46379 | FB7: =YEAR(FA7)&IF(YEAR(FA7)>YEAR(TODAY()),"E",IF(AND(YEAR(FA7)=YEAR(TODAY()),MONTH(FA7)>MONTH(TODAY())),"E",IF(AND(YEAR(FA7)=YEAR(TODAY()),MONTH(FA7)=MONTH(TODAY()),DAY(FA7)<30),"E",""))) -> 2026E | FC7: =EX7+365 -> 46469 | FD7: =EY7+365 -> 46561 | FE7: =EZ7+365 -> 46653 | FF7: =FA7+365 -> 46744 | FG7: =YEAR(FF7)&IF(YEAR(FF7)>YEAR(TODAY()),"E",IF(AND(YEAR(FF7)=YEAR(TODAY()),MONTH(FF7)>MONTH(TODAY())),"E",IF(AND(YEAR(FF7)=YEAR(TODAY()),MONTH(FF7)=MONTH(TODAY()),DAY(FF7)<30),"E",""))) -> 2027E
D8: ="Q1"&IF(YEAR(7:7)>YEAR(TODAY()),"E",IF(AND(YEAR(7:7)=YEAR(TODAY()),MONTH(7:7)>MONTH(TODAY())),"E",IF(AND(YEAR(7:7)=YEAR(TODAY()),MONTH(7:7)=MONTH(TODAY()),DAY(7:7)<30),"E","A"))) -> Q1A | E8: ="Q2"&IF(YEAR(7:7)>YEAR(TODAY()),"E",IF(AND(YEAR(7:7)=YEAR(TODAY()),MONTH(7:7)>MONTH(TODAY())),"E",IF(AND(YEAR(7:7)=YEAR(TODAY()),MONTH(7:7)=MONTH(TODAY()),DAY(7:7)<30),"E","A"))) -> Q2A | F8: ="Q3"&IF(YEAR(7:7)>YEAR(TODAY()),"E",IF(AND(YEAR(7:7)=YEAR(TODAY()),MONTH(7:7)>MONTH(TODAY())),"E",IF(AND(YEAR(7:7)=YEAR(TODAY()),MONTH(7:7)=MONTH(TODAY()),DAY(7:7)<30),"E","A"))) -> Q3A | G8: ="Q4"&IF(YEAR(7:7)>YEAR(TODAY()),"E",IF(AND(YEAR(7:7)=YEAR(TODAY()),MONTH(7:7)>MONTH(TODAY())),"E",IF(AND(YEAR(7:7)=YEAR(TODAY()),MONTH(7:7)=MONTH(TODAY()),DAY(7:7)<30),"E","A"))) -> Q4A | I8: ="Q1"&IF(YEAR(7:7)>YEAR(TODAY()),"E",IF(AND(YEAR(7:7)=YEAR(TODAY()),MONTH(7:7)>MONTH(TODAY())),"E",IF(AND(YEAR(7:7)=YEAR(TODAY()),MONTH(7:7)=MONTH(TODAY()),DAY(7:7)<30),"E","A"))) -> Q1A | J8: ="Q2"&IF(YEAR(7:7)>YEAR(TODAY()),"E",IF(AND(YEAR(7:7)=YEAR(TODAY()),MONTH(7:7)>MONTH(TODAY())),"E",IF(AND(YEAR(7:7)=YEAR(TODAY()),MONTH(7:7)=MONTH(TODAY()),DAY(7:7)<30),"E","A"))) -> Q2A | K8: ="Q3"&IF(YEAR(7:7)>YEAR(TODAY()),"E",IF(AND(YEAR(7:7)=YEAR(TODAY()),MONTH(7:7)>MONTH(TODAY())),"E",IF(AND(YEAR(7:7)=YEAR(TODAY()),MONTH(7:7)=MONTH(TODAY()),DAY(7:7)<30),"E","A"))) -> Q3A | L8: ="Q4"&IF(YEAR(7:7)>YEAR(TODAY()),"E",IF(AND(YEAR(7:7)=YEAR(TODAY()),MONTH(7:7)>MONTH(TODAY())),"E",IF(AND(YEAR(7:7)=YEAR(TODAY()),MONTH(7:7)=MONTH(TODAY()),DAY(7:7)<30),"E","A"))) -> Q4A | N8: ="Q1"&IF(YEAR(7:7)>YEAR(TODAY()),"E",IF(AND(YEAR(7:7)=YEAR(TODAY()),MONTH(7:7)>MONTH(TODAY())),"E",IF(AND(YEAR(7:7)=YEAR(TODAY()),MONTH(7:7)=MONTH(TODAY()),DAY(7:7)<30),"E","A"))) -> Q1A | O8: ="Q2"&IF(YEAR(7:7)>YEAR(TODAY()),"E",IF(AND(YEAR(7:7)=YEAR(TODAY()),MONTH(7:7)>MONTH(TODAY())),"E",IF(AND(YEAR(7:7)=YEAR(TODAY()),MONTH(7:7)=MONTH(TODAY()),DAY(7:7)<30),"E","A"))) -> Q2A | P8: ="Q3"&IF(YEAR(7:7)>YEAR(TODAY()),"E",IF(AND(YEAR(7:7)=YEAR(TODAY()),MONTH(7:7)>MONTH(TODAY())),"E",IF(AND(YEAR(7:7)=YEAR(TODAY()),MONTH(7:7)=MONTH(TODAY()),DAY(7:7)<30),"E","A"))) -> Q3A | Q8: ="Q4"&IF(YEAR(7:7)>YEAR(TODAY()),"E",IF(AND(YEAR(7:7)=YEAR(TODAY()),MONTH(7:7)>MONTH(TODAY())),"E",IF(AND(YEAR(7:7)=YEAR(TODAY()),MONTH(7:7)=MONTH(TODAY()),DAY(7:7)<30),"E","A"))) -> Q4A | S8: ="Q1"&IF(YEAR(7:7)>YEAR(TODAY()),"E",IF(AND(YEAR(7:7)=YEAR(TODAY()),MONTH(7:7)>MONTH(TODAY())),"E",IF(AND(YEAR(7:7)=YEAR(TODAY()),MONTH(7:7)=MONTH(TODAY()),DAY(7:7)<30),"E","A"))) -> Q1A | T8: ="Q2"&IF(YEAR(7:7)>YEAR(TODAY()),"E",IF(AND(YEAR(7:7)=YEAR(TODAY()),MONTH(7:7)>MONTH(TODAY())),"E",IF(AND(YEAR(7:7)=YEAR(TODAY()),MONTH(7:7)=MONTH(TODAY()),DAY(7:7)<30),"E","A"))) -> Q2A | U8: ="Q3"&IF(YEAR(7:7)>YEAR(TODAY()),"E",IF(AND(YEAR(7:7)=YEAR(TODAY()),MONTH(7:7)>MONTH(TODAY())),"E",IF(AND(YEAR(7:7)=YEAR(TODAY()),MONTH(7:7)=MONTH(TODAY()),DAY(7:7)<30),"E","A"))) -> Q3A | V8: ="Q4"&IF(YEAR(7:7)>YEAR(TODAY()),"E",IF(AND(YEAR(7:7)=YEAR(TODAY()),MONTH(7:7)>MONTH(TODAY())),"E",IF(AND(YEAR(7:7)=YEAR(TODAY()),MONTH(7:7)=MONTH(TODAY()),DAY(7:7)<30),"E","A"))) -> Q4A | X8: ="Q1"&IF(YEAR(7:7)>YEAR(TODAY()),"E",IF(AND(YEAR(7:7)=YEAR(TODAY()),MONTH(7:7)>MONTH(TODAY())),"E",IF(AND(YEAR(7:7)=YEAR(TODAY()),MONTH(7:7)=MONTH(TODAY()),DAY(7:7)<30),"E","A"))) -> Q1A | Y8: ="Q2"&IF(YEAR(7:7)>YEAR(TODAY()),"E",IF(AND(YEAR(7:7)=YEAR(TODAY()),MONTH(7:7)>MONTH(TODAY())),"E",IF(AND(YEAR(7:7)=YEAR(TODAY()),MONTH(7:7)=MONTH(TODAY()),DAY(7:7)<30),"E","A"))) -> Q2A | Z8: ="Q3"&IF(YEAR(7:7)>YEAR(TODAY()),"E",IF(AND(YEAR(7:7)=YEAR(TODAY()),MONTH(7:7)>MONTH(TODAY())),"E",IF(AND(YEAR(7:7)=YEAR(TODAY()),MONTH(7:7)=MONTH(TODAY()),DAY(7:7)<30),"E","A"))) -> Q3A | AA8: ="Q4"&IF(YEAR(7:7)>YEAR(TODAY()),"E",IF(AND(YEAR(7:7)=YEAR(TODAY()),MONTH(7:7)>MONTH(TODAY())),"E",IF(AND(YEAR(7:7)=YEAR(TODAY()),MONTH(7:7)=MONTH(TODAY()),DAY(7:7)<30),"E","A"))) -> Q4A | AC8: ="Q1"&IF(YEAR(7:7)>YEAR(TODAY()),"E",IF(AND(YEAR(7:7)=YEAR(TODAY()),MONTH(7:7)>MONTH(TODAY())),"E",IF(AND(YEAR(7:7)=YEAR(TODAY()),MONTH(7:7)=MONTH(TODAY()),DAY(7:7)<30),"E","A"))) -> Q1A | AD8: ="Q2"&IF(YEAR(7:7)>YEAR(TODAY()),"E",IF(AND(YEAR(7:7)=YEAR(TODAY()),MONTH(7:7)>MONTH(TODAY())),"E",IF(AND(YEAR(7:7)=YEAR(TODAY()),MONTH(7:7)=MONTH(TODAY()),DAY(7:7)<30),"E","A"))) -> Q2A | AE8: ="Q3"&IF(YEAR(7:7)>YEAR(TODAY()),"E",IF(AND(YEAR(7:7)=YEAR(TODAY()),MONTH(7:7)>MONTH(TODAY())),"E",IF(AND(YEAR(7:7)=YEAR(TODAY()),MONTH(7:7)=MONTH(TODAY()),DAY(7:7)<30),"E","A"))) -> Q3A | AF8: ="Q4"&IF(YEAR(7:7)>YEAR(TODAY()),"E",IF(AND(YEAR(7:7)=YEAR(TODAY()),MONTH(7:7)>MONTH(TODAY())),"E",IF(AND(YEAR(7:7)=YEAR(TODAY()),MONTH(7:7)=MONTH(TODAY()),DAY(7:7)<30),"E","A"))) -> Q4A | AH8: ="Q1"&IF(YEAR(7:7)>YEAR(TODAY()),"E",IF(AND(YEAR(7:7)=YEAR(TODAY()),MONTH(7:7)>MONTH(TODAY())),"E",IF(AND(YEAR(7:7)=YEAR(TODAY()),MONTH(7:7)=MONTH(TODAY()),DAY(7:7)<30),"E","A"))) -> Q1A | AI8: ="Q2"&IF(YEAR(7:7)>YEAR(TODAY()),"E",IF(AND(YEAR(7:7)=YEAR(TODAY()),MONTH(7:7)>MONTH(TODAY())),"E",IF(AND(YEAR(7:7)=YEAR(TODAY()),MONTH(7:7)=MONTH(TODAY()),DAY(7:7)<30),"E","A"))) -> Q2A | AJ8: ="Q3"&IF(YEAR(7:7)>YEAR(TODAY()),"E",IF(AND(YEAR(7:7)=YEAR(TODAY()),MONTH(7:7)>MONTH(TODAY())),"E",IF(AND(YEAR(7:7)=YEAR(TODAY()),MONTH(7:7)=MONTH(TODAY()),DAY(7:7)<30),"E","A"))) -> Q3A | AK8: ="Q4"&IF(YEAR(7:7)>YEAR(TODAY()),"E",IF(AND(YEAR(7:7)=YEAR(TODAY()),MONTH(7:7)>MONTH(TODAY())),"E",IF(AND(YEAR(7:7)=YEAR(TODAY()),MONTH(7:7)=MONTH(TODAY()),DAY(7:7)<30),"E","A"))) -> Q4A | AM8: ="Q1"&IF(YEAR(7:7)>YEAR(TODAY()),"E",IF(AND(YEAR(7:7)=YEAR(TODAY()),MONTH(7:7)>MONTH(TODAY())),"E",IF(AND(YEAR(7:7)=YEAR(TODAY()),MONTH(7:7)=MONTH(TODAY()),DAY(7:7)<30),"A","A"))) -> Q1A | AN8: ="Q2"&IF(YEAR(7:7)>YEAR(TODAY()),"E",IF(AND(YEAR(7:7)=YEAR(TODAY()),MONTH(7:7)>MONTH(TODAY())),"E",IF(AND(YEAR(7:7)=YEAR(TODAY()),MONTH(7:7)=MONTH(TODAY()),DAY(7:7)<30),"E","A"))) -> Q2A | AO8: ="Q3"&IF(YEAR(7:7)>YEAR(TODAY()),"E",IF(AND(YEAR(7:7)=YEAR(TODAY()),MONTH(7:7)>MONTH(TODAY())),"E",IF(AND(YEAR(7:7)=YEAR(TODAY()),MONTH(7:7)=MONTH(TODAY()),DAY(7:7)<30),"E","A"))) -> Q3A | AP8: ="Q4"&IF(YEAR(7:7)>YEAR(TODAY()),"E",IF(AND(YEAR(7:7)=YEAR(TODAY()),MONTH(7:7)>MONTH(TODAY())),"E",IF(AND(YEAR(7:7)=YEAR(TODAY()),MONTH(7:7)=MONTH(TODAY()),DAY(7:7)<30),"E","A"))) -> Q4A | AR8: ="Q1"&IF(YEAR(7:7)>YEAR(TODAY()),"E",IF(AND(YEAR(7:7)=YEAR(TODAY()),MONTH(7:7)>MONTH(TODAY())),"E",IF(AND(YEAR(7:7)=YEAR(TODAY()),MONTH(7:7)=MONTH(TODAY()),DAY(7:7)<30),"E","A"))) -> Q1A | AS8: ="Q2"&IF(YEAR(7:7)>YEAR(TODAY()),"E",IF(AND(YEAR(7:7)=YEAR(TODAY()),MONTH(7:7)>MONTH(TODAY())),"E",IF(AND(YEAR(7:7)=YEAR(TODAY()),MONTH(7:7)=MONTH(TODAY()),DAY(7:7)<30),"E","A"))) -> Q2A | AT8: ="Q3"&IF(YEAR(7:7)>YEAR(TODAY()),"E",IF(AND(YEAR(7:7)=YEAR(TODAY()),MONTH(7:7)>MONTH(TODAY())),"E",IF(AND(YEAR(7:7)=YEAR(TODAY()),MONTH(7:7)=MONTH(TODAY()),DAY(7:7)<30),"E","A"))) -> Q3A | AU8: ="Q4"&IF(YEAR(7:7)>YEAR(TODAY()),"E",IF(AND(YEAR(7:7)=YEAR(TODAY()),MONTH(7:7)>MONTH(TODAY())),"E",IF(AND(YEAR(7:7)=YEAR(TODAY()),MONTH(7:7)=MONTH(TODAY()),DAY(7:7)<30),"E","A"))) -> Q4A | AW8: ="Q1"&IF(YEAR(7:7)>YEAR(TODAY()),"E",IF(AND(YEAR(7:7)=YEAR(TODAY()),MONTH(7:7)>MONTH(TODAY())),"E",IF(AND(YEAR(7:7)=YEAR(TODAY()),MONTH(7:7)=MONTH(TODAY()),DAY(7:7)<30),"E","A"))) -> Q1A | AX8: ="Q2"&IF(YEAR(7:7)>YEAR(TODAY()),"E",IF(AND(YEAR(7:7)=YEAR(TODAY()),MONTH(7:7)>MONTH(TODAY())),"E",IF(AND(YEAR(7:7)=YEAR(TODAY()),MONTH(7:7)=MONTH(TODAY()),DAY(7:7)<30),"E","A"))) -> Q2A | AY8: ="Q3"&IF(YEAR(7:7)>YEAR(TODAY()),"E",IF(AND(YEAR(7:7)=YEAR(TODAY()),MONTH(7:7)>MONTH(TODAY())),"E",IF(AND(YEAR(7:7)=YEAR(TODAY()),MONTH(7:7)=MONTH(TODAY()),DAY(7:7)<30),"E","A"))) -> Q3A | AZ8: ="Q4"&IF(YEAR(7:7)>YEAR(TODAY()),"E",IF(AND(YEAR(7:7)=YEAR(TODAY()),MONTH(7:7)>MONTH(TODAY())),"E",IF(AND(YEAR(7:7)=YEAR(TODAY()),MONTH(7:7)=MONTH(TODAY()),DAY(7:7)<30),"E","A"))) -> Q4A | BB8: ="Q1"&IF(YEAR(7:7)>YEAR(TODAY()),"E",IF(AND(YEAR(7:7)=YEAR(TODAY()),MONTH(7:7)>MONTH(TODAY())),"E",IF(AND(YEAR(7:7)=YEAR(TODAY()),MONTH(7:7)=MONTH(TODAY()),DAY(7:7)<30),"E","A"))) -> Q1A | BC8: ="Q2"&IF(YEAR(7:7)>YEAR(TODAY()),"E",IF(AND(YEAR(7:7)=YEAR(TODAY()),MONTH(7:7)>MONTH(TODAY())),"E",IF(AND(YEAR(7:7)=YEAR(TODAY()),MONTH(7:7)=MONTH(TODAY()),DAY(7:7)<30),"E","A"))) -> Q2A | BD8: ="Q3"&IF(YEAR(7:7)>YEAR(TODAY()),"E",IF(AND(YEAR(7:7)=YEAR(TODAY()),MONTH(7:7)>MONTH(TODAY())),"E",IF(AND(YEAR(7:7)=YEAR(TODAY()),MONTH(7:7)=MONTH(TODAY()),DAY(7:7)<30),"E","A"))) -> Q3A | BE8: ="Q4"&IF(YEAR(7:7)>YEAR(TODAY()),"E",IF(AND(YEAR(7:7)=YEAR(TODAY()),MONTH(7:7)>MONTH(TODAY())),"E",IF(AND(YEAR(7:7)=YEAR(TODAY()),MONTH(7:7)=MONTH(TODAY()),DAY(7:7)<30),"E","A"))) -> Q4A | BG8: ="Q1"&IF(YEAR(7:7)>YEAR(TODAY()),"E",IF(AND(YEAR(7:7)=YEAR(TODAY()),MONTH(7:7)>MONTH(TODAY())),"E",IF(AND(YEAR(7:7)=YEAR(TODAY()),MONTH(7:7)=MONTH(TODAY()),DAY(7:7)<30),"E","A"))) -> Q1A | BH8: ="Q2"&IF(YEAR(7:7)>YEAR(TODAY()),"E",IF(AND(YEAR(7:7)=YEAR(TODAY()),MONTH(7:7)>MONTH(TODAY())),"E",IF(AND(YEAR(7:7)=YEAR(TODAY()),MONTH(7:7)=MONTH(TODAY()),DAY(7:7)<30),"E","A"))) -> Q2A | BI8: ="Q3"&IF(YEAR(7:7)>YEAR(TODAY()),"E",IF(AND(YEAR(7:7)=YEAR(TODAY()),MONTH(7:7)>MONTH(TODAY())),"E",IF(AND(YEAR(7:7)=YEAR(TODAY()),MONTH(7:7)=MONTH(TODAY()),DAY(7:7)<30),"E","A"))) -> Q3A | BJ8: ="Q4"&IF(YEAR(7:7)>YEAR(TODAY()),"E",IF(AND(YEAR(7:7)=YEAR(TODAY()),MONTH(7:7)>MONTH(TODAY())),"E",IF(AND(YEAR(7:7)=YEAR(TODAY()),MONTH(7:7)=MONTH(TODAY()),DAY(7:7)<30),"E","A"))) -> Q4A | BL8: ="Q1"&IF(YEAR(7:7)>YEAR(TODAY()),"E",IF(AND(YEAR(7:7)=YEAR(TODAY()),MONTH(7:7)>MONTH(TODAY())),"E",IF(AND(YEAR(7:7)=YEAR(TODAY()),MONTH(7:7)=MONTH(TODAY()),DAY(7:7)<30),"E","A"))) -> Q1A | BM8: ="Q2"&IF(YEAR(7:7)>YEAR(TODAY()),"E",IF(AND(YEAR(7:7)=YEAR(TODAY()),MONTH(7:7)>MONTH(TODAY())),"E",IF(AND(YEAR(7:7)=YEAR(TODAY()),MONTH(7:7)=MONTH(TODAY()),DAY(7:7)<30),"E","A"))) -> Q2A | BN8: ="Q3"&IF(YEAR(7:7)>YEAR(TODAY()),"E",IF(AND(YEAR(7:7)=YEAR(TODAY()),MONTH(7:7)>MONTH(TODAY())),"E",IF(AND(YEAR(7:7)=YEAR(TODAY()),MONTH(7:7)=MONTH(TODAY()),DAY(7:7)<30),"E","A"))) -> Q3A | BO8: ="Q4"&IF(YEAR(7:7)>YEAR(TODAY()),"E",IF(AND(YEAR(7:7)=YEAR(TODAY()),MONTH(7:7)>MONTH(TODAY())),"E",IF(AND(YEAR(7:7)=YEAR(TODAY()),MONTH(7:7)=MONTH(TODAY()),DAY(7:7)<30),"E","A"))) -> Q4A | BQ8: ="Q1"&IF(YEAR(7:7)>YEAR(TODAY()),"E",IF(AND(YEAR(7:7)=YEAR(TODAY()),MONTH(7:7)>MONTH(TODAY())),"E",IF(AND(YEAR(7:7)=YEAR(TODAY()),MONTH(7:7)=MONTH(TODAY()),DAY(7:7)<30),"E","A"))) -> Q1A | BR8: ="Q2"&IF(YEAR(7:7)>YEAR(TODAY()),"E",IF(AND(YEAR(7:7)=YEAR(TODAY()),MONTH(7:7)>MONTH(TODAY())),"E",IF(AND(YEAR(7:7)=YEAR(TODAY()),MONTH(7:7)=MONTH(TODAY()),DAY(7:7)<30),"E","A"))) -> Q2A | BS8: ="Q3"&IF(YEAR(7:7)>YEAR(TODAY()),"E",IF(AND(YEAR(7:7)=YEAR(TODAY()),MONTH(7:7)>MONTH(TODAY())),"E",IF(AND(YEAR(7:7)=YEAR(TODAY()),MONTH(7:7)=MONTH(TODAY()),DAY(7:7)<30),"E","A"))) -> Q3A | BT8: ="Q4"&IF(YEAR(7:7)>YEAR(TODAY()),"E",IF(AND(YEAR(7:7)=YEAR(TODAY()),MONTH(7:7)>MONTH(TODAY())),"E",IF(AND(YEAR(7:7)=YEAR(TODAY()),MONTH(7:7)=MONTH(TODAY()),DAY(7:7)<30),"E","A"))) -> Q4A | BV8: ="Q1"&IF(YEAR(7:7)>YEAR(TODAY()),"E",IF(AND(YEAR(7:7)=YEAR(TODAY()),MONTH(7:7)>MONTH(TODAY())),"E",IF(AND(YEAR(7:7)=YEAR(TODAY()),MONTH(7:7)=MONTH(TODAY()),DAY(7:7)<30),"E","A"))) -> Q1A | BW8: ="Q2"&IF(YEAR(7:7)>YEAR(TODAY()),"E",IF(AND(YEAR(7:7)=YEAR(TODAY()),MONTH(7:7)>MONTH(TODAY())),"E",IF(AND(YEAR(7:7)=YEAR(TODAY()),MONTH(7:7)=MONTH(TODAY()),DAY(7:7)<30),"E","A"))) -> Q2A | BX8: ="Q3"&IF(YEAR(7:7)>YEAR(TODAY()),"E",IF(AND(YEAR(7:7)=YEAR(TODAY()),MONTH(7:7)>MONTH(TODAY())),"E",IF(AND(YEAR(7:7)=YEAR(TODAY()),MONTH(7:7)=MONTH(TODAY()),DAY(7:7)<30),"E","A"))) -> Q3A | BY8: ="Q4"&IF(YEAR(7:7)>YEAR(TODAY()),"E",IF(AND(YEAR(7:7)=YEAR(TODAY()),MONTH(7:7)>MONTH(TODAY())),"E",IF(AND(YEAR(7:7)=YEAR(TODAY()),MONTH(7:7)=MONTH(TODAY()),DAY(7:7)<30),"E","A"))) -> Q4A | CA8: ="Q1"&IF(YEAR(7:7)>YEAR(TODAY()),"E",IF(AND(YEAR(7:7)=YEAR(TODAY()),MONTH(7:7)>MONTH(TODAY())),"E",IF(AND(YEAR(7:7)=YEAR(TODAY()),MONTH(7:7)=MONTH(TODAY()),DAY(7:7)<30),"E","A"))) -> Q1A | CB8: ="Q2"&IF(YEAR(7:7)>YEAR(TODAY()),"E",IF(AND(YEAR(7:7)=YEAR(TODAY()),MONTH(7:7)>MONTH(TODAY())),"E",IF(AND(YEAR(7:7)=YEAR(TODAY()),MONTH(7:7)=MONTH(TODAY()),DAY(7:7)<30),"E","A"))) -> Q2A | CC8: ="Q3"&IF(YEAR(7:7)>YEAR(TODAY()),"E",IF(AND(YEAR(7:7)=YEAR(TODAY()),MONTH(7:7)>MONTH(TODAY())),"E",IF(AND(YEAR(7:7)=YEAR(TODAY()),MONTH(7:7)=MONTH(TODAY()),DAY(7:7)<30),"E","A"))) -> Q3A | CD8: ="Q4"&IF(YEAR(7:7)>YEAR(TODAY()),"E",IF(AND(YEAR(7:7)=YEAR(TODAY()),MONTH(7:7)>MONTH(TODAY())),"E",IF(AND(YEAR(7:7)=YEAR(TODAY()),MONTH(7:7)=MONTH(TODAY()),DAY(7:7)<30),"E","A"))) -> Q4A | CF8: ="Q1"&IF(YEAR(7:7)>YEAR(TODAY()),"E",IF(AND(YEAR(7:7)=YEAR(TODAY()),MONTH(7:7)>MONTH(TODAY())),"E",IF(AND(YEAR(7:7)=YEAR(TODAY()),MONTH(7:7)=MONTH(TODAY()),DAY(7:7)<30),"E","A"))) -> Q1A | CG8: ="Q2"&IF(YEAR(7:7)>YEAR(TODAY()),"E",IF(AND(YEAR(7:7)=YEAR(TODAY()),MONTH(7:7)>MONTH(TODAY())),"E",IF(AND(YEAR(7:7)=YEAR(TODAY()),MONTH(7:7)=MONTH(TODAY()),DAY(7:7)<30),"E","A"))) -> Q2A | CH8: ="Q3"&IF(YEAR(7:7)>YEAR(TODAY()),"E",IF(AND(YEAR(7:7)=YEAR(TODAY()),MONTH(7:7)>MONTH(TODAY())),"E",IF(AND(YEAR(7:7)=YEAR(TODAY()),MONTH(7:7)=MONTH(TODAY()),DAY(7:7)<30),"E","A"))) -> Q3A | CI8: ="Q4"&IF(YEAR(7:7)>YEAR(TODAY()),"E",IF(AND(YEAR(7:7)=YEAR(TODAY()),MONTH(7:7)>MONTH(TODAY())),"E",IF(AND(YEAR(7:7)=YEAR(TODAY()),MONTH(7:7)=MONTH(TODAY()),DAY(7:7)<30),"E","A"))) -> Q4A | CK8: ="Q1"&IF(YEAR(7:7)>YEAR(TODAY()),"E",IF(AND(YEAR(7:7)=YEAR(TODAY()),MONTH(7:7)>MONTH(TODAY())),"E",IF(AND(YEAR(7:7)=YEAR(TODAY()),MONTH(7:7)=MONTH(TODAY()),DAY(7:7)<30),"E","A"))) -> Q1A | CL8: ="Q2"&IF(YEAR(7:7)>YEAR(TODAY()),"E",IF(AND(YEAR(7:7)=YEAR(TODAY()),MONTH(7:7)>MONTH(TODAY())),"E",IF(AND(YEAR(7:7)=YEAR(TODAY()),MONTH(7:7)=MONTH(TODAY()),DAY(7:7)<30),"E","A"))) -> Q2A | CM8: ="Q3"&IF(YEAR(7:7)>YEAR(TODAY()),"E",IF(AND(YEAR(7:7)=YEAR(TODAY()),MONTH(7:7)>MONTH(TODAY())),"E",IF(AND(YEAR(7:7)=YEAR(TODAY()),MONTH(7:7)=MONTH(TODAY()),DAY(7:7)<30),"E","A"))) -> Q3A | CN8: Q4A | CP8: ="Q1"&IF(YEAR(7:7)>YEAR(TODAY()),"E",IF(AND(YEAR(7:7)=YEAR(TODAY()),MONTH(7:7)>MONTH(TODAY())),"E",IF(AND(YEAR(7:7)=YEAR(TODAY()),MONTH(7:7)=MONTH(TODAY()),DAY(7:7)<30),"E","A"))) -> Q1A | CQ8: ="Q2"&IF(YEAR(7:7)>YEAR(TODAY()),"E",IF(AND(YEAR(7:7)=YEAR(TODAY()),MONTH(7:7)>MONTH(TODAY())),"E",IF(AND(YEAR(7:7)=YEAR(TODAY()),MONTH(7:7)=MONTH(TODAY()),DAY(7:7)<30),"E","A"))) -> Q2A | CR8: ="Q3"&IF(YEAR(7:7)>YEAR(TODAY()),"E",IF(AND(YEAR(7:7)=YEAR(TODAY()),MONTH(7:7)>MONTH(TODAY())),"E",IF(AND(YEAR(7:7)=YEAR(TODAY()),MONTH(7:7)=MONTH(TODAY()),DAY(7:7)<30),"E","A"))) -> Q3A | CS8: ="Q4"&IF(YEAR(7:7)>YEAR(TODAY()),"E",IF(AND(YEAR(7:7)=YEAR(TODAY()),MONTH(7:7)>MONTH(TODAY())),"E",IF(AND(YEAR(7:7)=YEAR(TODAY()),MONTH(7:7)=MONTH(TODAY()),DAY(7:7)<30),"E","A"))) -> Q4A | CU8: ="Q1"&IF(YEAR(7:7)>YEAR(TODAY()),"E",IF(AND(YEAR(7:7)=YEAR(TODAY()),MONTH(7:7)>MONTH(TODAY())),"E",IF(AND(YEAR(7:7)=YEAR(TODAY()),MONTH(7:7)=MONTH(TODAY()),DAY(7:7)<30),"E","A"))) -> Q1A | CV8: ="Q2"&IF(YEAR(7:7)>YEAR(TODAY()),"E",IF(AND(YEAR(7:7)=YEAR(TODAY()),MONTH(7:7)>MONTH(TODAY())),"E",IF(AND(YEAR(7:7)=YEAR(TODAY()),MONTH(7:7)=MONTH(TODAY()),DAY(7:7)<30),"E","A"))) -> Q2A | CW8: ="Q3"&IF(YEAR(7:7)>YEAR(TODAY()),"E",IF(AND(YEAR(7:7)=YEAR(TODAY()),MONTH(7:7)>MONTH(TODAY())),"E",IF(AND(YEAR(7:7)=YEAR(TODAY()),MONTH(7:7)=MONTH(TODAY()),DAY(7:7)<30),"E","A"))) -> Q3A | CX8: ="Q4"&IF(YEAR(7:7)>YEAR(TODAY()),"E",IF(AND(YEAR(7:7)=YEAR(TODAY()),MONTH(7:7)>MONTH(TODAY())),"E",IF(AND(YEAR(7:7)=YEAR(TODAY()),MONTH(7:7)=MONTH(TODAY()),DAY(7:7)<30),"E","A"))) -> Q4A | CZ8: ="Q1"&IF(YEAR(7:7)>YEAR(TODAY()),"E",IF(AND(YEAR(7:7)=YEAR(TODAY()),MONTH(7:7)>MONTH(TODAY())),"E",IF(AND(YEAR(7:7)=YEAR(TODAY()),MONTH(7:7)=MONTH(TODAY()),DAY(7:7)<30),"E","A"))) -> Q1A | DA8: ="Q2"&IF(YEAR(7:7)>YEAR(TODAY()),"E",IF(AND(YEAR(7:7)=YEAR(TODAY()),MONTH(7:7)>MONTH(TODAY())),"E",IF(AND(YEAR(7:7)=YEAR(TODAY()),MONTH(7:7)=MONTH(TODAY()),DAY(7:7)<30),"E","A"))) -> Q2A | DB8: ="Q3"&IF(YEAR(7:7)>YEAR(TODAY()),"E",IF(AND(YEAR(7:7)=YEAR(TODAY()),MONTH(7:7)>MONTH(TODAY())),"E",IF(AND(YEAR(7:7)=YEAR(TODAY()),MONTH(7:7)=MONTH(TODAY()),DAY(7:7)<30),"E","A"))) -> Q3A | DC8: ="Q4"&IF(YEAR(7:7)>YEAR(TODAY()),"E",IF(AND(YEAR(7:7)=YEAR(TODAY()),MONTH(7:7)>MONTH(TODAY())),"E",IF(AND(YEAR(7:7)=YEAR(TODAY()),MONTH(7:7)=MONTH(TODAY()),DAY(7:7)<30),"E","A"))) -> Q4A | DE8: ="Q1"&IF(YEAR(7:7)>YEAR(TODAY()),"E",IF(AND(YEAR(7:7)=YEAR(TODAY()),MONTH(7:7)>MONTH(TODAY())),"E",IF(AND(YEAR(7:7)=YEAR(TODAY()),MONTH(7:7)=MONTH(TODAY()),DAY(7:7)<30),"E","A"))) -> Q1A | DF8: ="Q2"&IF(YEAR(7:7)>YEAR(TODAY()),"E",IF(AND(YEAR(7:7)=YEAR(TODAY()),MONTH(7:7)>MONTH(TODAY())),"E",IF(AND(YEAR(7:7)=YEAR(TODAY()),MONTH(7:7)=MONTH(TODAY()),DAY(7:7)<30),"E","A"))) -> Q2A | DG8: ="Q3"&IF(YEAR(7:7)>YEAR(TODAY()),"E",IF(AND(YEAR(7:7)=YEAR(TODAY()),MONTH(7:7)>MONTH(TODAY())),"E",IF(AND(YEAR(7:7)=YEAR(TODAY()),MONTH(7:7)=MONTH(TODAY()),DAY(7:7)<30),"E","A"))) -> Q3A | DH8: ="Q4"&IF(YEAR(7:7)>YEAR(TODAY()),"E",IF(AND(YEAR(7:7)=YEAR(TODAY()),MONTH(7:7)>MONTH(TODAY())),"E",IF(AND(YEAR(7:7)=YEAR(TODAY()),MONTH(7:7)=MONTH(TODAY()),DAY(7:7)<30),"E","A"))) -> Q4A | DJ8: ="Q1"&IF(YEAR(7:7)>YEAR(TODAY()),"E",IF(AND(YEAR(7:7)=YEAR(TODAY()),MONTH(7:7)>MONTH(TODAY())),"E",IF(AND(YEAR(7:7)=YEAR(TODAY()),MONTH(7:7)=MONTH(TODAY()),DAY(7:7)<30),"E","A"))) -> Q1A | DK8: ="Q2"&IF(YEAR(7:7)>YEAR(TODAY()),"E",IF(AND(YEAR(7:7)=YEAR(TODAY()),MONTH(7:7)>MONTH(TODAY())),"E",IF(AND(YEAR(7:7)=YEAR(TODAY()),MONTH(7:7)=MONTH(TODAY()),DAY(7:7)<30),"E","A"))) -> Q2A | DL8: ="Q3"&IF(YEAR(7:7)>YEAR(TODAY()),"E",IF(AND(YEAR(7:7)=YEAR(TODAY()),MONTH(7:7)>MONTH(TODAY())),"E",IF(AND(YEAR(7:7)=YEAR(TODAY()),MONTH(7:7)=MONTH(TODAY()),DAY(7:7)<30),"E","A"))) -> Q3A | DM8: ="Q4"&IF(YEAR(7:7)>YEAR(TODAY()),"E",IF(AND(YEAR(7:7)=YEAR(TODAY()),MONTH(7:7)>MONTH(TODAY())),"E",IF(AND(YEAR(7:7)=YEAR(TODAY()),MONTH(7:7)=MONTH(TODAY()),DAY(7:7)<30),"E","A"))) -> Q4A | DO8: ="Q1"&IF(YEAR(7:7)>YEAR(TODAY()),"E",IF(AND(YEAR(7:7)=YEAR(TODAY()),MONTH(7:7)>MONTH(TODAY())),"E",IF(AND(YEAR(7:7)=YEAR(TODAY()),MONTH(7:7)=MONTH(TODAY()),DAY(7:7)<30),"E","A"))) -> Q1A | DP8: ="Q2"&IF(YEAR(7:7)>YEAR(TODAY()),"E",IF(AND(YEAR(7:7)=YEAR(TODAY()),MONTH(7:7)>MONTH(TODAY())),"E",IF(AND(YEAR(7:7)=YEAR(TODAY()),MONTH(7:7)=MONTH(TODAY()),DAY(7:7)<30),"E","A"))) -> Q2A | DQ8: ="Q3"&IF(YEAR(7:7)>YEAR(TODAY()),"E",IF(AND(YEAR(7:7)=YEAR(TODAY()),MONTH(7:7)>MONTH(TODAY())),"E",IF(AND(YEAR(7:7)=YEAR(TODAY()),MONTH(7:7)=MONTH(TODAY()),DAY(7:7)<30),"E","A"))) -> Q3A | DR8: ="Q4"&IF(YEAR(7:7)>YEAR(TODAY()),"E",IF(AND(YEAR(7:7)=YEAR(TODAY()),MONTH(7:7)>MONTH(TODAY())),"E",IF(AND(YEAR(7:7)=YEAR(TODAY()),MONTH(7:7)=MONTH(TODAY()),DAY(7:7)<30),"E","A"))) -> Q4A | DT8: ="Q1"&IF(YEAR(7:7)>YEAR(TODAY()),"E",IF(AND(YEAR(7:7)=YEAR(TODAY()),MONTH(7:7)>MONTH(TODAY())),"E",IF(AND(YEAR(7:7)=YEAR(TODAY()),MONTH(7:7)=MONTH(TODAY()),DAY(7:7)<30),"E","A"))) -> Q1A | DU8: ="Q2"&IF(YEAR(7:7)>YEAR(TODAY()),"E",IF(AND(YEAR(7:7)=YEAR(TODAY()),MONTH(7:7)>MONTH(TODAY())),"E",IF(AND(YEAR(7:7)=YEAR(TODAY()),MONTH(7:7)=MONTH(TODAY()),DAY(7:7)<30),"E","A"))) -> Q2A | DV8: ="Q3"&IF(YEAR(7:7)>YEAR(TODAY()),"E",IF(AND(YEAR(7:7)=YEAR(TODAY()),MONTH(7:7)>MONTH(TODAY())),"E",IF(AND(YEAR(7:7)=YEAR(TODAY()),MONTH(7:7)=MONTH(TODAY()),DAY(7:7)<30),"E","A"))) -> Q3A | DW8: ="Q4"&IF(YEAR(7:7)>YEAR(TODAY()),"E",IF(AND(YEAR(7:7)=YEAR(TODAY()),MONTH(7:7)>MONTH(TODAY())),"E",IF(AND(YEAR(7:7)=YEAR(TODAY()),MONTH(7:7)=MONTH(TODAY()),DAY(7:7)<30),"E","A"))) -> Q4A | DY8: ="Q1"&IF(YEAR(7:7)>YEAR(TODAY()),"E",IF(AND(YEAR(7:7)=YEAR(TODAY()),MONTH(7:7)>MONTH(TODAY())),"E",IF(AND(YEAR(7:7)=YEAR(TODAY()),MONTH(7:7)=MONTH(TODAY()),DAY(7:7)<30),"E","A"))) -> Q1A | DZ8: ="Q2"&IF(YEAR(7:7)>YEAR(TODAY()),"E",IF(AND(YEAR(7:7)=YEAR(TODAY()),MONTH(7:7)>MONTH(TODAY())),"E",IF(AND(YEAR(7:7)=YEAR(TODAY()),MONTH(7:7)=MONTH(TODAY()),DAY(7:7)<30),"E","A"))) -> Q2A | EA8: ="Q3"&IF(YEAR(7:7)>YEAR(TODAY()),"E",IF(AND(YEAR(7:7)=YEAR(TODAY()),MONTH(7:7)>MONTH(TODAY())),"E",IF(AND(YEAR(7:7)=YEAR(TODAY()),MONTH(7:7)=MONTH(TODAY()),DAY(7:7)<30),"E","A"))) -> Q3A | EB8: ="Q4"&IF(YEAR(7:7)>YEAR(TODAY()),"E",IF(AND(YEAR(7:7)=YEAR(TODAY()),MONTH(7:7)>MONTH(TODAY())),"E",IF(AND(YEAR(7:7)=YEAR(TODAY()),MONTH(7:7)=MONTH(TODAY()),DAY(7:7)<30),"E","A"))) -> Q4A | ED8: ="Q1"&IF(YEAR(7:7)>YEAR(TODAY()),"E",IF(AND(YEAR(7:7)=YEAR(TODAY()),MONTH(7:7)>MONTH(TODAY())),"E",IF(AND(YEAR(7:7)=YEAR(TODAY()),MONTH(7:7)=MONTH(TODAY()),DAY(7:7)<30),"E","A"))) -> Q1A | EE8: ="Q2"&IF(YEAR(7:7)>YEAR(TODAY()),"E",IF(AND(YEAR(7:7)=YEAR(TODAY()),MONTH(7:7)>MONTH(TODAY())),"E",IF(AND(YEAR(7:7)=YEAR(TODAY()),MONTH(7:7)=MONTH(TODAY()),DAY(7:7)<30),"E","A"))) -> Q2A | EF8: ="Q3"&IF(YEAR(7:7)>YEAR(TODAY()),"E",IF(AND(YEAR(7:7)=YEAR(TODAY()),MONTH(7:7)>MONTH(TODAY())),"E",IF(AND(YEAR(7:7)=YEAR(TODAY()),MONTH(7:7)=MONTH(TODAY()),DAY(7:7)<30),"E","A"))) -> Q3A | EG8: ="Q4"&IF(YEAR(7:7)>YEAR(TODAY()),"E",IF(AND(YEAR(7:7)=YEAR(TODAY()),MONTH(7:7)>MONTH(TODAY())),"E",IF(AND(YEAR(7:7)=YEAR(TODAY()),MONTH(7:7)=MONTH(TODAY()),DAY(7:7)<30),"E","A"))) -> Q4A | EI8: ="Q1"&IF(YEAR(7:7)>YEAR(TODAY()),"E",IF(AND(YEAR(7:7)=YEAR(TODAY()),MONTH(7:7)>MONTH(TODAY())),"E",IF(AND(YEAR(7:7)=YEAR(TODAY()),MONTH(7:7)=MONTH(TODAY()),DAY(7:7)<30),"E","A"))) -> Q1A | EJ8: ="Q2"&IF(YEAR(7:7)>YEAR(TODAY()),"E",IF(AND(YEAR(7:7)=YEAR(TODAY()),MONTH(7:7)>MONTH(TODAY())),"E",IF(AND(YEAR(7:7)=YEAR(TODAY()),MONTH(7:7)=MONTH(TODAY()),DAY(7:7)<30),"E","A"))) -> Q2A | EK8: ="Q3"&IF(YEAR(7:7)>YEAR(TODAY()),"E",IF(AND(YEAR(7:7)=YEAR(TODAY()),MONTH(7:7)>MONTH(TODAY())),"E",IF(AND(YEAR(7:7)=YEAR(TODAY()),MONTH(7:7)=MONTH(TODAY()),DAY(7:7)<30),"E","A"))) -> Q3A | EL8: ="Q4"&IF(YEAR(7:7)>YEAR(TODAY()),"E",IF(AND(YEAR(7:7)=YEAR(TODAY()),MONTH(7:7)>MONTH(TODAY())),"E",IF(AND(YEAR(7:7)=YEAR(TODAY()),MONTH(7:7)=MONTH(TODAY()),DAY(7:7)<30),"E","A"))) -> Q4A | EN8: ="Q1"&IF(YEAR(7:7)>YEAR(TODAY()),"E",IF(AND(YEAR(7:7)=YEAR(TODAY()),MONTH(7:7)>MONTH(TODAY())),"E",IF(AND(YEAR(7:7)=YEAR(TODAY()),MONTH(7:7)=MONTH(TODAY()),DAY(7:7)<30),"E","A"))) -> Q1A | EO8: ="Q2"&IF(YEAR(7:7)>YEAR(TODAY()),"E",IF(AND(YEAR(7:7)=YEAR(TODAY()),MONTH(7:7)>MONTH(TODAY())),"E",IF(AND(YEAR(7:7)=YEAR(TODAY()),MONTH(7:7)=MONTH(TODAY()),DAY(7:7)<30),"E","A"))) -> Q2A | EP8: ="Q3"&IF(YEAR(7:7)>YEAR(TODAY()),"E",IF(AND(YEAR(7:7)=YEAR(TODAY()),MONTH(7:7)>MONTH(TODAY())),"E",IF(AND(YEAR(7:7)=YEAR(TODAY()),MONTH(7:7)=MONTH(TODAY()),DAY(7:7)<30),"E","A"))) -> Q3A | EQ8: ="Q4"&IF(YEAR(7:7)>YEAR(TODAY()),"E",IF(AND(YEAR(7:7)=YEAR(TODAY()),MONTH(7:7)>MONTH(TODAY())),"E",IF(AND(YEAR(7:7)=YEAR(TODAY()),MONTH(7:7)=MONTH(TODAY()),DAY(7:7)<30),"E","A"))) -> Q4A | ES8: ="Q1"&IF(YEAR(7:7)>YEAR(TODAY()),"E",IF(AND(YEAR(7:7)=YEAR(TODAY()),MONTH(7:7)>MONTH(TODAY())),"E",IF(AND(YEAR(7:7)=YEAR(TODAY()),MONTH(7:7)=MONTH(TODAY()),DAY(7:7)<30),"E","A"))) -> Q1A | ET8: ="Q2"&IF(YEAR(7:7)>YEAR(TODAY()),"E",IF(AND(YEAR(7:7)=YEAR(TODAY()),MONTH(7:7)>MONTH(TODAY())),"E",IF(AND(YEAR(7:7)=YEAR(TODAY()),MONTH(7:7)=MONTH(TODAY()),DAY(7:7)<30),"E","A"))) -> Q2A | EU8: ="Q3"&IF(YEAR(7:7)>YEAR(TODAY()),"E",IF(AND(YEAR(7:7)=YEAR(TODAY()),MONTH(7:7)>MONTH(TODAY())),"E",IF(AND(YEAR(7:7)=YEAR(TODAY()),MONTH(7:7)=MONTH(TODAY()),DAY(7:7)<30),"E","A"))) -> Q3A | EV8: ="Q4"&IF(YEAR(7:7)>YEAR(TODAY()),"E",IF(AND(YEAR(7:7)=YEAR(TODAY()),MONTH(7:7)>MONTH(TODAY())),"E",IF(AND(YEAR(7:7)=YEAR(TODAY()),MONTH(7:7)=MONTH(TODAY()),DAY(7:7)<30),"E","A"))) -> Q4A | EX8: ="Q1"&IF(YEAR(7:7)>YEAR(TODAY()),"E",IF(AND(YEAR(7:7)=YEAR(TODAY()),MONTH(7:7)>MONTH(TODAY())),"E",IF(AND(YEAR(7:7)=YEAR(TODAY()),MONTH(7:7)=MONTH(TODAY()),DAY(7:7)<30),"E","A"))) -> Q1A | EY8: ="Q2"&IF(YEAR(7:7)>YEAR(TODAY()),"E",IF(AND(YEAR(7:7)=YEAR(TODAY()),MONTH(7:7)>MONTH(TODAY())),"E",IF(AND(YEAR(7:7)=YEAR(TODAY()),MONTH(7:7)=MONTH(TODAY()),DAY(7:7)<30),"E","A"))) -> Q2E | EZ8: ="Q3"&IF(YEAR(7:7)>YEAR(TODAY()),"E",IF(AND(YEAR(7:7)=YEAR(TODAY()),MONTH(7:7)>MONTH(TODAY())),"E",IF(AND(YEAR(7:7)=YEAR(TODAY()),MONTH(7:7)=MONTH(TODAY()),DAY(7:7)<30),"E","A"))) -> Q3E | FA8: ="Q4"&IF(YEAR(7:7)>YEAR(TODAY()),"E",IF(AND(YEAR(7:7)=YEAR(TODAY()),MONTH(7:7)>MONTH(TODAY())),"E",IF(AND(YEAR(7:7)=YEAR(TODAY()),MONTH(7:7)=MONTH(TODAY()),DAY(7:7)<30),"E","A"))) -> Q4E | FC8: ="Q1"&IF(YEAR(7:7)>YEAR(TODAY()),"E",IF(AND(YEAR(7:7)=YEAR(TODAY()),MONTH(7:7)>MONTH(TODAY())),"E",IF(AND(YEAR(7:7)=YEAR(TODAY()),MONTH(7:7)=MONTH(TODAY()),DAY(7:7)<30),"E","A"))) -> Q1E | FD8: ="Q2"&IF(YEAR(7:7)>YEAR(TODAY()),"E",IF(AND(YEAR(7:7)=YEAR(TODAY()),MONTH(7:7)>MONTH(TODAY())),"E",IF(AND(YEAR(7:7)=YEAR(TODAY()),MONTH(7:7)=MONTH(TODAY()),DAY(7:7)<30),"E","A"))) -> Q2E | FE8: ="Q3"&IF(YEAR(7:7)>YEAR(TODAY()),"E",IF(AND(YEAR(7:7)=YEAR(TODAY()),MONTH(7:7)>MONTH(TODAY())),"E",IF(AND(YEAR(7:7)=YEAR(TODAY()),MONTH(7:7)=MONTH(TODAY()),DAY(7:7)<30),"E","A"))) -> Q3E | FF8: ="Q4"&IF(YEAR(7:7)>YEAR(TODAY()),"E",IF(AND(YEAR(7:7)=YEAR(TODAY()),MONTH(7:7)>MONTH(TODAY())),"E",IF(AND(YEAR(7:7)=YEAR(TODAY()),MONTH(7:7)=MONTH(TODAY()),DAY(7:7)<30),"E","A"))) -> Q4E
B9: IAG | H9: =IABG -> 18811 | M9: =IABG -> 22679 | N9: =IABG -> 4931 | O9: =IABG -> 5240 | P9: =IABG -> 6233 | Q9: =IABG -> 7449 | R9: =IABG -> 23853 | S9: =IABG -> 6429 | T9: =IABG -> 5559 | ... BU9: =IABG -> #ERROR! | BV9: =+BV600 -> 9920 | BW9: =+BW600 -> 10370 | BX9: =+BX600 -> 10736 | BY9: =+BY600 -> 11049 | BZ9: =+SUM(BV9:BY9) -> 42075 | CA9: =+CA600 -> 12234 | CB9: =+CB600 -> 12146 | CC9: =+CC600 -> 13297 | CD9: =+CD600 -> 12863 | CE9: =+SUM(CA9:CD9) -> 50540 | CF9: =CF512 -> #NAME? | CG9: =CG512 -> #NAME? | CH9: =CH512 -> #NAME? | CI9: =CI512 -> #NAME? | CJ9: =+SUM(CF9:CI9) -> #NAME? | CK9: =CK512 -> #NAME? | CL9: =CL512 -> #NAME? | CM9: =CM512 -> #NAME? | CN9: =CN512 -> #NAME? | CO9: =+SUM(CK9:CN9) -> #NAME? | CP9: =CP512 -> #NAME? | CQ9: =CQ512 -> #NAME? | CR9: =CR512 -> #NAME? | CS9: =CS512 -> #NAME? | CT9: =+SUM(CP9:CS9) -> #NAME? | CU9: =CU512 -> #NAME? | CV9: =CV512 -> #NAME? | CW9: =CW512 -> #NAME? | CX9: =CX512 -> #NAME? | CY9: =+SUM(CU9:CX9) -> #NAME? | CZ9: =CZ512 -> #NAME? | DA9: =DA512 -> #NAME? | DB9: =DB512 -> #NAME? | DC9: =DC512 -> #NAME? | DD9: =+SUM(CZ9:DC9) -> #NAME? | DE9: =DE512 -> #NAME? | DF9: =DF512 -> #NAME? | DG9: =DG512 -> #NAME? | DH9: =DH512 -> #NAME? | DI9: =+SUM(DE9:DH9) -> #NAME? | DJ9: =DJ512 -> #NAME? | DK9: =DK512 -> #NAME? | DL9: =DL512 -> #NAME? | DM9: =DM512 -> #NAME? | DN9: =+SUM(DJ9:DM9) -> #NAME? | DO9: =DO512 -> #NAME? | DP9: =DP512 -> #NAME? | DQ9: =DQ512 -> #NAME? | DR9: =DR512 -> #NAME? | DS9: =+SUM(DO9:DR9) -> #NAME? | DT9: =DT512 -> #NAME? | DU9: =DU512 -> #NAME? | DV9: =DV512 -> #NAME? | DW9: =DW512 -> #NAME? | DX9: =+SUM(DT9:DW9) -> #NAME? | DY9: =DY512 -> #NAME? | DZ9: =DZ512 -> #NAME? | EA9: =EA512 -> #NAME? | EB9: =EB512 -> #NAME? | EC9: =+SUM(DY9:EB9) -> #NAME? | ED9: =ED512 -> #NAME? | EE9: =EE512 -> #NAME? | EF9: =EF512 -> #NAME? | EG9: =EG512 -> #NAME? | EH9: =+SUM(ED9:EG9) -> #NAME? | EI9: =EI512 -> #NAME? | EJ9: =EJ512 -> #NAME? | EK9: =EK512 -> #NAME? | EL9: =EL512 -> #NAME? | EM9: =+SUM(EI9:EL9) -> #NAME? | EN9: =EN512 -> #NAME? | EO9: =EO512 -> #NAME? | EP9: =EP512 -> #NAME? | EQ9: =EQ512 -> #NAME? | ER9: =+SUM(EN9:EQ9) -> #NAME? | ES9: =ES512 -> #NAME? | ET9: =ET512 -> #NAME? | EU9: =EU512 -> #NAME? | EV9: =EV512 -> #NAME? | EW9: =+SUM(ES9:EV9) -> #NAME? | EX9: =EX512 -> #NAME? | EY9: =EY512 -> #NAME? | EZ9: =EZ512 -> #NAME? | FA9: =FA512 -> #NAME? | FB9: =+SUM(EX9:FA9) -> #NAME? | FC9: =FC512 -> #NAME? | FD9: =FD512 -> #NAME? | FE9: =FE512 -> #NAME? | FF9: =FF512 -> #NAME? | FG9: =+SUM(FC9:FF9) -> #NAME?
B10: All others | H10: =AOG -> 2036 | M10: =AOG -> 2392 | N10: =AOG -> 1070 | O10: =AOG -> 687 | P10: =AOG -> 498 | Q10: =AOG -> 165 | R10: =AOG -> 2420 | S10: =AOG -> 674 | T10: =AOG -> 1187 | ... BY10: =AOG -> #ERROR! | BZ10: =+SUM(BV10:BY10) -> #ERROR! | CA10: =AOG -> #ERROR! | CB10: =AOG -> #ERROR! | CC10: =AOG -> #ERROR! | CD10: =AOG -> #ERROR! | CE10: =+SUM(CA10:CD10) -> #ERROR! | CF10: =AOG -> #ERROR! | CG10: =AOG -> #ERROR! | CH10: =AOG -> #ERROR! | CI10: =AOG -> #ERROR! | CJ10: =+SUM(CF10:CI10) -> #ERROR! | CK10: =AOG -> #ERROR! | CL10: =AOG -> #ERROR! | CM10: =AOG -> #ERROR! | CN10: =AOG -> #ERROR! | CO10: =+SUM(CK10:CN10) -> #ERROR! | CP10: =AOG -> #ERROR! | CQ10: =AOG -> #ERROR! | CR10: =AOG -> #ERROR! | CS10: =AOG -> #ERROR! | CT10: =AOG -> #ERROR! | CU10: =AOG -> #ERROR! | CV10: =AOG -> #ERROR! | CW10: =AOG -> #ERROR! | ... FG10: =AOG -> #ERROR!
B11: Revenue (GAAP) | DE11: =DE12 -> 14796 | DF11: =DF12 -> 14763 | DG11: =DG12 -> 16149 | DH11: =DH12 -> 17053 | DI11: =DI12 -> 62761 | DJ11: =DJ12 -> 16066 | DK11: =DK12 -> 16962 | DL11: =DL12 -> 19163 | ... DX11: =DX12 -> 77867 | DY11: 19673 | DZ11: 19631 | EA11: 19192 | EB11: 20528 | EC11: =SUM(DY11:EB11) -> 79024 | ED11: 18353 | EE11: 15321 | EF11: 15338 | EG11: 14042 | EH11: =SUM(ED11:EG11) -> 63054 | EI11: =EI242 -> #ERROR! | EJ11: =EJ242 -> #ERROR! | EK11: =EK242 -> #ERROR! | EL11: =EL242 -> #ERROR! | EM11: =SUM(EI11:EL11) -> #ERROR! | EN11: =EN242 -> #ERROR! | EO11: =EO242 -> #ERROR! | EP11: =EP242 -> #ERROR! | EQ11: =EQ242 -> #ERROR! | ER11: =SUM(EN11:EQ11) -> #ERROR! | ES11: =ES242 -> #ERROR! | ET11: =ET242 -> #ERROR! | EU11: =EU242 -> #ERROR! | EV11: =EV242 -> #ERROR! | EW11: =SUM(ES11:EV11) -> #ERROR! | EX11: =EX242 -> #ERROR! | EY11: =EY242 -> #ERROR! | EZ11: =EZ242 -> #ERROR! | FA11: =FA242 -> #ERROR! | FB11: =SUM(EX11:FA11) -> #ERROR! | FC11: =FC242 -> #ERROR! | FD11: =FD242 -> #ERROR! | FE11: =FE242 -> #ERROR! | FF11: =FF242 -> #ERROR! | FG11: =SUM(FC11:FF11) -> #ERROR!
B12: Total Revenues | H12: =SUM(H9,H10) -> 20847 | M12: =SUM(M9,M10) -> 25071 | N12: 6001 | O12: 5927 | P12: 6731 | Q12: 7614 | R12: =+SUM(N12:Q12) -> 26273 | S12: 7103 | T12: 6746 | U12: 7328 | V12: 8212 | W12: =+SUM(S12:V12) -> 29389 | X12: 7993 | Y12: 8300 | Z12: 8731 | AA12: 8702 | AB12: =+SUM(X12:AA12) -> 33726 | AC12: 6677 | AD12: 6334 | AE12: 6545 | AF12: 6983 | AG12: =+SUM(AC12:AF12) -> 26539 | AH12: 6781 | AI12: 6319 | AJ12: 6504 | AK12: 7160 | AL12: =+SUM(AH12:AK12) -> 26764 | AM12: 6751 | AN12: 6816 | AO12: 7833 | AP12: 8741 | AQ12: =AQ858 -> 30141 | AR12: 8091 | AS12: 8049 | AT12: 8471 | AU12: 9598 | AV12: =AV858 -> 34209 | AW12: 9434 | AX12: 9231 | AY12: 9960 | AZ12: 10201 | BA12: =SUM(AW12:AZ12) -> 38826 | BB12: 8940 | BC12: 8009 | BD12: 8739 | BE12: 9694 | BF12: =SUM(BB12:BE12) -> 35382 | BG12: 8852 | BH12: 8680 | BI12: 10090 | BJ12: 10712 | BK12: =SUM(BG12:BJ12) -> 38334 | BL12: 9673 | BM12: 9470 | BN12: 10217 | BO12: 8226 | BP12: =SUM(BL12:BO12) -> 37586 | BQ12: 7145 | BR12: 8024 | BS12: 9389 | BT12: 10569 | BU12: =SUM(BQ12:BT12) -> 35127 | BV12: 10299 | BW12: 10765 | BX12: 11102 | BY12: 11457 | BZ12: =SUM(BV12:BY12) -> 43623 | CA12: 12847 | CB12: 13032 | CC12: 14233 | CD12: 13887 | CE12: =SUM(CA12:CD12) -> 53999 | CF12: 12906 | CG12: 13501 | CH12: 13457 | CI12: 13477 | CJ12: =SUM(CF12:CI12) -> 53341 | CK12: 12580 | CL12: 12811 | CM12: 13483 | CN12: 13834 | CO12: =SUM(CK12:CN12) -> 52708 | CP12: 12764 | CQ12: 13831 | CR12: 14554 | CS12: 14721 | CT12: =SUM(CP12:CS12) -> 55870 | CU12: 12781 | CV12: 13195 | CW12: 14465 | CX12: 14914 | CY12: =SUM(CU12:CX12) -> 55355 | CZ12: =13702+99 -> 13801 | DA12: 13533 | DB12: 15778 | DC12: 16374 | DD12: =SUM(CZ12:DC12) -> 59486 | DE12: 14796 | DF12: 14763 | DG12: 16149 | DH12: 17053 | DI12: =SUM(DE12:DH12) -> 62761 | DJ12: 16066 | DK12: 16962 | DL12: 19163 | DM12: 18657 | DN12: =SUM(DJ12:DM12) -> 70848 | DO12: 16061 | DP12: 16505 | DQ12: 19190 | DR12: 20209 | DS12: =SUM(DO12:DR12) -> 71965 | DT12: 19828 | DU12: 19728 | DV12: 18333 | DW12: 19978 | DX12: =SUM(DT12:DW12) -> 77867 | DY12: 18566 | DZ12: 18533 | EA12: 18087 | EB12: 19532 | EC12: =SUM(DY12:EB12) -> 74718 | ED12: =ED11 -> 18353 | EE12: =EE11 -> 15321 | EF12: =EF11 -> 15338 | EG12: =EG11 -> 14042 | EH12: =SUM(ED12:EG12) -> 63054 | EI12: =EI11 -> #ERROR! | EJ12: =EJ11 -> #ERROR! | EK12: =EK11 -> #ERROR! | EL12: =EL11 -> #ERROR! | EM12: =SUM(EI12:EL12) -> #ERROR! | EN12: =EN11 -> #ERROR! | EO12: =EO11 -> #ERROR! | EP12: =EP11 -> #ERROR! | EQ12: =EQ11 -> #ERROR! | ER12: =SUM(EN12:EQ12) -> #ERROR! | ES12: =ES11 -> #ERROR! | ET12: =ET11 -> #ERROR! | EU12: =EU11 -> #ERROR! | EV12: =EV11 -> #ERROR! | EW12: =SUM(ES12:EV12) -> #ERROR! | EX12: =EX11 -> #ERROR! | EY12: =EY11 -> #ERROR! | EZ12: =EZ11 -> #ERROR! | FA12: =FA11 -> #ERROR! | FB12: =SUM(EX12:FA12) -> #ERROR! | FC12: =FC11 -> #ERROR! | FD12: =FD11 -> #ERROR! | FE12: =FE11 -> #ERROR! | FF12: =FF11 -> #ERROR! | FG12: =SUM(FC12:FF12) -> #ERROR!
B13: Q/Q | CK13: =(CK12-CI12)/CI12 -> -0.066557839 | CL13: =(CL12-CK12)/CK12 -> 0.01836248 | CM13: =(CM12-CL12)/CL12 -> 0.052454922 | CN13: =(CN12-CM12)/CM12 -> 0.026032782 | CP13: =(CP12-CN12)/CN12 -> -0.07734567 | CQ13: =(CQ12-CP12)/CP12 -> 0.083594484 | CR13: =(CR12-CQ12)/CQ12 -> 0.052273878 | CS13: =(CS12-CR12)/CR12 -> 0.011474509 | CU13: =(CU12-CS12)/CS12 -> -0.13178453 | CV13: =(CV12-CU12)/CU12 -> 0.032391832 | CW13: =(CW12-CV12)/CV12 -> 0.096248579 | CX13: =(CX12-CW12)/CW12 -> 0.031040442 | CZ13: =(CZ12-CX12)/CX12 -> -0.074627866 | DA13: =(DA12-CZ12)/CZ12 -> -0.019418883 | DB13: =(DB12-DA12)/DA12 -> 0.16589079 | DC13: =(DC12-DB12)/DB12 -> 0.037774116 | DE13: =(DE12-DC12)/DC12 -> -0.096372298 | DF13: =(DF12-DE12)/DE12 -> -0.0022303325 | DG13: =(DG12-DF12)/DF12 -> 0.093883357 | DH13: =(DH12-DG12)/DG12 -> 0.055978698 | DJ13: =(DJ12-DH12)/DH12 -> -0.057878379 | DK13: =(DK12-DJ12)/DJ12 -> 0.055769949 | DL13: =(DL12-DK12)/DK12 -> 0.12976064 | DM13: =(DM12-DL12)/DL12 -> -0.026405051 | DO13: =(DO12-DM12)/DM12 -> -0.13914349 | DP13: =(DP12-DO12)/DO12 -> 0.027644605 | DQ13: =(DQ12-DP12)/DP12 -> 0.16267798 | DR13: =(DR12-DQ12)/DQ12 -> 0.053100573 | DT13: =(DT12-DR12)/DR12 -> -0.018852986 | DU13: =(DU12-DT12)/DT12 -> -0.005043373 | DV13: =(DV12-DU12)/DU12 -> -0.070711679 | DW13: =(DW12-DV12)/DV12 -> 0.089728904 | DY13: =(DY12-DW12)/DW12 -> -0.070677746 | DZ13: =(DZ12-DY12)/DY12 -> -0.0017774426 | EA13: =(EA12-DZ12)/DZ12 -> -0.024065181 | EB13: =(EB12-EA12)/EA12 -> 0.079891635 | ED13: =(ED12-EB12)/EB12 -> -0.060362482 | EE13: =(EE12-ED12)/ED12 -> -0.1652046 | EF13: =(EF12-EE12)/EE12 -> 0.0011095881 | EG13: =(EG12-EF12)/EF12 -> -0.084496023 | EI13: =(EI12-EG12)/EG12 -> #ERROR! | EJ13: =(EJ12-EI12)/EI12 -> #ERROR! | EK13: =(EK12-EJ12)/EJ12 -> #ERROR! | EL13: =(EL12-EK12)/EK12 -> #ERROR! | EN13: =(EN12-EL12)/EL12 -> #ERROR! | EO13: =(EO12-EN12)/EN12 -> #ERROR! | EP13: =(EP12-EO12)/EO12 -> #ERROR! | EQ13: =(EQ12-EP12)/EP12 -> #ERROR! | ES13: =(ES12-EQ12)/EQ12 -> #ERROR! | ET13: =(ET12-ES12)/ES12 -> #ERROR! | EU13: =(EU12-ET12)/ET12 -> #ERROR! | EV13: =(EV12-EU12)/EU12 -> #ERROR! | EX13: =(EX12-EV12)/EV12 -> #ERROR! | EY13: =(EY12-EX12)/EX12 -> #ERROR! | EZ13: =(EZ12-EY12)/EY12 -> #ERROR! | FA13: =(FA12-EZ12)/EZ12 -> #ERROR! | FC13: =(FC12-FA12)/FA12 -> #ERROR! | FD13: =(FD12-FC12)/FC12 -> #ERROR! | FE13: =(FE12-FD12)/FD12 -> #ERROR! | FF13: =(FF12-FE12)/FE12 -> #ERROR!
B14: Y/Y | CK14: =(CK12-CF12)/CF12 -> -0.025259569 | CL14: =(CL12-CG12)/CG12 -> -0.051107325 | CM14: =(CM12-CH12)/CH12 -> 0.00193208 | CN14: =(CN12-CI12)/CI12 -> 0.026489575 | CO14: =(CO12-CJ12)/CJ12 -> -0.011867044 | CP14: =(CP12-CK12)/CK12 -> 0.014626391 | CQ14: =(CQ12-CL12)/CL12 -> 0.079619077 | CR14: =(CR12-CM12)/CM12 -> 0.079433361 | ... FG14: =(FG12-FB12)/FB12 -> #ERROR!
B15: 3 Yr Seasonal | CU15: =AVERAGE(CU13,CP13,CK13) -> -0.091896012 | CV15: =AVERAGE(CV13,CQ13,CL13) -> 0.044782932 | CW15: =AVERAGE(CW13,CR13,CM13) -> 0.066992459 | CX15: =AVERAGE(CX13,CS13,CN13) -> 0.022849244 | CZ15: =AVERAGE(CZ13,CU13,CP13) -> -0.094586021 | DA15: =AVERAGE(DA13,CV13,CQ13) -> 0.032189144 | DB15: =AVERAGE(DB13,CW13,CR13) -> 0.10480441 | DC15: =AVERAGE(DC13,CX13,CS13) -> 0.026763022 | DE15: =AVERAGE(DE13,CZ13,CU13) -> -0.10092823 | DF15: =AVERAGE(DF13,DA13,CV13) -> 0.0035808721 | DG15: =AVERAGE(DG13,DB13,CW13) -> 0.11867424 | DH15: =AVERAGE(DH13,DC13,CX13) -> 0.041597752 | DJ15: =AVERAGE(DJ13,DE13,CZ13) -> -0.076292848 | DK15: =AVERAGE(DK13,DF13,DA13) -> 0.011373578 | DL15: =AVERAGE(DL13,DG13,DB13) -> 0.12984493 | DM15: =AVERAGE(DM13,DH13,DC13) -> 0.022449254 | DO15: =AVERAGE(DO13,DJ13,DE13) -> -0.097798054 | DP15: =AVERAGE(DP13,DK13,DF13) -> 0.027061407 | DQ15: =AVERAGE(DQ13,DL13,DG13) -> 0.12877399 | DR15: =AVERAGE(DR13,DM13,DH13) -> 0.027558073 | DT15: =AVERAGE(DT13,DO13,DJ13) -> -0.071958283 | DU15: =AVERAGE(DU13,DP13,DK13) -> 0.026123727 | DV15: =AVERAGE(DV13,DQ13,DL13) -> 0.07390898 | DW15: =AVERAGE(DW13,DR13,DM13) -> 0.038808142 | DY15: =AVERAGE(DY13,DT13,DO13) -> -0.076224739 | DZ15: =AVERAGE(DZ13,DU13,DP13) -> 0.0069412631 | EA15: =AVERAGE(EA13,DV13,DQ13) -> 0.022633706 | EB15: =AVERAGE(EB13,DW13,DR13) -> 0.074240371 | ED15: =AVERAGE(ED13,DY13,DT13) -> -0.049964405 | EE15: =AVERAGE(EE13,DZ13,DU13) -> -0.057341805 | EF15: =AVERAGE(EF13,EA13,DV13) -> -0.031222424 | EG15: =AVERAGE(EG13,EB13,DW13) -> 0.028374839
B16: 5 Yr Seasonal | CU16: =AVERAGE(CU13,CP13,CK13,CF13,CA13) -> -0.091896012 | CV16: =AVERAGE(CV13,CQ13,CL13,CG13,CB13) -> 0.044782932 | CW16: =AVERAGE(CW13,CR13,CM13,CH13,CC13) -> 0.066992459 | CX16: =AVERAGE(CX13,CS13,CN13,CI13,CD13) -> 0.022849244 | CZ16: =AVERAGE(CZ13,CU13,CP13,CK13,CF13) -> -0.087578975 | DA16: =AVERAGE(DA13,CV13,CQ13,CL13,CG13) -> 0.028732478 | DB16: =AVERAGE(DB13,CW13,CR13,CM13,CH13) -> 0.091717041 | DC16: =AVERAGE(DC13,CX13,CS13,CN13,CI13) -> 0.026580462 | DE16: =AVERAGE(DE13,CZ13,CU13,CP13,CK13) -> -0.08933764 | DF16: =AVERAGE(DF13,DA13,CV13,CQ13,CL13) -> 0.022539916 | DG16: =AVERAGE(DG13,DB13,CW13,CR13,CM13) -> 0.092150304 | DH16: =AVERAGE(DH13,DC13,CX13,CS13,CN13) -> 0.032460109 | DJ16: =AVERAGE(DJ13,DE13,CZ13,CU13,CP13) -> -0.087601748 | DK16: =AVERAGE(DK13,DF13,DA13,CV13,CQ13) -> 0.03002141 | DL16: =AVERAGE(DL13,DG13,DB13,CW13,CR13) -> 0.10761145 | DM16: =AVERAGE(DM13,DH13,DC13,CX13,CS13) -> 0.021972543 | DO16: =AVERAGE(DO13,DJ13,DE13,CZ13,CU13) -> -0.099961311 | DP16: =AVERAGE(DP13,DK13,DF13,DA13,CV13) -> 0.018831434 | DQ16: =AVERAGE(DQ13,DL13,DG13,DB13,CW13) -> 0.12969227 | DR16: =AVERAGE(DR13,DM13,DH13,DC13,CX13) -> 0.030297756 | DT16: =AVERAGE(DT13,DO13,DJ13,DE13,CZ13) -> -0.077375003 | DU16: =AVERAGE(DU13,DP13,DK13,DF13,DA13) -> 0.011344393 | DV16: =AVERAGE(DV13,DQ13,DL13,DG13,DB13) -> 0.096300216 | DW16: =AVERAGE(DW13,DR13,DM13,DH13,DC13) -> 0.042035448 | DY16: =AVERAGE(DY13,DT13,DO13,DJ13,DE13) -> -0.076584979 | DZ16: =AVERAGE(DZ13,DU13,DP13,DK13,DF13) -> 0.014872681 | EA16: =AVERAGE(EA13,DV13,DQ13,DL13,DG13) -> 0.058309023 | EB16: =AVERAGE(EB13,DW13,DR13,DM13,DH13) -> 0.050458952 | ED16: =AVERAGE(ED13,DY13,DT13,DO13,DJ13) -> -0.069383016 | EE16: =AVERAGE(EE13,DZ13,DU13,DP13,DK13) -> -0.017722172 | EF16: =AVERAGE(EF13,EA13,DV13,DQ13,DL13) -> 0.039754269 | EG16: =AVERAGE(EG13,EB13,DW13,DR13,DM13) -> 0.022364008
B17: Guidance | CU17: $12.8B+/-$500MM | CV17: $13.2B+/-$500MM | CW17: $14.3B+/-$500MM | CX17: $14.8B+/-$500MM | CZ17: $14.0B+/-$500MM | DA17: $13.5B+/-$500MM | DB17: $14.9B+/-$500MM | DC17: $15.7B+/-$500MM | DE17: $14.8B+/-$500MM | DF17: $14.4B+/-$500MM | DG17: $15.7B+/-$500MM | DH17: $16.3B+/-$500MM | DJ17: $15B +/- $500MM | DK17: $16.3B +/- $500M | DL17: $18.1B +/- $500M | DM17: $19B | DO17: $16B | DP17: $15.6B | DQ17: $18B | DR17: $19.2B | DS17: $71B | EE17: .
B18: D&A | N18: =depAmort -> 630 | O18: =depAmort -> 674 | P18: =depAmort -> 734 | Q18: =depAmort -> 769 | R18: =depAmort -> 2807 | S18: =depAmort -> 792 | T18: =depAmort -> 791 | U18: =depAmort -> 925 | ... CC18: =depAmort -> 1529 | CD18: 1645 | CE18: =depAmort -> 6064 | CF18: 1750 | CG18: 1840.2469 | CH18: 1861.9367 | CI18: 1843 | CJ18: =depAmort -> 7522 | CK18: 1937.0467 | CL18: =1712+279 -> 1991 | CM18: =1729+292 -> 2021 | CN18: =depAmort -> 1956 | CO18: =depAmort -> 8032 | CP18: =depAmort -> 2007 | CQ18: =depAmort -> 2170 | CR18: =depAmort -> 2198 | CS18: =depAmort -> 2174 | CT18: =depAmort -> 8549 | CU18: =depAmort -> 2099 | ... FG18: =depAmort -> 17045.799
B19: COGS ex D&A (variable costs) | N19: =COGS-depAmort -> 2119 | O19: =COGS-depAmort -> 2353 | P19: =COGS-depAmort -> 2442 | Q19: =COGS-depAmort -> 2367 | R19: =COGS-depAmort -> 9281 | S19: =COGS-depAmort -> 2102 | T19: =COGS-depAmort -> 1949 | U19: =COGS-depAmort -> 2101 | ... FG19: =COGS-depAmort -> #ERROR!
B20: Cost of Revenues | N20: 2749 | O20: 3027 | P20: 3176 | Q20: =R20-SUM(N20:P20) -> 3136 | R20: 12088 | S20: 2894 | T20: 2740 | U20: 3026 | V20: 3176 | W20: 11836 | X20: 2989 | Y20: 3283 | Z20: 3148 | AA20: 3230 | AB20: =+SUM(X20:AA20) -> 12650 | AC20: 3225 | AD20: 3307 | AE20: 3553 | AF20: 3402 | AG20: =+SUM(AC20:AF20) -> 13487 | AH20: =3301 -> 3301 | AI20: =3350 -> 3350 | AJ20: 3331 | AK20: 3464 | AL20: =+SUM(AH20:AK20) -> 13446 | AM20: 3239 | AN20: 3348 | AO20: 3275 | AP20: 3185 | AQ20: =+SUM(AM20:AP20) -> 13047 | AR20: =3221 -> 3221 | AS20: 3269 | AT20: 3752 | AU20: 4221 | AV20: =SUM(AR20:AU20) -> 14463 | AW20: 3836 | AX20: 4028 | AY20: =4012-140 -> 3872 | AZ20: 3901 | BA20: =SUM(AW20:AZ20) -> 15637 | BB20: 3997 | BC20: 3838 | BD20: 4445 | BE20: 4884 | BF20: =SUM(BB20:BE20) -> 17164 | BG20: 4420 | BH20: 4605 | BI20: =4919-113 -> 4806 | BJ20: 4486 | BK20: =SUM(BG20:BJ20) -> 18317 | BL20: 4466 | BM20: 4221 | BN20: 4198 | BO20: 3857 | BP20: =SUM(BL20:BO20) -> 16742 | BQ20: 3907 | BR20: 3945 | BS20: 3985 | BT20: 3729 | BU20: =SUM(BQ20:BT20) -> 15566 | BV20: 3770 | BW20: 3530 | BX20: 3781 | BY20: =BZ20-SUM(BV20:BX20) -> 4051 | BZ20: 15132 | CA20: 4962 | CB20: 5130 | CC20: 5215 | CD20: 4935 | CE20: =SUM(CA20:CD20) -> 20242 | CF20: 4641 | CG20: 4947 | CH20: 4942 | CI20: =5660 -> 5660 | CJ20: =SUM(CF20:CI20) -> 20190 | CK20: 5514 | CL20: 5341 | CM20: 5069 | CN20: 5263 | CO20: =SUM(CK20:CN20) -> 21187 | CP20: 5138 | CQ20: 4914 | CR20: 5096 | CS20: 5100 | CT20: =SUM(CP20:CS20) -> 20248 | CU20: 5051 | CV20: 4947 | CW20: 5354 | CX20: 5324 | CY20: =SUM(CU20:CX20) -> 20676 | CZ20: 5572 | DA20: 5560 | DB20: 5795 | DC20: 6269 | DD20: =SUM(CZ20:DC20) -> 23196 | DE20: 5649 | DF20: 5665 | DG20: 6092 | DH20: 6286 | DI20: =SUM(DE20:DH20) -> 23692 | DJ20: 6335 | DK20: 6543 | DL20: 6803 | DM20: 7430 | DN20: =SUM(DJ20:DM20) -> 27111 | DO20: 6972 | DP20: 6627 | DQ20: 7895 | DR20: 8331 | DS20: =SUM(DO20:DR20) -> 29825 | DT20: 7812 | DU20: 9221 | DV20: 8592 | DW20: 8630 | DX20: =SUM(DT20:DW20) -> 34255 | DY20: 8819 | DZ20: 8425 | EA20: 8446 | EB20: 9519 | EC20: =SUM(DY20:EB20) -> 35209 | ED20: 9109 | EE20: 9734 | EF20: 8803 | EG20: 8542 | EH20: =SUM(ED20:EG20) -> 36188 | EI20: =Sales-grossProfit -> #ERROR! | EJ20: =Sales-grossProfit -> #ERROR! | EK20: =Sales-grossProfit -> #ERROR! | EL20: =Sales-grossProfit -> #ERROR! | EM20: =SUM(EI20:EL20) -> #ERROR! | EN20: =Sales-grossProfit -> #ERROR! | EO20: =Sales-grossProfit -> #ERROR! | EP20: =Sales-grossProfit -> #ERROR! | EQ20: =Sales-grossProfit -> #ERROR! | ER20: =SUM(EN20:EQ20) -> #ERROR! | ES20: =Sales-grossProfit -> #ERROR! | ET20: =Sales-grossProfit -> #ERROR! | EU20: =Sales-grossProfit -> #ERROR! | EV20: =Sales-grossProfit -> #ERROR! | EW20: =SUM(ES20:EV20) -> #ERROR! | EX20: =Sales-grossProfit -> #ERROR! | EY20: =Sales-grossProfit -> #ERROR! | EZ20: =Sales-grossProfit -> #ERROR! | FA20: =Sales-grossProfit -> #ERROR! | FB20: =SUM(EX20:FA20) -> #ERROR! | FC20: =Sales-grossProfit -> #ERROR! | FD20: =Sales-grossProfit -> #ERROR! | FE20: =Sales-grossProfit -> #ERROR! | FF20: =Sales-grossProfit -> #ERROR! | FG20: =SUM(FC20:FF20) -> #ERROR!
B21: COGS (Non-GAAP) | CP21: 5151 | CQ21: 4914 | CR21: 5096 | CS21: 5100 | CT21: =SUM(CP21:CS21) -> 20261 | CU21: =CU12-CU27 -> 4931 | CV21: =CV12-CV27 -> 4872 | CW21: =CW12-CW27 -> 5354 | CX21: =CX12-CX27 -> 5252 | CY21: =SUM(CU21:CX21) -> 20409 | CZ21: =CZ12-CZ27 -> 5146 | DA21: =DA12-DA27 -> 5164 | DB21: =DB12-DB27 -> 5560 | DC21: =DC12-DC27 -> 6037 | DD21: =SUM(CZ21:DC21) -> 21907 | DE21: =DE12-DE27 -> 5440 | DF21: =DF12-DF27 -> 5467 | DG21: =DG12-DG27 -> 5822 | DH21: =DH12-DH27 -> 5996 | DI21: =SUM(DE21:DH21) -> 22725 | DJ21: =DJ12-DJ27 -> 6060 | DK21: =DK12-DK27 -> 6268 | DL21: =DL12-DL27 -> 6527 | DM21: =DM12-DM27 -> 7151 | DN21: =SUM(DJ21:DM21) -> 26006 | DO21: =DO12-DO27 -> 6691 | DP21: =DP12-DP27 -> 6340 | DQ21: =DQ12-DQ27 -> 7607 | DR21: =DR12-DR27 -> 8063 | DS21: =SUM(DO21:DR21) -> 28701 | DT21: =DT12-DT27 -> 7523 | DU21: =DU12-DU27 -> 8919 | DV21: =DV12-DV27 -> 8282 | DW21: =DW12-DW27 -> 8320 | DX21: =SUM(DT21:DW21) -> 33044 | DY21: =DY12-DY27 -> 7717 | DZ21: =DZ12-DZ27 -> 7557 | EA21: =EA12-EA27 -> 7635 | EB21: =EB12-EB27 -> 8706 | EC21: =SUM(DY21:EB21) -> 31615 | ED21: =ED12-ED27 -> 8608 | EE21: =EE12-EE27 -> 8454 | EF21: =EF12-EF27 -> 8301 | EG21: =EG12-EG27 -> 7897 | EH21: =SUM(ED21:EG21) -> 33260 | EI21: =EI12-EI27 -> #ERROR! | EJ21: =EJ12-EJ27 -> #ERROR! | EK21: =EK12-EK27 -> #ERROR! | EL21: =EL12-EL27 -> #ERROR! | EM21: =SUM(EI21:EL21) -> #ERROR! | EN21: =EN12-EN27 -> #ERROR! | EO21: =EO12-EO27 -> #ERROR! | EP21: =EP12-EP27 -> #ERROR! | EQ21: =EQ12-EQ27 -> #ERROR! | ER21: =SUM(EN21:EQ21) -> #ERROR! | ES21: =ES12-ES27 -> #ERROR! | ET21: =ET12-ET27 -> #ERROR! | EU21: =EU12-EU27 -> #ERROR! | EV21: =EV12-EV27 -> #ERROR! | EW21: =SUM(ES21:EV21) -> #ERROR! | EX21: =EX12-EX27 -> #ERROR! | EY21: =EY12-EY27 -> #ERROR! | EZ21: =EZ12-EZ27 -> #ERROR! | FA21: =FA12-FA27 -> #ERROR! | FB21: =SUM(EX21:FA21) -> #ERROR! | FC21: =FC12-FC27 -> #ERROR! | FD21: =FD12-FD27 -> #ERROR! | FE21: =FE12-FE27 -> #ERROR! | FF21: =FF12-FF27 -> #ERROR! | FG21: =SUM(FC21:FF21) -> #ERROR!
B22: Gross profits | N22: =+N12-N20 -> 3252 | O22: =+O12-O20 -> 2900 | P22: =+P12-P20 -> 3555 | Q22: =+Q12-Q20 -> 4478 | R22: =+R12-R20 -> 14185 | S22: =+S12-S20 -> 4209 | T22: =+T12-T20 -> 4006 | U22: =+U12-U20 -> 4302 | ... AF22: =+AF12-AF20 -> 3581 | AG22: =SUM(AC22:AF22) -> 13052 | AH22: =+AH12-AH20 -> 3480 | AI22: =+AI12-AI20 -> 2969 | AJ22: =+AJ12-AJ20 -> 3173 | AK22: =+AK12-AK20 -> 3696 | AL22: =SUM(AH22:AK22) -> 13318 | AM22: =AM12-AM20 -> 3512 | AN22: =AN12-AN20 -> 3468 | AO22: =AO12-AO20 -> 4558 | AP22: =AP12-AP20 -> 5556 | AQ22: =SUM(AM22:AP22) -> 17094 | AR22: =AR12-AR20 -> 4870 | AS22: =AS12-AS20 -> 4780 | AT22: =AT12-AT20 -> 4719 | AU22: =AU12-AU20 -> 5377 | AV22: =SUM(AR22:AU22) -> 19746 | AW22: =AW12-AW20 -> 5598 | AX22: =AX12-AX20 -> 5203 | AY22: =AY12-AY20 -> 6088 | AZ22: =AZ12-AZ20 -> 6300 | BA22: =SUM(AW22:AZ22) -> 23189 | BB22: =BB12-BB20 -> 4943 | BC22: =BC12-BC20 -> 4171 | BD22: =BD12-BD20 -> 4294 | BE22: =BE12-BE20 -> 4810 | BF22: =SUM(BB22:BE22) -> 18218 | BG22: =BG12-BG20 -> 4432 | BH22: =BH12-BH20 -> 4075 | BI22: =BI12-BI20 -> 5284 | BJ22: =BJ12-BJ20 -> 6226 | BK22: =SUM(BG22:BJ22) -> 20017 | BL22: =BL12-BL20 -> 5207 | BM22: =BM12-BM20 -> 5249 | BN22: =BN12-BN20 -> 6019 | BO22: =BO12-BO20 -> 4369 | BP22: =SUM(BL22:BO22) -> 20844 | BQ22: =BQ12-BQ20 -> 3238 | BR22: =BR12-BR20 -> 4079 | BS22: =BS12-BS20 -> 5404 | BT22: =BT12-BT20 -> 6840 | BU22: =SUM(BQ22:BT22) -> 19561 | BV22: =BV12-BV20 -> 6529 | BW22: =BW12-BW20 -> 7235 | BX22: =BX12-BX20 -> 7321 | BY22: =BY12-BY20 -> 7406 | BZ22: =SUM(BV22:BY22) -> 28491 | CA22: =CA12-CA20 -> 7885 | CB22: =CB12-CB20 -> 7902 | CC22: =CC12-CC20 -> 9018 | CD22: =CD12-CD20 -> 8952 | CE22: =SUM(CA22:CD22) -> 33757 | CF22: =CF12-CF20 -> 8265 | CG22: =CG12-CG20 -> 8554 | CH22: =CH12-CH20 -> 8515 | CI22: =CI12-CI20 -> 7817 | CJ22: =SUM(CF22:CI22) -> 33151 | CK22: =CK12-CK20 -> 7066 | CL22: =CL12-CL20 -> 7470 | CM22: =CM12-CM20 -> 8414 | CN22: =CN12-CN20 -> 8571 | CO22: =SUM(CK22:CN22) -> 31521 | CP22: =CP12-CP20 -> 7626 | CQ22: =CQ12-CQ20 -> 8917 | CR22: =CR12-CR20 -> 9458 | CS22: =CS12-CS20 -> 9621 | CT22: =SUM(CP22:CS22) -> 35622 | CU22: =CU12-CU20 -> 7730 | CV22: =CV12-CV20 -> 8248 | CW22: =CW12-CW20 -> 9111 | CX22: =CX12-CX20 -> 9590 | CY22: =SUM(CU22:CX22) -> 34679 | CZ22: =CZ12-CZ20-99 -> 8130 | DA22: =DA12-DA20 -> 7973 | DB22: =DB12-DB20 -> 9983 | DC22: =DC12-DC20 -> 10105 | DD22: =SUM(CZ22:DC22) -> 36191 | DE22: =DE12-DE20 -> 9147 | DF22: =DF12-DF20 -> 9098 | DG22: =DG12-DG20 -> 10057 | DH22: =DH12-DH20 -> 10767 | DI22: =SUM(DE22:DH22) -> 39069 | DJ22: =DJ12-DJ20 -> 9731 | DK22: =DK12-DK20 -> 10419 | DL22: =DL12-DL20 -> 12360 | DM22: =DM12-DM20 -> 11227 | DN22: =SUM(DJ22:DM22) -> 43737 | DO22: =DO12-DO20 -> 9089 | DP22: =DP12-DP20 -> 9878 | DQ22: =DQ12-DQ20 -> 11295 | DR22: =DR12-DR20 -> 11878 | DS22: =SUM(DO22:DR22) -> 42140 | DT22: =DT12-DT20 -> 12016 | DU22: =DU12-DU20 -> 10507 | DV22: =DV12-DV20 -> 9741 | DW22: =DW12-DW20 -> 11348 | DX22: =SUM(DT22:DW22) -> 43612 | DY22: =DY11-DY20 -> 10854 | DZ22: =DZ11-DZ20 -> 11206 | EA22: =EA11-EA20 -> 10746 | EB22: =EB11-EB20 -> 11009 | EC22: =SUM(DY22:EB22) -> 43815 | ED22: =ED11-ED20 -> 9244 | EE22: =EE11-EE20 -> 5587 | EF22: =EF11-EF20 -> 6535 | EG22: =EG11-EG20 -> 5500 | EH22: =SUM(ED22:EG22) -> 26866 | EI22: =EI27-EI88*0.5 -> #ERROR! | EJ22: =EJ27-EJ88*0.5 -> #ERROR! | EK22: =EK27-EK88*0.5 -> #ERROR! | EL22: =EL27-EL88*0.5 -> #ERROR! | EM22: =SUM(EI22:EL22) -> #ERROR! | EN22: =EN27-EN88*0.5 -> #ERROR! | EO22: =EO27-EO88*0.5 -> #ERROR! | EP22: =EP27-EP88*0.5 -> #ERROR! | EQ22: =EQ27-EQ88*0.5 -> #ERROR! | ER22: =SUM(EN22:EQ22) -> #ERROR! | ES22: =ES27-ES88*0.5 -> #ERROR! | ET22: =ET27-ET88*0.5 -> #ERROR! | EU22: =EU27-EU88*0.5 -> #ERROR! | EV22: =EV27-EV88*0.5 -> #ERROR! | EW22: =SUM(ES22:EV22) -> #ERROR! | EX22: =EX27-EX88*0.5 -> #ERROR! | EY22: =EY27-EY88*0.5 -> #ERROR! | EZ22: =EZ27-EZ88*0.5 -> #ERROR! | FA22: =FA27-FA88*0.5 -> #ERROR! | FB22: =SUM(EX22:FA22) -> #ERROR! | FC22: =FC27-FC88*0.5 -> #ERROR! | FD22: =FD27-FD88*0.5 -> #ERROR! | FE22: =FE27-FE88*0.5 -> #ERROR! | FF22: =FF27-FF88*0.5 -> #ERROR! | FG22: =SUM(FC22:FF22) -> #ERROR!
B23: Gross Margin (GAAP) | CZ23: =(CZ22+(CZ62)/(1-CZ110))/CZ12 -> 0.58908775 | DA23: =(DA22+(DA62)/(1-DA110))/DA12 -> 0.58915244 | DB23: =(DB22+(DB62)/(1-DB110))/DB12 -> 0.63271644 | DC23: =(DC22+(DC62)/(1-DC110))/DC12 -> 0.61713692 | DD23: =(DD22+(DD62)/(1-DD110))/DD12 -> 0.60839525 | DE23: =(DE22+(DE62)/(1-DE110))/DE12 -> 0.61820762 | DF23: =(DF22+(DF62)/(1-DF110))/DF12 -> 0.61627041 | DG23: =(DG22+(DG62)/(1-DG110))/DG12 -> 0.62276302 | ... DW23: =(DW22+(DW62)/(1-DW110))/DW12 -> 0.56802483 | DX23: =DX22/DX12 -> 0.56008322 | DY23: =(DY22+(DY62)/(1-DY110))/DY12 -> 0.58461704 | DZ23: =(DZ22+(DZ62)/(1-DZ110))/DZ12 -> 0.60465116 | EA23: =(EA22+(EA62)/(1-EA110))/EA12 -> 0.59412838 | EB23: =(EB22+(EB62)/(1-EB110))/EB12 -> 0.56363916 | EC23: =EC22/EC11 -> 0.55445181 | ED23: =(ED22+(ED62)/(1-ED110))/ED12 -> 0.50367787 | EE23: =(EE22+(EE62)/(1-EE110))/EE12 -> 0.36466288 | EF23: =(EF22+(EF62)/(1-EF110))/EF12 -> 0.42606598 | EG23: =(EG22+(EG62)/(1-EG110))/EG12 -> 0.3916821 | EH23: =EH22/EH11 -> 0.42607923 | EI23: =EI22/EI11 -> #ERROR! | EJ23: =EJ22/EJ11 -> #ERROR! | EK23: =EK22/EK11 -> #ERROR! | EL23: =EL22/EL11 -> #ERROR! | EM23: =EM22/EM11 -> #ERROR! | EN23: =EN22/EN11 -> #ERROR! | EO23: =EO22/EO11 -> #ERROR! | ... FG23: =FG22/FG11 -> #ERROR!
B24: Deferred Revenue Write down | CZ24: 64
B25: Inventory valuation | CZ25: 226 | DA25: 161 | DD25: =SUM(CZ25:DC25) -> 387 | DG25: 27 | DH25: 28 | DI25: =SUM(DE25:DH25) -> 55
B26: SBC COGS + Amort. Of Acq. Related Intangibles | CP26: =CP20-CP21 -> -13 | CU26: 120 | CV26: 75 | CX26: 72 | CY26: =SUM(CU26:CX26) -> 267 | CZ26: 235 | DA26: 235 | DB26: 235 | DC26: 232 | DD26: =SUM(CZ26:DC26) -> 937 | DE26: 209 | DF26: 198 | DG26: 243 | DH26: 262 | DI26: =SUM(DE26:DH26) -> 912 | DJ26: 275 | DK26: 275 | DL26: 276 | DM26: 279 | DN26: =SUM(DJ26:DM26) -> 1105 | DO26: 281 | DP26: 287 | DQ26: 288 | DR26: 268 | DS26: =SUM(DO26:DR26) -> 1124 | DT26: 289 | DU26: 302 | DV26: 310 | DW26: 310 | DX26: =SUM(DT26:DW26) -> 1211 | DY26: =312-317 -> -5 | DZ26: =314-544 -> -230 | EA26: =322-616 -> -294 | EB26: =335-518 -> -183 | EC26: =SUM(DY26:EB26) -> -712 | ED26: =353+148 -> 501 | EE26: =329+188+204+559 -> 1280 | EF26: =330+172 -> 502 | EG26: =329+152+164 -> 645 | EH26: =SUM(ED26:EG26) -> 2928 | EI26: =EI27-EI22 -> #ERROR! | EJ26: =EJ27-EJ22 -> #ERROR! | EK26: =EK27-EK22 -> #ERROR! | EL26: =EL27-EL22 -> #ERROR! | EM26: =SUM(EI26:EL26) -> #ERROR! | EN26: =EN27-EN22 -> #ERROR! | EO26: =EO27-EO22 -> #ERROR! | EP26: =EP27-EP22 -> #ERROR! | EQ26: =EQ27-EQ22 -> #ERROR! | ER26: =SUM(EN26:EQ26) -> #ERROR! | ES26: =ES27-ES22 -> #ERROR! | ET26: =ET27-ET22 -> #ERROR! | EU26: =EU27-EU22 -> #ERROR! | EV26: =EV27-EV22 -> #ERROR! | EW26: =SUM(ES26:EV26) -> #ERROR! | EX26: =EX27-EX22 -> #ERROR! | EY26: =EY27-EY22 -> #ERROR! | EZ26: =EZ27-EZ22 -> #ERROR! | FA26: =FA27-FA22 -> #ERROR! | FB26: =SUM(EX26:FA26) -> #ERROR! | FC26: =FC27-FC22 -> #ERROR! | FD26: =FD27-FD22 -> #ERROR! | FE26: =FE27-FE22 -> #ERROR! | FF26: =FF27-FF22 -> #ERROR! | FG26: =SUM(FC26:FF26) -> #ERROR!
B27: Gross Profit (Non -GAAP) | CP27: =CP12-CP21 -> 7613 | CQ27: =CQ12-CQ21 -> 8917 | CR27: =CR12-CR21 -> 9458 | CS27: =CS12-CS21 -> 9621 | CT27: =SUM(CP27:CS27) -> 35609 | CU27: =CU22+CU24+CU25+CU26 -> 7850 | CV27: =CV22+CV24+CV25+CV26 -> 8323 | CW27: =CW22+CW24+CW25+CW26 -> 9111 | CX27: =CX22+CX24+CX25+CX26 -> 9662 | CY27: =SUM(CU27:CX27) -> 34946 | CZ27: =CZ22+CZ24+CZ25+CZ26 -> 8655 | DA27: =DA22+DA24+DA25+DA26 -> 8369 | DB27: =DB22+DB24+DB25+DB26 -> 10218 | DC27: =DC22+DC24+DC25+DC26 -> 10337 | DD27: =SUM(CZ27:DC27) -> 37579 | DE27: =DE22+DE24+DE25+DE26 -> 9356 | DF27: =DF22+DF24+DF25+DF26 -> 9296 | DG27: =DG22+DG24+DG25+DG26 -> 10327 | DH27: =DH22+DH24+DH25+DH26 -> 11057 | DI27: =SUM(DE27:DH27) -> 40036 | DJ27: =DJ22+DJ24+DJ25+DJ26 -> 10006 | DK27: =DK22+DK24+DK25+DK26 -> 10694 | DL27: =DL22+DL24+DL25+DL26 -> 12636 | DM27: =DM22+DM24+DM25+DM26 -> 11506 | DN27: =SUM(DJ27:DM27) -> 44842 | DO27: =DO22+DO24+DO25+DO26 -> 9370 | DP27: =DP22+DP24+DP25+DP26 -> 10165 | DQ27: =DQ22+DQ24+DQ25+DQ26 -> 11583 | DR27: =DR22+DR24+DR25+DR26 -> 12146 | DS27: =SUM(DO27:DR27) -> 43264 | DT27: =DT22+DT24+DT25+DT26 -> 12305 | DU27: =DU22+DU24+DU25+DU26 -> 10809 | DV27: =DV22+DV24+DV25+DV26 -> 10051 | DW27: =DW22+DW24+DW25+DW26 -> 11658 | DX27: =SUM(DT27:DW27) -> 44823 | DY27: =DY22+DY26 -> 10849 | DZ27: =DZ22+DZ26 -> 10976 | EA27: =EA22+EA26 -> 10452 | EB27: =EB22+EB26 -> 10826 | EC27: =SUM(DY27:EB27) -> 43103 | ED27: =ED22+ED26 -> 9745 | EE27: =EE22+EE26 -> 6867 | EF27: =EF22+EF26 -> 7037 | EG27: =EG22+EG26 -> 6145 | EH27: =SUM(ED27:EG27) -> 29794 | EI27: =EI12*EI28 -> #ERROR! | EJ27: =EJ12*EJ28 -> #ERROR! | EK27: =EK12*EK28 -> #ERROR! | EL27: =EL12*EL28 -> #ERROR! | EM27: =SUM(EI27:EL27) -> #ERROR! | EN27: =EN12*EN28 -> #ERROR! | EO27: =EO12*EO28 -> #ERROR! | EP27: =EP12*EP28 -> #ERROR! | EQ27: =EQ12*EQ28 -> #ERROR! | ER27: =SUM(EN27:EQ27) -> #ERROR! | ES27: =ES12*ES28 -> #ERROR! | ET27: =ET12*ET28 -> #ERROR! | EU27: =EU12*EU28 -> #ERROR! | EV27: =EV12*EV28 -> #ERROR! | EW27: =SUM(ES27:EV27) -> #ERROR! | EX27: =EX12*EX28 -> #ERROR! | EY27: =EY12*EY28 -> #ERROR! | EZ27: =EZ12*EZ28 -> #ERROR! | FA27: =FA12*FA28 -> #ERROR! | FB27: =SUM(EX27:FA27) -> #ERROR! | FC27: =FC12*FC28 -> #ERROR! | FD27: =FD12*FD28 -> #ERROR! | FE27: =FE12*FE28 -> #ERROR! | FF27: =FF12*FF28 -> #ERROR! | FG27: =SUM(FC27:FF27) -> #ERROR!
B28: GM% (Non -GAAP) | CP28: =CP27/CP12 -> 0.59644312 | CQ28: =CQ27/CQ12 -> 0.64471116 | CR28: =CR27/CR12 -> 0.64985571 | CS28: =CS27/CS12 -> 0.65355614 | CT28: =CT27/CT12 -> 0.63735457 | CU28: =CU27/CU12 -> 0.61419294 | CV28: =CV27/CV12 -> 0.63076923 | CW28: =CW27/CW12 -> 0.62986519 | ... EH28: =EH27/EH12 -> 0.47251562 | EI28: 0.39 | EJ28: 0.39 | EK28: 0.42 | EL28: 0.47 | EM28: =EM27/EM12 -> #ERROR! | EN28: 0.47 | EO28: 0.47 | EP28: 0.47 | EQ28: 0.475 | ER28: =ER27/ER12 -> #ERROR! | ES28: 0.49 | ET28: 0.5 | EU28: 0.5 | EV28: 0.51 | EW28: =EW27/EW12 -> #ERROR! | EX28: 0.52 | EY28: 0.52 | EZ28: 0.52 | FA28: 0.53 | FB28: =FB27/FB12 -> #ERROR! | FC28: 0.54 | FD28: 0.54 | FE28: 0.54 | FF28: 0.55 | FG28: =FG27/FG12 -> #ERROR!
B29: Y/Y GM Drop Through | CP29: =(CP27-CK27)/(CP12-CK12) -> 41.375 | CQ29: =(CQ27-CL27)/(CQ12-CL12) -> 8.7421569 | CR29: =(CR27-CM27)/(CR12-CM12) -> 8.8309991 | CS29: =(CS27-CN27)/(CS12-CN12) -> 10.846674 | CU29: =(CU27-CP27)/(CU12-CP12) -> 13.941176 | CV29: =(CV27-CQ27)/(CV12-CQ12) -> 0.93396226 | CW29: =(CW27-CR27)/(CW12-CR12) -> 3.8988764 | CX29: =(CX27-CS27)/(CX12-CS12) -> 0.21243523 | CZ29: =(CZ27-CU27)/(CZ12-CU12) -> 0.78921569 | DA29: =(DA27-CV27)/(DA12-CV12) -> 0.13609467 | DB29: =(DB27-CW27)/(DB12-CW12) -> 0.84310739 | DC29: =(DC27-CX27)/(DC12-CX12) -> 0.46232877 | DE29: =(DE27-CZ27)/(DE12-CZ12) -> 0.70452261 | DF29: =(DF27-DA27)/(DF12-DA12) -> 0.75365854 | DG29: =(DG27-DB27)/(DG12-DB12) -> 0.29380054 | DH29: =(DH27-DC27)/(DH12-DC12) -> 1.0603829 | DJ29: =(DJ27-DE27)/(DJ12-DE12) -> 0.51181102 | DK29: =(DK27-DF27)/(DK12-DF12) -> 0.63574352 | DL29: =(DL27-DG27)/(DL12-DG12) -> 0.76609157 | DM29: =(DM27-DH27)/(DM12-DH12) -> 0.27992519 | DO29: =(DO27-DJ27)/(DO12-DJ12) -> 127.2 | DP29: =(DP27-DK27)/(DP12-DK12) -> 1.1575492 | DQ29: =(DQ27-DL27)/(DQ12-DL12) -> -39 | DR29: =(DR27-DM27)/(DR12-DM12) -> 0.41237113 | DT29: =(DT27-DO27)/(DT12-DO12) -> 0.77913459 | DU29: =(DU27-DP27)/(DU12-DP12) -> 0.19981384 | DV29: =(DV27-DQ27)/(DV12-DQ12) -> 1.7876313 | DW29: =(DW27-DR27)/(DW12-DR12) -> 2.1125541 | DY29: =(DY27-DT27)/(DY12-DT12) -> 1.1537242 | DZ29: =(DZ27-DU27)/(DZ12-DU12) -> -0.13974895 | EA29: =(EA27-DV27)/(EA12-DV12) -> -1.6300813 | EB29: =(EB27-DW27)/(EB12-DW12) -> 1.8654709 | ED29: =(ED27-DY27)/(ED12-DY12) -> 5.1830986 | EE29: =(EE27-DZ27)/(EE12-DZ12) -> 1.2792653 | EF29: =(EF27-EA27)/(EF12-EA12) -> 1.2422699 | EG29: =(EG27-EB27)/(EG12-EB12) -> 0.85264117 | EI29: =(EI27-ED27)/(EI12-ED12) -> #ERROR! | EJ29: =(EJ27-EE27)/(EJ12-EE12) -> #ERROR! | EK29: =(EK27-EF27)/(EK12-EF12) -> #ERROR! | EL29: =(EL27-EG27)/(EL12-EG12) -> #ERROR! | EN29: =(EN27-EI27)/(EN12-EI12) -> #ERROR! | EO29: =(EO27-EJ27)/(EO12-EJ12) -> #ERROR! | EP29: =(EP27-EK27)/(EP12-EK12) -> #ERROR! | EQ29: =(EQ27-EL27)/(EQ12-EL12) -> #ERROR! | ES29: =(ES27-EN27)/(ES12-EN12) -> #ERROR! | ET29: =(ET27-EO27)/(ET12-EO12) -> #ERROR! | EU29: =(EU27-EP27)/(EU12-EP12) -> #ERROR! | EV29: =(EV27-EQ27)/(EV12-EQ12) -> #ERROR! | EX29: =(EX27-ES27)/(EX12-ES12) -> #ERROR! | EY29: =(EY27-ET27)/(EY12-ET12) -> #ERROR! | EZ29: =(EZ27-EU27)/(EZ12-EU12) -> #ERROR! | FA29: =(FA27-EV27)/(FA12-EV12) -> #ERROR! | FC29: =(FC27-EX27)/(FC12-EX12) -> #ERROR! | FD29: =(FD27-EY27)/(FD12-EY12) -> #ERROR! | FE29: =(FE27-EZ27)/(FE12-EZ12) -> #ERROR! | FF29: =(FF27-FA27)/(FF12-FA12) -> #ERROR!
B30: GM% (Non -GAAP) - Guidance | DE30: 0.63 | DF30: 0.63 | DG30: 0.63 | DH30: 0.63 | DJ30: 0.6
B31: R&D expenses | N31: 595 | O31: 623 | P31: 617 | Q31: 674 | R31: =+SUM(N31:Q31) -> 2509 | S31: 663 | T31: 731 | U31: 840 | V31: 877 | W31: =+SUM(S31:V31) -> 3111 | X31: 951 | Y31: 971 | Z31: 977 | AA31: 998 | AB31: =+SUM(X31:AA31) -> 3897 | AC31: 995 | AD31: 919 | AE31: 930 | AF31: 952 | AG31: =+SUM(AC31:AF31) -> 3796 | AH31: 982 | AI31: 1024 | AJ31: 1006 | AK31: 1022 | AL31: =+SUM(AH31:AK31) -> 4034 | AM31: 1019 | AN31: 1029 | AO31: 1135 | AP31: 1177 | AQ31: =+SUM(AM31:AP31) -> 4360 | AR31: 1195 | AS31: 1186 | AT31: 1183 | AU31: 1214 | AV31: =+SUM(AR31:AU31) -> 4778 | AW31: 1266 | AX31: 1176 | AY31: 1341 | AZ31: 1362 | BA31: =+SUM(AW31:AZ31) -> 5145 | BB31: 1562 | BC31: 1496 | BD31: 1389 | BE31: 1426 | BF31: =SUM(BB31:BE31) -> 5873 | BG31: 1400 | BH31: 1353 | BI31: =1526-5 -> 1521 | BJ31: 1481 | BK31: =SUM(BG31:BJ31) -> 5755 | BL31: 1467 | BM31: 1468 | BN31: 1471 | BO31: 1316 | BP31: =SUM(BL31:BO31) -> 5722 | BQ31: 1317 | BR31: 1303 | BS31: 1430 | BT31: 1603 | BU31: =(SUM(BQ31:BT31))-0.002 -> 5652.998 | BV31: 1564 | BW31: 1666 | BX31: 1675 | BY31: 1671 | BZ31: =SUM(BV31:BY31) -> 6576 | CA31: 1916 | CB31: 1986 | CC31: 2140 | CD31: 2308 | CE31: =SUM(CA31:CD31) -> 8350 | CF31: 2401 | CG31: 2513 | CH31: 2605 | CI31: 2629 | CJ31: =SUM(CF31:CI31) -> 10148 | CK31: 2527 | CL31: 2516 | CM31: 2742 | CN31: 2826 | CO31: =SUM(CK31:CN31) -> 10611 | CP31: 2846 | CQ31: 2859 | CR31: 2842 | CS31: 2990 | CT31: =SUM(CP31:CS31) -> 11537 | CU31: 2995 | CV31: 3087 | CW31: 2927 | CX31: 3119 | CY31: =SUM(CU31:CX31) -> 12128 | CZ31: 3246 | DA31: 3145 | DB31: 3069 | DC31: 3280 | DD31: =SUM(CZ31:DC31) -> 12740 | DE31: 3326 | DF31: 3275 | DG31: 3223 | DH31: 3274 | DI31: =SUM(DE31:DH31) -> 13098 | DJ31: 3311 | DK31: 3371 | DL31: 3428 | DM31: 3433 | DN31: =SUM(DJ31:DM31) -> 13543 | DO31: 3332 | DP31: 3438 | DQ31: 3208 | DR31: 3384 | DS31: =SUM(DO31:DR31) -> 13362 | DT31: 3275 | DU31: 3354 | DV31: 3272 | DW31: 3655 | DX31: =SUM(DT31:DW31) -> 13556 | DY31: 3623 | DZ31: 3715 | EA31: 3803 | EB31: 4049 | EC31: =SUM(DY31:EB31) -> 15190 | ED31: 4362 | EE31: 4400 | EF31: 4302 | EG31: 4464 | EH31: =SUM(ED31:EG31) -> 17528 | EI31: 3900 | EJ31: 3650 | EK31: 3400 | EL31: 3100 | EM31: =SUM(EI31:EL31) -> 14050 | EN31: 3100 | EO31: 3300 | EP31: 3400 | EQ31: 3500 | ER31: =SUM(EN31:EQ31) -> 13300 | ES31: 3550 | ET31: 3600 | EU31: 3650 | EV31: 3700 | EW31: =SUM(ES31:EV31) -> 14500 | EX31: 3800 | EY31: 3900 | EZ31: 3900 | FA31: 3900 | FB31: =SUM(EX31:FA31) -> 15500 | FC31: 3900 | FD31: 4000 | FE31: 4000 | FF31: 4000 | FG31: =SUM(FC31:FF31) -> 15900
B32: MG&A expenses | N32: 711 | O32: 671 | P32: 766 | Q32: 928 | R32: =+SUM(N32:Q32) -> 3076 | S32: 891 | T32: 924 | U32: 952 | V32: 1105 | W32: =+SUM(S32:V32) -> 3872 | X32: 1124 | Y32: 1223 | Z32: 1321 | AA32: 1421 | AB32: =+SUM(X32:AA32) -> 5089 | AC32: 1155 | AD32: 1174 | AE32: 1064 | AF32: 1071 | AG32: =+SUM(AC32:AF32) -> 4464 | AH32: 1072 | AI32: 1063 | AJ32: 1095 | AK32: 1104 | AL32: =+SUM(AH32:AK32) -> 4334 | AM32: 1018 | AN32: 1079 | AO32: 1046 | AP32: =AQ32-SUM(AM32:AO32) -> 1135 | AQ32: 4278 | AR32: 1141 | AS32: 1170 | AT32: 1123 | AU32: 1225 | AV32: =+SUM(AR32:AU32) -> 4659 | AW32: 1262 | AX32: 1342 | AY32: 1478 | AZ32: 1606 | BA32: =+SUM(AW32:AZ32) -> 5688 | BB32: 1644 | BC32: 1593 | BD32: 1425 | BE32: 1434 | BF32: =+SUM(BB32:BE32) -> 6096 | BG32: 1277 | BH32: 1284 | BI32: =1383-5 -> 1378 | BJ32: 1462 | BK32: =+SUM(BG32:BJ32) -> 5401 | BL32: 1349 | BM32: 1430 | BN32: 1416 | BO32: 1263 | BP32: =+SUM(BL32:BO32) -> 5458 | BQ32: 1200 | BR32: 1250 | BS32: 1320 | BT32: 1468 | BU32: =(+SUM(BQ32:BT32))-0.002 -> 5237.998 | BV32: 1514 | BW32: 1584 | BX32: 1506 | BY32: 1705 | BZ32: =+SUM(BV32:BY32) -> 6309 | CA32: 1775 | CB32: 1905 | CC32: 2017 | CD32: 1973 | CE32: =+SUM(CA32:CD32) -> 7670 | CF32: 1973 | CG32: 2131 | CH32: 1995 | CI32: 1958 | CJ32: =+SUM(CF32:CI32) -> 8057 | CK32: 1947 | CL32: 2165 | CM32: 1970 | CN32: 2006 | CO32: =+SUM(CK32:CN32) -> 8088 | CP32: 2037 | CQ32: 2061 | CR32: 1979 | CS32: 2049 | CT32: =+SUM(CP32:CS32) -> 8126 | CU32: 1953 | CV32: 1949 | CW32: 1910 | CX32: 2118 | CY32: =+SUM(CU32:CX32) -> 7930 | CZ32: 2226 | DA32: 2007 | DB32: 2006 | DC32: 2158 | DD32: =+SUM(CZ32:DC32) -> 8397 | DE32: 2104 | DF32: 1854 | DG32: 1666 | DH32: 1850 | DI32: =+SUM(DE32:DH32) -> 7474 | DJ32: 1900 | DK32: 1725 | DL32: 1605 | DM32: 1520 | DN32: =+SUM(DJ32:DM32) -> 6750 | DO32: 1533 | DP32: 1589 | DQ32: 1486 | DR32: 1542 | DS32: =+SUM(DO32:DR32) -> 6150 | DT32: 1541 | DU32: 1447 | DV32: 1435 | DW32: 1757 | DX32: =+SUM(DT32:DW32) -> 6180 | DY32: 1328 | DZ32: 1599 | EA32: 1674 | EB32: 1942 | EC32: =+SUM(DY32:EB32) -> 6543 | ED32: 1752 | EE32: 1800 | EF32: 1744 | EG32: 1706 | EH32: =+SUM(ED32:EG32) -> 7002 | EI32: 1600 | EJ32: 1500 | EK32: 1400 | EL32: 1400 | EM32: =+SUM(EI32:EL32) -> 5900 | EN32: 1400 | EO32: 1300 | EP32: 1300 | EQ32: 1250 | ER32: =+SUM(EN32:EQ32) -> 5250 | ES32: 1250 | ET32: 1250 | EU32: =ET32 -> 1250 | EV32: =EU32 -> 1250 | EW32: =+SUM(ES32:EV32) -> 5000 | EX32: =EV32+50 -> 1300 | EY32: =EX32+50 -> 1350 | EZ32: =EY32+50 -> 1400 | FA32: =EZ32+50 -> 1450 | FB32: =+SUM(EX32:FA32) -> 5500 | FC32: =FA32+50 -> 1500 | FD32: =FC32+50 -> 1550 | FE32: =FD32+50 -> 1600 | FF32: =FE32+50 -> 1650 | FG32: =+SUM(FC32:FF32) -> 6300
B33: Amortization/ other GAAP adj | X33: 0 | Y33: 0 | Z33: 0 | AA33: 0 | AB33: =SUM(X33:AA33) -> 0 | AC33: 0 | AD33: 0 | AE33: 0 | AF33: 0 | AG33: =SUM(AC33:AF33) -> 0 | AH33: 0 | AI33: 0 | AJ33: 0 | AK33: 0 | AL33: 0 | AM33: 84 | AN33: 84 | AO33: =68+5 -> 73 | AP33: 65 | AR33: 58 | AS33: 43 | AT33: 40 | AU33: 38 | AV33: =SUM(AR33:AU33) -> 179 | AW33: 38 | AX33: 36 | AY33: 29 | AZ33: 23 | BA33: =SUM(AW33:AZ33) -> 126 | BB33: 19 | BC33: 10 | BD33: =98+8 -> 106 | BE33: =457+5 -> 462 | BF33: =SUM(BB33:BE33) -> 597 | BG33: =75+5 -> 80 | BH33: =82+6 -> 88 | BI33: =125+3 -> 128 | BJ33: =234+2 -> 236 | BK33: =SUM(BG33:BJ33) -> 532 | BL33: 329 | BM33: 96 | BN33: 34 | BO33: 251 | BP33: =SUM(BL33:BO33) -> 710 | BQ33: 74 | BR33: 91 | BS33: =63+12 -> 75 | BT33: =3+19 -> 22 | BU33: =SUM(BQ33:BT33) -> 262 | BV33: 3 | BW33: 4 | BX33: 4 | BY33: 7 | BZ33: =SUM(BV33:BY33) -> 18 | CA33: 36 | CB33: 76 | CC33: 76 | CD33: 72 | CE33: =SUM(CA33:CD33) -> 260 | CF33: 81 | CG33: 78 | CH33: 74 | CI33: 75 | CJ33: =SUM(CF33:CI33) -> 308 | CK33: 73 | CL33: 70 | CM33: =124+74 -> 198 | CN33: =74+116 -> 190 | CO33: =SUM(CK33:CN33) -> 531 | CP33: 73 | CQ33: =81+72 -> 153 | CR33: =20+77 -> 97 | CS33: =72+57 -> 129 | CT33: =+CS33+CR33+CQ33+CP33 -> 452 | CU33: 62 | CV33: =248+68 -> 316 | CW33: =14+68 -> 82 | CX33: =-13+67 -> 54 | CY33: =SUM(CU33:CX33) -> 514 | CZ33: 90 | DA33: =1414+89 -> 1503 | DB33: 74 | DC33: 41 | DD33: =SUM(CZ33:DC33) -> 1708 | DE33: 38 | DF33: =235-198 -> 37 | DG33: 49 | DH33: 53 | DI33: =SUM(DE33:DH33) -> 177 | DJ33: 50 | DK33: 50 | DL33: 50 | DM33: 50 | DN33: =SUM(DJ33:DM33) -> 200 | DO33: 50 | DP33: 50 | DQ33: 50 | DR33: 50 | DS33: =SUM(DO33:DR33) -> 200 | DX33: =SUM(DT33:DW33) -> 0 | DY33: 500 | DZ33: 346 | EA33: 0 | EB33: 0 | EC33: =SUM(DY33:EB33) -> 846 | EH33: =SUM(ED33:EG33) -> 0 | EM33: =SUM(EI33:EL33) -> 0 | ER33: =SUM(EN33:EQ33) -> 0 | EW33: =SUM(ES33:EV33) -> 0 | FB33: =SUM(EX33:FA33) -> 0 | FG33: =SUM(FC33:FF33) -> 0
B34: Restructuring & other | CP34: 137 | CU34: 105 | DB34: 372 | DC34: 100 | DD34: =SUM(CZ34:DC34) -> 472 | DE34: 80 | DF34: 105 | DG34: 4 | DH34: 195 | DI34: =SUM(DE34:DH34) -> 384 | DL34: -72 | DN34: =SUM(DJ34:DM34) -> -72 | DP34: 184 | DQ34: 104 | DR34: 105 | DS34: =SUM(DO34:DR34) -> 393 | DT34: 162 | DU34: 9 | DV34: -25 | DW34: 52 | DX34: =SUM(DT34:DW34) -> 198 | DY34: =2209-DY33 -> 1709 | DZ34: 0 | EA34: 42 | EB34: 29 | EC34: =SUM(DY34:EB34) -> 1780 | ED34: -1211 | EE34: 87 | EF34: 664 | EG34: 462 | EH34: =SUM(ED34:EG34) -> 2 | EM34: =SUM(EI34:EL34) -> 0 | ER34: =SUM(EN34:EQ34) -> 0 | EW34: =SUM(ES34:EV34) -> 0 | FB34: =SUM(EX34:FA34) -> 0 | FG34: =SUM(FC34:FF34) -> 0
B35: Other acq. Related Charges | CY35: =SUM(CU35:CX35) -> 0 | CZ35: -100 | DD35: =SUM(CZ35:DC35) -> -100 | DG35: -113 | DI35: =SUM(DE35:DH35) -> -113 | DK35: =-235+494 -> 259 | DN35: =SUM(DJ35:DM35) -> 259 | DS35: =SUM(DO35:DR35) -> 0 | DU35: -50 | DV35: -52 | DW35: -53 | DX35: =SUM(DT35:DW35) -> -155 | DY35: =-146-52 -> -198 | DZ35: =-52-142 -> -194 | EA35: =-53-174 -> -227 | EB35: =-52-164 -> -216 | EC35: =SUM(DY35:EB35) -> -835 | ED35: =-51-559 -> -610 | EE35: =-48-702 -> -750 | EF35: =-43-621 -> -664 | EG35: =-43-584 -> -627 | EH35: =SUM(ED35:EG35) -> -2651 | EM35: =SUM(EI35:EL35) -> 0 | ER35: =SUM(EN35:EQ35) -> 0 | EW35: =SUM(ES35:EV35) -> 0 | FB35: =SUM(EX35:FA35) -> 0 | FG35: =SUM(FC35:FF35) -> 0
B36: Total operating expenses | N36: =+SUM(N31:N32) -> 1306 | O36: =+SUM(O31:O32) -> 1294 | P36: =+SUM(P31:P32) -> 1383 | Q36: =+SUM(Q31:Q32) -> 1602 | R36: =+SUM(R31:R32) -> 5585 | S36: =+SUM(S31:S32) -> 1554 | T36: =+SUM(T31:T32) -> 1655 | U36: =+SUM(U31:U32) -> 1792 | ... W36: =+SUM(W31:W32) -> 6983 | X36: =RD+MGA -> 2075 | Y36: =RD+MGA -> 2194 | Z36: =RD+MGA -> 2298 | AA36: =RD+MGA -> 2419 | AB36: =+SUM(X36:AA36) -> 8986 | AC36: =RD+MGA -> 2150 | AD36: =RD+MGA -> 2093 | AE36: =RD+MGA -> 1994 | AF36: =RD+MGA -> 2023 | AG36: =+SUM(AC36:AF36) -> 8260 | AH36: =+SUM(AH31:AH33) -> 2054 | AI36: =+SUM(AI31:AI33) -> 2087 | AJ36: =+SUM(AJ31:AJ33) -> 2101 | AK36: =+SUM(AK31:AK33) -> 2126 | AL36: =+SUM(AH36:AK36) -> 8368 | AM36: =SUM(AM31,AM32,AM33) -> 2121 | AN36: =SUM(AN31,AN32,AN33) -> 2192 | AO36: =SUM(AO31,AO32,AO33) -> 2254 | AP36: =SUM(AP31,AP32,AP33) -> 2377 | AQ36: =+SUM(AM36:AP36) -> 8944 | AR36: =SUM(AR31,AR32,AR33) -> 2394 | AS36: =SUM(AS31,AS32,AS33) -> 2399 | AT36: =SUM(AT31,AT32,AT33) -> 2346 | AU36: =SUM(AU31,AU32,AU33) -> 2477 | AV36: =SUM(AV31,AV32,AV33) -> 9616 | AW36: =SUM(AW31,AW32,AW33) -> 2566 | AX36: =SUM(AX31,AX32,AX33) -> 2554 | AY36: =SUM(AY31,AY32,AY33) -> 2848 | ... CO36: =SUM(CO31,CO32,CO33) -> 19230 | CP36: =SUM(CP31,CP32,CP33,CP34) -> 5093 | CQ36: =SUM(CQ31,CQ32,CQ33,CQ34) -> 5073 | CR36: =SUM(CR31,CR32,CR33,CR34) -> 4918 | CS36: =SUM(CS31,CS32,CS33,CS34) -> 5168 | CT36: =SUM(CT31,CT32,CT33) -> 20115 | CU36: =SUM(CU31,CU32,CU33,CU34) -> 5115 | CV36: =SUM(CV31,CV32,CV33,CV34) -> 5352 | CW36: =SUM(CW31,CW32,CW33,CW34) -> 4919 | CX36: =SUM(CX31,CX32,CX33,CX34) -> 5291 | CY36: =SUM(CY31,CY32,CY33) -> 20572 | CZ36: =SUM(CZ31,CZ32,CZ33,CZ34) -> 5562 | DA36: =SUM(DA31,DA32,DA33,DA34) -> 6655 | DB36: =SUM(DB31,DB32,DB33,DB34) -> 5521 | DC36: =SUM(DC31,DC32,DC33,DC34) -> 5579 | DD36: =SUM(DD31,DD32,DD33,DD34) -> 23317 | DE36: =SUM(DE31,DE32,DE33,DE34) -> 5548 | DF36: =SUM(DF31,DF32,DF33,DF34) -> 5271 | DG36: =SUM(DG31,DG32,DG33,DG34) -> 4942 | ... FG36: =SUM(FG31,FG32,FG33,FG34) -> 22200
B37: Total Operating expenses (Non-GAAP) | CP37: =CP31+CP32+CP35 -> 4883 | CQ37: =CQ31+CQ32+CQ35 -> 4920 | CR37: =CR31+CR32+CR35 -> 4821 | CS37: =CS31+CS32+CS35 -> 5039 | CT37: =SUM(CP37:CS37) -> 19663 | CU37: =CU31+CU32+CU35 -> 4948 | CV37: =CV31+CV32+CV35 -> 5036 | CW37: =CW31+CW32+CW35 -> 4837 | CX37: =CX31+CX32+CX35 -> 5237 | CY37: =SUM(CU37:CX37) -> 20058 | CZ37: =CZ31+CZ32+CZ35 -> 5372 | DA37: =DA31+DA32+DA35 -> 5152 | DB37: =DB31+DB32+DB35 -> 5075 | DC37: =DC31+DC32+DC35 -> 5438 | DD37: =SUM(CZ37:DC37) -> 21037 | DE37: =DE31+DE32+DE35 -> 5430 | DF37: =DF31+DF32+DF35 -> 5129 | DG37: =DG31+DG32+DG35 -> 4776 | DH37: =DH31+DH32+DH35 -> 5124 | DI37: =SUM(DE37:DH37) -> 20459 | DJ37: =DJ31+DJ32+DJ35 -> 5211 | DK37: =DK31+DK32+DK35 -> 5355 | DL37: =DL31+DL32+DL35 -> 5033 | DM37: =DM31+DM32+DM35 -> 4953 | DN37: =SUM(DJ37:DM37) -> 20552 | DO37: =DO31+DO32+DO35 -> 4865 | DP37: =DP31+DP32+DP35 -> 5027 | DQ37: =DQ31+DQ32+DQ35 -> 4694 | DR37: =DR31+DR32+DR35 -> 4926 | DS37: =SUM(DO37:DR37) -> 19512 | DT37: =DT31+DT32+DT35 -> 4816 | DU37: =DU31+DU32+DU35 -> 4751 | DV37: =IF(ISERROR(DV31+DV32+DV35), "NA", DV31+DV32+DV35) -> 4655 | DW37: =IF(ISERROR(DW31+DW32+DW35), "NA", DW31+DW32+DW35) -> 5359 | DX37: =SUM(DT37:DW37) -> 19581 | DY37: =DY31+DY32+DY35 -> 4753 | DZ37: =DZ31+DZ32+DZ35 -> 5120 | EA37: =EA31+EA32+EA35 -> 5250 | EB37: =EB31+EB32+EB35 -> 5775 | EC37: =SUM(DY37:EB37) -> 20898 | ED37: =ED31+ED32+ED35 -> 5504 | EE37: =EE31+EE32+EE35 -> 5450 | EF37: =EF31+EF32+EF35 -> 5382 | EG37: =EG31+EG32+EG35 -> 5543 | EH37: =SUM(ED37:EG37) -> 21879 | EI37: =EI31+EI32+EI35-EI38 -> #ERROR! | EJ37: =EJ31+EJ32+EJ35-EJ38 -> #ERROR! | EK37: =EK31+EK32+EK35-EK38 -> #ERROR! | EL37: =EL31+EL32+EL35-EL38 -> #ERROR! | EM37: =SUM(EI37:EL37) -> #ERROR! | EN37: =EN31+EN32+EN35-EN38 -> #ERROR! | EO37: =EO31+EO32+EO35-EO38 -> #ERROR! | EP37: =EP31+EP32+EP35-EP38 -> #ERROR! | EQ37: =EQ31+EQ32+EQ35-EQ38 -> #ERROR! | ER37: =SUM(EN37:EQ37) -> #ERROR! | ES37: =ES31+ES32+ES35-ES38 -> #ERROR! | ET37: =ET31+ET32+ET35-ET38 -> #ERROR! | EU37: =EU31+EU32+EU35-EU38 -> #ERROR! | EV37: =EV31+EV32+EV35-EV38 -> #ERROR! | EW37: =SUM(ES37:EV37) -> #ERROR! | EX37: =EX31+EX32+EX35-EX38 -> #ERROR! | EY37: =EY31+EY32+EY35-EY38 -> #ERROR! | EZ37: =EZ31+EZ32+EZ35-EZ38 -> #ERROR! | FA37: =FA31+FA32+FA35-FA38 -> #ERROR! | FB37: =SUM(EX37:FA37) -> #ERROR! | FC37: =FC31+FC32+FC35-FC38 -> #ERROR! | FD37: =FD31+FD32+FD35-FD38 -> #ERROR! | FE37: =FE31+FE32+FE35-FE38 -> #ERROR! | FF37: =FF31+FF32+FF35-FF38 -> #ERROR! | FG37: =SUM(FC37:FF37) -> #ERROR!
B38: Opex SBC | CP38: $4.8B | CQ38: $4.9B | CR38: $4.9B | CS38: $4.9B | CU38: $4.9B | CV38: $4.9B | CW38: $4.9B | CX38: $5B | CZ38: $5.5B | DA38: $5.1B | DB38: $5.2B | DC38: $5.2B | DE38: $5.2B | DF38: $5.2B | DG38: $5.1B | DH38: $5.1B | DJ38: $5B | DK38: ~$5.1B | EH38: =SUM(ED38:EG38) -> 0 | EI38: =EI88*0.75 -> #ERROR! | EJ38: =EJ88*0.75 -> #ERROR! | EK38: =EK88*0.75 -> #ERROR! | EL38: =EL88*0.75 -> #ERROR! | EM38: =SUM(EI38:EL38) -> #ERROR! | EN38: =EN88*0.75 -> #ERROR! | EO38: =EO88*0.75 -> #ERROR! | EP38: =EP88*0.75 -> #ERROR! | EQ38: =EQ88*0.75 -> #ERROR! | ER38: =SUM(EN38:EQ38) -> #ERROR! | ES38: =ES88*0.75 -> #ERROR! | ET38: =ET88*0.75 -> #ERROR! | EU38: =EU88*0.75 -> #ERROR! | EV38: =EV88*0.75 -> #ERROR! | EW38: =SUM(ES38:EV38) -> #ERROR! | EX38: =EX88*0.75 -> #ERROR! | EY38: =EY88*0.75 -> #ERROR! | EZ38: =EZ88*0.75 -> #ERROR! | FA38: =FA88*0.75 -> #ERROR! | FB38: =SUM(EX38:FA38) -> #ERROR! | FC38: =FC88*0.75 -> #ERROR! | FD38: =FD88*0.75 -> #ERROR! | FE38: =FE88*0.75 -> #ERROR! | FF38: =FF88*0.75 -> #ERROR! | FG38: =SUM(FC38:FF38) -> #ERROR!
B39: Opex% (Non -GAAP) | DE39: =DE37/DE12 -> 0.36699108 | DF39: =DF37/DF12 -> 0.34742261 | DG39: =DG37/DG12 -> 0.29574587 | DH39: =DH37/DH12 -> 0.30047499 | DJ39: =DJ37/DJ12 -> 0.32434956 | DK39: =DK37/DK12 -> 0.3157057 | DL39: =DL37/DL12 -> 0.26264155 | DM39: =DM37/DM12 -> 0.26547676 | DO39: =DO37/DO12 -> 0.30290766 | DP39: =DP37/DP12 -> 0.30457437 | DQ39: =DQ37/DQ12 -> 0.24460657 | DR39: =DR37/DR12 -> 0.24375278 | DS39: =DS37/DS12 -> 0.2711318 | DT39: =DT37/DT12 -> 0.24288884 | DU39: =DU37/DU12 -> 0.24082522 | DV39: =DV37/DV12 -> 0.25391371 | ... FG39: =FG37/FG12 -> #ERROR!
B40: Operating income | N40: =+N22-N36 -> 1946 | O40: =+O22-O36 -> 1606 | P40: =+P22-P36 -> 2172 | Q40: =+Q22-Q36 -> 2876 | R40: =+R22-R36 -> 8600 | S40: =+S22-S36 -> 2655 | T40: =+T22-T36 -> 2351 | U40: =+U22-U36 -> 2510 | ... W40: =+W22-W36 -> 10570 | X40: =grossProfit-X36 -> 2929 | Y40: =grossProfit-Y36 -> 2823 | Z40: =grossProfit-Z36 -> 3285 | AA40: =grossProfit-AA36 -> 3053 | AB40: =+AB22-AB36 -> 12090 | AC40: =grossProfit-RD-MGA -> 1302 | AD40: =grossProfit-RD-MGA -> 934 | AE40: =grossProfit-RD-MGA -> 998 | AF40: =grossProfit-RD-MGA -> 1558 | AG40: =+AG22-AG36 -> 4792 | AH40: =grossProfit-RD-MGA -> 1426 | AI40: =grossProfit-RD-MGA -> 882 | AJ40: =grossProfit-RD-MGA -> 1072 | AK40: =grossProfit-RD-MGA -> 1570 | AL40: =+AL22-AL36 -> 4950 | AM40: =grossProfit-opExpenses -> 1391 | AN40: =grossProfit-opExpenses -> 1276 | AO40: =grossProfit-opExpenses -> 2304 | AP40: =grossProfit-opExpenses -> 3179 | AQ40: =grossProfit-opExpenses -> 8150 | AR40: =grossProfit-opExpenses -> 2476 | AS40: =grossProfit-opExpenses -> 2381 | AT40: =grossProfit-opExpenses -> 2373 | ... FG40: =grossProfit-opExpenses -> #ERROR!
B41: Operating Income (Non -GAAP) | CP41: =CP27-CP37 -> 2730 | CQ41: =CQ27-CQ37 -> 3997 | CR41: =CR27-CR37 -> 4637 | CS41: =CS27-CS37 -> 4582 | CT41: =SUM(CP41:CS41) -> 15946 | CU41: =CU27-CU37 -> 2902 | CV41: =CV27-CV37 -> 3287 | CW41: =CW27-CW37 -> 4274 | CX41: =CX27-CX37 -> 4425 | CY41: =SUM(CU41:CX41) -> 14888 | CZ41: =CZ27-CZ37 -> 3283 | DA41: =DA27-DA37 -> 3217 | DB41: =DB27-DB37 -> 5143 | DC41: =DC27-DC37 -> 4899 | DD41: =SUM(CZ41:DC41) -> 16542 | DE41: =DE27-DE37 -> 3926 | DF41: =DF27-DF37 -> 4167 | DG41: =DG27-DG37 -> 5551 | DH41: =DH27-DH37 -> 5933 | DI41: =SUM(DE41:DH41) -> 19577 | DJ41: =DJ27-DJ37 -> 4795 | DK41: =DK27-DK37 -> 5339 | DL41: =DL27-DL37 -> 7603 | DM41: =DM27-DM37 -> 6553 | DN41: =SUM(DJ41:DM41) -> 24290 | DO41: =DO27-DO37 -> 4505 | DP41: =DP27-DP37 -> 5138 | DQ41: =DQ27-DQ37 -> 6889 | DR41: =DR27-DR37 -> 7220 | DS41: =SUM(DO41:DR41) -> 23752 | DT41: =DT27-DT37+50 -> 7539 | DU41: =DU27-DU37 -> 6058 | DV41: =DV27-DV37 -> 5396 | DW41: =DW27-DW37 -> 6299 | DX41: =SUM(DT41:DW41) -> 25292 | DY41: =DY27-DY37 -> 6096 | DZ41: =DZ27-DZ37 -> 5856 | EA41: =EA27-EA37 -> 5202 | EB41: =EB27-EB37 -> 5051 | EC41: =SUM(DY41:EB41) -> 22205 | ED41: =ED27-ED37 -> 4241 | EE41: =EE27-EE37 -> 1417 | EF41: =EF27-EF37 -> 1655 | EG41: =EG27-EG37 -> 602 | EH41: =SUM(ED41:EG41) -> 7915 | EI41: =EI27-EI37 -> #ERROR! | EJ41: =EJ27-EJ37 -> #ERROR! | EK41: =EK27-EK37 -> #ERROR! | EL41: =EL27-EL37 -> #ERROR! | EM41: =SUM(EI41:EL41) -> #ERROR! | EN41: =EN27-EN37 -> #ERROR! | EO41: =EO27-EO37 -> #ERROR! | EP41: =EP27-EP37 -> #ERROR! | EQ41: =EQ27-EQ37 -> #ERROR! | ER41: =SUM(EN41:EQ41) -> #ERROR! | ES41: =ES27-ES37 -> #ERROR! | ET41: =ET27-ET37 -> #ERROR! | EU41: =EU27-EU37 -> #ERROR! | EV41: =EV27-EV37 -> #ERROR! | EW41: =SUM(ES41:EV41) -> #ERROR! | EX41: =EX27-EX37 -> #ERROR! | EY41: =EY27-EY37 -> #ERROR! | EZ41: =EZ27-EZ37 -> #ERROR! | FA41: =FA27-FA37 -> #ERROR! | FB41: =SUM(EX41:FA41) -> #ERROR! | FC41: =FC27-FC37 -> #ERROR! | FD41: =FD27-FD37 -> #ERROR! | FE41: =FE27-FE37 -> #ERROR! | FF41: =FF27-FF37 -> #ERROR! | FG41: =SUM(FC41:FF41) -> #ERROR!
B42: OPM% (Non -GAAP) | CP42: =CP41/CP12 -> 0.2138828 | CQ42: =CQ41/CQ12 -> 0.2889885 | CR42: =CR41/CR12 -> 0.31860657 | CS42: =CS41/CS12 -> 0.31125603 | CU42: =CU41/CU12 -> 0.22705579 | CV42: =CV41/CV12 -> 0.24910951 | CW42: =CW41/CW12 -> 0.29547183 | CX42: =CX41/CX12 -> 0.29670109 | CY42: =CY41/CY12 -> 0.26895493 | CZ42: =CZ41/CZ12 -> 0.23788131 | DA42: =DA41/DA12 -> 0.23771521 | DB42: =DB41/DB12 -> 0.3259602 | ... FG42: =FG41/FG12 -> #ERROR!
B43: Gains on equity investments | U43: 195 | V43: 327 | W43: 883 | X43: 449 | Y43: =AB43-X43-Z43-AA43 -> 2144 | Z43: 716 | AA43: 450 | AB43: 3759 | AC43: 0 | AD43: 3 | AE43: -182 | AF43: -287 | AG43: =SUM(AC43:AF43) -> -466 | AH43: -46 | AI43: -59 | AJ43: -96 | AK43: -171 | AL43: =SUM(AH43:AK43) -> -372 | AM43: -127 | AN43: -58 | AO43: -63 | AP43: -35 | AQ43: =SUM(AM43:AP43) -> -283 | AR43: 19 | AS43: -8 | AT43: -10 | AU43: -3 | AV43: =SUM(AR43:AU43) -> -2 | AW43: 4 | AX43: -22 | AY43: -2 | AZ43: -25 | BA43: =SUM(AW43:AZ43) -> -45 | BB43: 2 | BC43: 37 | BD43: 168 | BE43: 7 | BF43: =SUM(BB43:BE43) -> 214 | BG43: 29 | BH43: -1 | BI43: 148 | BJ43: -19 | BK43: =SUM(BG43:BJ43) -> 157 | BL43: -59 | BM43: -109 | BN43: =-312+18-102 -> -396 | BO43: =-1192-BO59 -> -254 | BP43: =SUM(BL43:BO43) -> -818 | BQ43: =-72-41 -> -113 | BR43: =-44-25 -> -69 | BS43: =-59-20 -> -79 | BT43: 91 | BU43: =SUM(BQ43:BT43) -> -170 | BV43: =-39+8 -> -31 | BW43: 193 | BX43: 77 | BY43: 109 | BZ43: =SUM(BV43:BY43) -> 348 | CA43: =70-42 -> 28 | CB43: =-66+41 -> -25 | CC43: =132-40 -> 92 | CD43: 17 | CE43: =SUM(CA43:CD43) -> 112 | CF43: -19 | CG43: 47 | CH43: 53 | CI43: 60 | CJ43: =SUM(CF43:CI43) -> 141 | CK43: -26 | CL43: 11 | CM43: 452 | CN43: 34 | CO43: =SUM(CK43:CN43) -> 471 | CP43: 48 | CQ43: 95 | CR43: 35 | CS43: 233 | CT43: =SUM(CP43:CS43) -> 411 | CU43: 32 | CV43: 100 | CW43: 165 | CX43: 18 | CY43: =SUM(CU43:CX43) -> 315 | CZ43: 22 | DA43: 478 | DB43: -12 | DC43: 18 | DD43: =SUM(CZ43:DC43) -> 506 | DE43: 252 | DF43: 342 | DG43: 846 | DH43: 1211 | DI43: =SUM(DE43:DH43) -> 2651 | DJ43: 643 | DK43: -203 | DL43: =-75 -> -75 | DM43: -490 | DN43: =SUM(DJ43:DM43) -> -125 | DO43: 434 | DP43: 170 | DQ43: 318 | DR43: 617 | DS43: =SUM(DO43:DR43) -> 1539 | DT43: -111 | DU43: 267 | DV43: 56 | DW43: 1692 | DX43: =SUM(DT43:DW43) -> 1904 | DY43: 368 | DZ43: 295 | EA43: 1707 | EB43: 359 | EC43: =SUM(DY43:EB43) -> 2729 | ED43: 4323 | EE43: =-90 -> -90 | EF43: -151 | EG43: 186 | EH43: =SUM(ED43:EG43) -> 4268 | EM43: =SUM(EI43:EL43) -> 0 | ER43: =SUM(EN43:EQ43) -> 0 | EW43: =SUM(ES43:EV43) -> 0 | FB43: =SUM(EX43:FA43) -> 0 | FG43: =SUM(FC43:FF43) -> 0
B44: Interest and other | U44: 121 | V44: 181 | W44: 578 | X44: 191 | Y44: =AB44-X44-Z44-AA44 -> 197 | Z44: 250 | AA44: 349 | AB44: 987 | AC44: 264 | AD44: 126 | AE44: -70 | AF44: 73 | AG44: =SUM(AC44:AF44) -> 393 | AH44: =79-24-7 -> 48 | AI44: 43 | AJ44: 49 | AK44: 54 | AL44: =SUM(AH44:AK44) -> 194 | AM44: 52 | AN44: 53 | AO44: 34 | AP44: 53 | AQ44: =SUM(AM44:AP44) -> 192 | AR44: 49 | AS44: 47 | AT44: =75-13+1 -> 63 | AU44: 130 | AV44: =SUM(AR44:AU44) -> 289 | AW44: =121-2-4 -> 115 | AX44: 127 | AY44: =145-6+6 -> 145 | AZ44: 178 | BA44: =SUM(AW44:AZ44) -> 565 | BB44: =168-7-7 -> 154 | BC44: =152-7-1 -> 144 | BD44: 272 | BE44: 632 | BF44: =SUM(BB44:BE44) -> 1202 | BG44: 169 | BH44: =192-4-8 -> 180 | BI44: 211 | BJ44: 233 | BK44: =SUM(BG44:BJ44) -> 793 | BL44: =198-30 -> 168 | BM44: 167 | BN44: =126+5 -> 131 | BO44: 22 | BP44: =SUM(BL44:BO44) -> 488 | BQ44: 95 | BR44: 31 | BS44: 32 | BT44: 5 | BU44: =SUM(BQ44:BT44) -> 163 | BV44: 29 | BW44: 11 | BX44: 38 | BY44: 31 | BZ44: =SUM(BV44:BY44) -> 109 | CA44: =28-6+163 -> 185 | CB44: =20+1 -> 21 | CC44: 15 | CD44: =CE44-SUM(CA44:CC44) -> -29 | CE44: =98-41+135 -> 192 | CF44: =28-31+26 -> 23 | CG44: =25-21+51 -> 55 | CH44: =23-14+18 -> 27 | CI44: -11 | CJ44: =SUM(CF44:CI44) -> 94 | CK44: -50 | CL44: -37 | CM44: -32 | CN44: -32 | CO44: =SUM(CK44:CN44) -> -151 | CP44: 112 | CQ44: -17 | CR44: -25 | CS44: -27 | CT44: =SUM(CP44:CS44) -> 43 | CU44: 26 | CV44: -13 | CW44: -104 | CX44: -14 | CY44: =SUM(CU44:CX44) -> -105 | CZ44: -82 | DA44: -126 | DB44: -132 | DC44: -104 | DD44: =SUM(CZ44:DC44) -> -444 | DE44: -36 | DF44: =403 -> 403 | DG44: -31 | DH44: -571 | DI44: =SUM(DE44:DH44) -> -235 | DJ44: -102 | DK44: 459 | DL44: -132 | DM44: -99 | DN44: =SUM(DJ44:DM44) -> 126 | DO44: -61 | DP44: -63 | DQ44: -46 | DR44: 654 | DS44: =SUM(DO44:DR44) -> 484 | DT44: -313 | DU44: -29 | DV44: -74 | DW44: -88 | DX44: =SUM(DT44:DW44) -> -504 | DY44: -156 | DZ44: -96 | EA44: -76 | EB44: -154 | EC44: =SUM(DY44:EB44) -> -482 | ED44: 997 | EE44: -119 | EF44: 138 | EG44: 150 | EH44: =SUM(ED44:EG44) -> 1166 | EI44: =CF!EI166-CF!EI163 -> 81.524003 | EJ44: =CF!EJ166-CF!EJ163 -> #ERROR! | EK44: =CF!EK166-CF!EK163 -> #ERROR! | EL44: =CF!EL166-CF!EL163 -> #ERROR! | EM44: =SUM(EI44:EL44) -> #ERROR! | EN44: =CF!EN166-CF!EN163 -> #ERROR! | EO44: =CF!EO166-CF!EO163 -> #ERROR! | EP44: =CF!EP166-CF!EP163 -> #ERROR! | EQ44: =CF!EQ166-CF!EQ163 -> #ERROR! | ER44: =SUM(EN44:EQ44) -> #ERROR! | ES44: =CF!ES166-CF!ES163 -> #ERROR! | ET44: =CF!ET166-CF!ET163 -> #ERROR! | EU44: =CF!EU166-CF!EU163 -> #ERROR! | EV44: =CF!EV166-CF!EV163 -> #ERROR! | EW44: =SUM(ES44:EV44) -> #ERROR! | EX44: =CF!EX166-CF!EX163 -> #ERROR! | EY44: =CF!EY166-CF!EY163 -> #ERROR! | EZ44: =CF!EZ166-CF!EZ163 -> #ERROR! | FA44: =CF!FA166-CF!FA163 -> #ERROR! | FB44: =SUM(EX44:FA44) -> #ERROR! | FC44: =CF!FC166-CF!FC163 -> #ERROR! | FD44: =CF!FD166-CF!FD163 -> #ERROR! | FE44: =CF!FE166-CF!FE163 -> #ERROR! | FF44: =CF!FF166-CF!FF163 -> #ERROR! | FG44: =SUM(FC44:FF44) -> #ERROR!
B45: Other income, net | N45: 200 | O45: 144 | P45: 170 | Q45: 244 | R45: =+SUM(N45:Q45) -> 758 | S45: 347 | T45: 290 | U45: =SUM(U44,U43) -> 316 | V45: =SUM(V44,V43) -> 508 | W45: =SUM(W44,W43) -> 1461 | X45: =SUM(X44,X43) -> 640 | Y45: =SUM(Y44,Y43) -> 2341 | Z45: =SUM(Z44,Z43) -> 966 | AA45: =SUM(AA44,AA43) -> 799 | AB45: =+SUM(X45:AA45) -> 4746 | AC45: =SUM(AC44,AC43) -> 264 | AD45: =SUM(AD44,AD43) -> 129 | AE45: =SUM(AE44,AE43) -> -252 | AF45: =SUM(AF44,AF43) -> -214 | AG45: =+SUM(AC45:AF45) -> -73 | AH45: =SUM(AH44,AH43) -> 2 | AI45: =SUM(AI44,AI43) -> -16 | AJ45: =SUM(AJ44,AJ43) -> -47 | AK45: =SUM(AK44,AK43) -> -117 | AL45: =+SUM(AH45:AK45) -> -178 | AM45: =AM44+AM43 -> -75 | AN45: =SUM(AN44,AN43) -> -5 | AO45: =SUM(AO44,AO43) -> -29 | AP45: =SUM(AP44,AP43) -> 18 | AQ45: =+SUM(AM45:AP45) -> -91 | AR45: =SUM(AR44,AR43) -> 68 | AS45: =SUM(AS44,AS43) -> 39 | AT45: =SUM(AT44,AT43) -> 53 | AU45: =SUM(AU44,AU43) -> 127 | AV45: =+SUM(AR45:AU45) -> 287 | AW45: =SUM(AW44,AW43) -> 119 | AX45: =SUM(AX44,AX43) -> 105 | AY45: =SUM(AY44,AY43) -> 143 | AZ45: =SUM(AZ44,AZ43) -> 153 | BA45: =+SUM(AW45:AZ45) -> 520 | BB45: =SUM(BB44,BB43) -> 156 | BC45: =SUM(BC44,BC43) -> 181 | BD45: =SUM(BD44,BD43) -> 440 | BE45: =SUM(BE44,BE43) -> 639 | BF45: =+SUM(BB45:BE45) -> 1416 | BG45: =SUM(BG44,BG43) -> 198 | BH45: =SUM(BH44,BH43) -> 179 | BI45: =SUM(BI44,BI43) -> 359 | BJ45: =SUM(BJ44,BJ43) -> 214 | BK45: =+SUM(BG45:BJ45) -> 950 | BL45: =SUM(BL44,BL43) -> 109 | BM45: =SUM(BM44,BM43) -> 58 | BN45: =SUM(BN44,BN43) -> -265 | BO45: =SUM(BO44,BO43) -> -232 | BP45: =+SUM(BL45:BO45) -> -330 | BQ45: =SUM(BQ44,BQ43) -> -18 | BR45: =SUM(BR44,BR43) -> -38 | BS45: =SUM(BS44,BS43) -> -47 | BT45: =SUM(BT44,BT43) -> 96 | BU45: =+SUM(BQ45:BT45) -> -7 | BV45: =SUM(BV44,BV43) -> -2 | BW45: =SUM(BW44,BW43) -> 204 | BX45: =SUM(BX44,BX43) -> 115 | BY45: =SUM(BY44,BY43) -> 140 | BZ45: =+SUM(BV45:BY45) -> 457 | CA45: =SUM(CA44,CA43) -> 213 | CB45: =SUM(CB44,CB43) -> -4 | CC45: =SUM(CC44,CC43) -> 107 | CD45: =SUM(CD44,CD43) -> -12 | CE45: =+SUM(CA45:CD45) -> 304 | CF45: =SUM(CF44,CF43) -> 4 | CG45: =SUM(CG44,CG43) -> 102 | CH45: =SUM(CH44,CH43) -> 80 | CI45: =SUM(CI44,CI43) -> 49 | CJ45: =+SUM(CF45:CI45) -> 235 | CK45: =SUM(CK44,CK43) -> -76 | CL45: =SUM(CL44,CL43) -> -26 | CM45: =+CM44+CM43 -> 420 | CN45: =+CN44+CN43 -> 2 | CO45: =+SUM(CK45:CN45) -> 320 | CP45: =SUM(CP44,CP43) -> 160 | CQ45: =SUM(CQ44,CQ43) -> 78 | CR45: =SUM(CR44,CR43) -> 10 | CS45: =SUM(CS44,CS43) -> 206 | CT45: =+SUM(CP45:CS45) -> 454 | CU45: =SUM(CU44,CU43) -> 58 | CV45: =SUM(CV44,CV43) -> 87 | CW45: =SUM(CW44,CW43) -> 61 | CX45: =SUM(CX44,CX43) -> 4 | CY45: =+SUM(CU45:CX45) -> 210 | CZ45: =SUM(CZ44,CZ43) -> -60 | DA45: =SUM(DA44,DA43) -> 352 | DB45: =SUM(DB44,DB43) -> -144 | DC45: =SUM(DC44,DC43) -> -86 | DD45: =+SUM(CZ45:DC45) -> 62 | DE45: =SUM(DE44,DE43) -> 216 | DF45: =SUM(DF44,DF43) -> 745 | DG45: =SUM(DG44,DG43) -> 815 | DH45: =SUM(DH44,DH43) -> 640 | DI45: =+SUM(DE45:DH45) -> 2416 | DJ45: =SUM(DJ44,DJ43) -> 541 | DK45: =SUM(DK44,DK43) -> 256 | DL45: =SUM(DL44,DL43) -> -207 | DM45: =SUM(DM44,DM43) -> -589 | DN45: =+SUM(DJ45:DM45) -> 1 | DO45: =SUM(DO44,DO43) -> 373 | DP45: =SUM(DP44,DP43) -> 107 | DQ45: =SUM(DQ44,DQ43) -> 272 | DR45: =SUM(DR44,DR43) -> 1271 | DS45: =+SUM(DO45:DR45) -> 2023 | DT45: =SUM(DT44,DT43) -> -424 | DU45: =SUM(DU44,DU43) -> 238 | DV45: =SUM(DV44,DV43) -> -18 | DW45: =SUM(DW44,DW43) -> 1604 | DX45: =+SUM(DT45:DW45) -> 1400 | DY45: =SUM(DY44,DY43) -> 212 | DZ45: =SUM(DZ44,DZ43) -> 199 | EA45: =SUM(EA44,EA43) -> 1631 | EB45: =SUM(EB44,EB43) -> 205 | EC45: =+SUM(DY45:EB45) -> 2247 | ED45: =SUM(ED44,ED43) -> 5320 | EE45: =SUM(EE44,EE43) -> -209 | EF45: =SUM(EF44,EF43) -> -13 | EG45: =SUM(EG44,EG43) -> 336 | EH45: =+SUM(ED45:EG45) -> 5434 | EI45: =SUM(EI44,EI43) -> 81.524003 | EJ45: =SUM(EJ44,EJ43) -> #ERROR! | EK45: =SUM(EK44,EK43) -> #ERROR! | EL45: =SUM(EL44,EL43) -> #ERROR! | EM45: =+SUM(EI45:EL45) -> #ERROR! | EN45: =SUM(EN44,EN43) -> #ERROR! | EO45: =SUM(EO44,EO43) -> #ERROR! | EP45: =SUM(EP44,EP43) -> #ERROR! | EQ45: =SUM(EQ44,EQ43) -> #ERROR! | ER45: =+SUM(EN45:EQ45) -> #ERROR! | ES45: =SUM(ES44,ES43) -> #ERROR! | ET45: =SUM(ET44,ET43) -> #ERROR! | EU45: =SUM(EU44,EU43) -> #ERROR! | EV45: =SUM(EV44,EV43) -> #ERROR! | EW45: =+SUM(ES45:EV45) -> #ERROR! | EX45: =SUM(EX44,EX43) -> #ERROR! | EY45: =SUM(EY44,EY43) -> #ERROR! | EZ45: =SUM(EZ44,EZ43) -> #ERROR! | FA45: =SUM(FA44,FA43) -> #ERROR! | FB45: =+SUM(EX45:FA45) -> #ERROR! | FC45: =SUM(FC44,FC43) -> #ERROR! | FD45: =SUM(FD44,FD43) -> #ERROR! | FE45: =SUM(FE44,FE43) -> #ERROR! | FF45: =SUM(FF44,FF43) -> #ERROR! | FG45: =+SUM(FC45:FF45) -> #ERROR!
B46: Pretax income | N46: =+N40+N45 -> 2146 | O46: =+O40+O45 -> 1750 | P46: =+P40+P45 -> 2342 | Q46: =+Q40+Q45 -> 3120 | R46: =+R40+R45 -> 9358 | S46: =+S40+S45 -> 3002 | T46: =+T40+T45 -> 2641 | U46: =+U40+U45 -> 2826 | ... FG46: =+FG40+FG45 -> #ERROR!
B47: Pretax Income (Non-GAAP) | CP47: =CP41+CP45 -> 2890 | CQ47: =CQ41+CQ45 -> 4075 | CR47: =CR41+CR45 -> 4647 | CS47: =CS41+CS45 -> 4788 | CT47: =SUM(CP47:CS47) -> 16400 | CU47: =CU41+CU45 -> 2960 | CV47: =CV41+CV45 -> 3374 | CW47: =CW41+CW45 -> 4335 | CX47: =CX41+CX45 -> 4429 | CY47: =SUM(CU47:CX47) -> 15098 | CZ47: =CZ41+CZ45 -> 3223 | DA47: =DA41+DA45 -> 3569 | DB47: =DB41+DB45 -> 4999 | DC47: =DC41+DC45 -> 4813 | DD47: =SUM(CZ47:DC47) -> 16604 | DE47: =DE41+DE45 -> 4142 | DF47: =DF41+DF45-387 -> 4525 | DG47: =DG41+DG45 -> 6366 | DH47: =DH41+DH45 -> 6573 | DI47: =SUM(DE47:DH47) -> 21606 | DJ47: =DJ41+DJ45 -> 5336 | DK47: =DK41+DK45 -> 5595 | DL47: =DL41+DL45 -> 7396 | DM47: =DM41+DM45 -> 5964 | DN47: =SUM(DJ47:DM47) -> 24291 | DO47: =DO41+DO45 -> 4878 | DP47: =DP41+DP45 -> 5245 | DQ47: =DQ41+DQ45 -> 7161 | DR47: =DR41+DR45 -> 8491 | DS47: =SUM(DO47:DR47) -> 25775 | DT47: =DT41+DT45 -> 7115 | DU47: =DU41+DU45-165 -> 6131 | DV47: =DV41+DV45+146-6 -> 5518 | DW47: =DW41+DW45+48 -> 7951 | DX47: =SUM(DT47:DW47) -> 26715 | DY47: =DY41+DY45 -> 6308 | DZ47: =DZ41+DZ45 -> 6055 | EA47: =EA41+EA45 -> 6833 | EB47: =EB41+EB45 -> 5256 | EC47: =SUM(DY47:EB47) -> 24452 | ED47: =ED41+ED45-1121-4323 -> 4117 | EE47: =EE41+EE45+19+90 -> 1317 | EF47: =EF41+EF45+151-39 -> 1754 | EG47: =EG41+EG45-186-26 -> 726 | EH47: =SUM(ED47:EG47) -> 7914 | EI47: =EI41+EI45 -> #ERROR! | EJ47: =EJ41+EJ45 -> #ERROR! | EK47: =EK41+EK45 -> #ERROR! | EL47: =EL41+EL45 -> #ERROR! | EM47: =SUM(EI47:EL47) -> #ERROR! | EN47: =EN41+EN45 -> #ERROR! | EO47: =EO41+EO45 -> #ERROR! | EP47: =EP41+EP45 -> #ERROR! | EQ47: =EQ41+EQ45 -> #ERROR! | ER47: =SUM(EN47:EQ47) -> #ERROR! | ES47: =ES41+ES45 -> #ERROR! | ET47: =ET41+ET45 -> #ERROR! | EU47: =EU41+EU45 -> #ERROR! | EV47: =EV41+EV45 -> #ERROR! | EW47: =SUM(ES47:EV47) -> #ERROR! | EX47: =EX41+EX45 -> #ERROR! | EY47: =EY41+EY45 -> #ERROR! | EZ47: =EZ41+EZ45 -> #ERROR! | FA47: =FA41+FA45 -> #ERROR! | FB47: =SUM(EX47:FA47) -> #ERROR! | FC47: =FC41+FC45 -> #ERROR! | FD47: =FD41+FD45 -> #ERROR! | FE47: =FE41+FE45 -> #ERROR! | FF47: =FF41+FF45 -> #ERROR! | FG47: =SUM(FC47:FF47) -> #ERROR!
B48: Income taxes | N48: 708 | O48: 578 | P48: 767 | Q48: 1016 | R48: =+SUM(N48:Q48) -> 3069 | S48: =EBT-proFormaNetInc -> 985 | T48: =EBT-proFormaNetInc -> 861 | U48: =EBT-proFormaNetInc -> 922 | V48: =EBT-proFormaNetInc -> 1154 | W48: =+SUM(S48:V48) -> 3922 | X48: =EBT-proFormaNetInc -> 531 | Y48: =EBT-proFormaNetInc -> 1646 | Z48: =EBT-proFormaNetInc -> 1352 | AA48: =EBT-proFormaNetInc -> 1182 | AB48: =+SUM(X48:AA48) -> 4711 | AC48: =EBT-proFormaNetInc -> 467 | AD48: =EBT-proFormaNetInc -> 209 | AE48: =EBT-proFormaNetInc -> 91 | AF48: =EBT-proFormaNetInc -> 346 | AG48: =+SUM(AC48:AF48) -> 1113 | AH48: =EBT-proFormaNetInc -> 406 | AI48: =EBT-proFormaNetInc -> 246 | AJ48: =EBT-proFormaNetInc -> 257 | AK48: =EBT-proFormaNetInc -> 399 | AL48: =+SUM(AH48:AK48) -> 1308 | AM48: 401 | AN48: 375 | AO48: 618 | AP48: 1027 | AQ48: =+SUM(AM48:AP48) -> 2421 | AR48: 814 | AS48: 663 | AT48: 520 | AU48: 904 | AV48: =+SUM(AR48:AU48) -> 2901 | AW48: 973 | AX48: 716 | AY48: =0.308*AY46 -> 1041.964 | AZ48: 1009 | BA48: =+SUM(AW48:AZ48) -> 3739.964 | BB48: 517 | BC48: 368 | BD48: 513 | BE48: 626 | BF48: =+SUM(BB48:BE48) -> 2024 | BG48: =BG60+326 -> 563 | BH48: =BH60+181 -> 432 | BI48: =28.4%*BI46 -> 742.944 | BJ48: 990 | BK48: =+SUM(BG48:BJ48) -> 2727.944 | BL48: 728 | BM48: 712 | BN48: 819 | BO48: =EBT*0.289 -> 377.723 | BP48: =+SUM(BL48:BO48) -> 2636.723 | BQ48: 0 | BR48: 348 | BS48: 676 | BT48: =GAAPTax+438 -> 749 | BU48: =+SUM(BQ48:BT48) -> 1773 | BV48: 1004 | BW48: 1298 | BX48: 1296 | BY48: =BZ48-SUM(BV48:BX48) -> 983 | BZ48: 4581 | CA48: 1211 | CB48: 977 | CC48: 1424 | CD48: 1227 | CE48: =+SUM(CA48:CD48) -> 4839 | CF48: 1076 | CG48: 1107 | CH48: 949 | CI48: =736 -> 736 | CJ48: =+SUM(CF48:CI48) -> 3868 | CK48: 398 | CL48: 693 | CM48: 974 | CN48: 926 | CO48: =+SUM(CK48:CN48) -> 2991 | CP48: 740 | CQ48: 1126 | CR48: 1233 | CS48: 998 | CT48: =+SUM(CP48:CS48) -> 4097 | CU48: 681 | CV48: 277 | CW48: 1144 | CX48: 690 | CY48: =+SUM(CU48:CX48) -> 2792 | CZ48: 462 | DA48: 340 | DB48: 940 | DC48: 878 | DD48: =+SUM(CZ48:DC48) -> 2620 | DE48: 851 | DF48: 1764 | DG48: 1414 | DH48: 6722 | DI48: =+SUM(DE48:DH48) -> 10751 | DJ48: 557 | DK48: 523 | DL48: 744 | DM48: 440 | DN48: =+SUM(DJ48:DM48) -> 2264 | DO48: 573 | DP48: 545 | DQ48: 729 | DR48: 1163 | DS48: =+SUM(DO48:DR48) -> 3010 | DT48: 953 | DU48: 830 | DV48: 765 | DW48: 1631 | DX48: =+SUM(DT48:DW48) -> 4179 | DY48: 545 | DZ48: 684 | EA48: 35 | EB48: 571 | EC48: =+SUM(DY48:EB48) -> 1835 | ED48: 1548 | EE48: -455 | EF48: -1207 | EG48: -135 | EH48: =+SUM(ED48:EG48) -> -249 | EI48: =EBT*taxRate -> #ERROR! | EJ48: =EBT*taxRate -> #ERROR! | EK48: =EBT*taxRate -> #ERROR! | EL48: =EBT*taxRate -> #ERROR! | EM48: =+SUM(EI48:EL48) -> #ERROR! | EN48: =EBT*taxRate -> #ERROR! | EO48: =EBT*taxRate -> #ERROR! | EP48: =EBT*taxRate -> #ERROR! | EQ48: =EBT*taxRate -> #ERROR! | ER48: =+SUM(EN48:EQ48) -> #ERROR! | ES48: =EBT*taxRate -> #ERROR! | ET48: =EBT*taxRate -> #ERROR! | EU48: =EBT*taxRate -> #ERROR! | EV48: =EBT*taxRate -> #ERROR! | EW48: =+SUM(ES48:EV48) -> #ERROR! | EX48: =EBT*taxRate -> #ERROR! | EY48: =EBT*taxRate -> #ERROR! | EZ48: =EBT*taxRate -> #ERROR! | FA48: =EBT*taxRate -> #ERROR! | FB48: =+SUM(EX48:FA48) -> #ERROR! | FC48: =EBT*taxRate -> #ERROR! | FD48: =EBT*taxRate -> #ERROR! | FE48: =EBT*taxRate -> #ERROR! | FF48: =EBT*taxRate -> #ERROR! | FG48: =+SUM(FC48:FF48) -> #ERROR!
B49: Income Taxes (Non-GAAP) | CP49: =CP48+73 -> 813 | CQ49: =CQ48+42 -> 1168 | CR49: =CR48+62 -> 1295 | CS49: =CS48+20 -> 1018 | CT49: =SUM(CP49:CS49) -> 4294 | CU49: =CU48+73 -> 754 | CV49: =CV48+42 -> 319 | CW49: =CW48+62 -> 1206 | CX49: =CX48+20 -> 710 | CY49: =SUM(CU49:CX49) -> 2989 | CZ49: =CZ48+132 -> 594 | DA49: =DA48+370 -> 710 | DB49: =DB48+173 -> 1113 | DC49: =DC48+70 -> 948 | DD49: =SUM(CZ49:DC49) -> 3365 | DE49: =DE48+73 -> 924 | DF49: =DF47*0.2251 -> 1018.5775 | DG49: =DG48+104 -> 1518 | DH49: =DH48+114-5444 -> 1392 | DI49: =SUM(DE49:DH49) -> 4852.5775 | DJ49: =DJ48-2+606 -> 1161 | DK49: =DK47*0.117 -> 654.615 | DL49: =DL48+23+113+8 -> 888 | DM49: =DM48+130-508 -> 62 | DN49: =SUM(DJ49:DM49) -> 2765.615 | DO49: =DO48+4+253 -> 830 | DP49: =DP48+94-179 -> 460 | DQ49: =DQ48+114+29 -> 872 | DR49: =DR48-114+89+690 -> 1828 | DS49: =SUM(DO49:DR49) -> 3990 | DT49: =DT48-103+33 -> 883 | DU49: =DU48+23 -> 853 | DV49: =DV48+78 -> 843 | DW49: =DW48+75 -> 1706 | DX49: =SUM(DT49:DW49) -> 4285 | DY49: =DY48-291+359 -> 613 | DZ49: =138+19+DZ48 -> 841 | EA49: =EA48-192-7 -> -164 | EB49: =EB48-(-216-18) -> 805 | EC49: =SUM(DY49:EB49) -> 2095 | ED49: =ED48-1391+374 -> 531 | EE49: =EE48-33+624 -> 136 | EF49: =EF48+303+226 -> -678 | EG49: =EG48+267+200 -> 332 | EH49: =SUM(ED49:EG49) -> 321 | EI49: =EI47*EI110 -> #ERROR! | EJ49: =EJ47*EJ110 -> #ERROR! | EK49: =EK47*EK110 -> #ERROR! | EL49: =EL47*EL110 -> #ERROR! | EM49: =SUM(EI49:EL49) -> #ERROR! | EN49: =EN47*EN110 -> #ERROR! | EO49: =EO47*EO110 -> #ERROR! | EP49: =EP47*EP110 -> #ERROR! | EQ49: =EQ47*EQ110 -> #ERROR! | ER49: =SUM(EN49:EQ49) -> #ERROR! | ES49: =ES47*ES110 -> #ERROR! | ET49: =ET47*ET110 -> #ERROR! | EU49: =EU47*EU110 -> #ERROR! | EV49: =EV47*EV110 -> #ERROR! | EW49: =SUM(ES49:EV49) -> #ERROR! | EX49: =EX47*EX110 -> #ERROR! | EY49: =EY47*EY110 -> #ERROR! | EZ49: =EZ47*EZ110 -> #ERROR! | FA49: =FA47*FA110 -> #ERROR! | FB49: =SUM(EX49:FA49) -> #ERROR! | FC49: =FC47*FC110 -> #ERROR! | FD49: =FD47*FD110 -> #ERROR! | FE49: =FE47*FE110 -> #ERROR! | FF49: =FF47*FF110 -> #ERROR! | FG49: =SUM(FC49:FF49) -> #ERROR!
B50: Minority interest | BB50: 0 | BC50: 0 | BD50: 0 | BE50: 0 | BF50: =+SUM(BB50:BE50) -> 0 | BG50: 0 | BH50: 0 | BI50: 0 | BJ50: 0 | BK50: =+SUM(BG50:BJ50) -> 0 | BL50: 0 | BM50: 0 | BN50: 0 | BO50: 0 | BP50: =+SUM(BL50:BO50) -> 0 | BQ50: 0 | BR50: 0 | BS50: 0 | BT50: 0 | BU50: =+SUM(BQ50:BT50) -> 0 | BV50: 0 | BW50: 0 | BX50: 0 | BY50: 0 | BZ50: =+SUM(BV50:BY50) -> 0 | CA50: 0 | CB50: 0 | CC50: 0 | CD50: 0 | CE50: =+SUM(CA50:CD50) -> 0 | CF50: 0 | CG50: 0 | CH50: 0 | CI50: 0 | CJ50: =+SUM(CF50:CI50) -> 0 | CK50: 0 | CL50: 0 | CM50: 0 | CN50: 0 | CO50: =+SUM(CK50:CN50) -> 0 | CP50: 0 | CQ50: 0 | CR50: 0 | CS50: 0 | CT50: =+SUM(CP50:CS50) -> 0 | CU50: 0 | CV50: 0 | CW50: 0 | CX50: 0 | CY50: =+SUM(CU50:CX50) -> 0 | CZ50: 0 | DA50: 0 | DB50: 0 | DC50: 0 | DD50: =+SUM(CZ50:DC50) -> 0 | DE50: 0 | DF50: 0 | DG50: 0 | DH50: 0 | DI50: =+SUM(DE50:DH50) -> 0 | DJ50: 0 | DK50: 0 | DL50: 0 | DM50: 0 | DN50: =+SUM(DJ50:DM50) -> 0 | DO50: 0 | DP50: 0 | DQ50: 0 | DR50: 0 | DS50: =+SUM(DO50:DR50) -> 0 | DT50: 0 | DU50: 0 | DV50: 0 | DW50: 0 | DX50: =+SUM(DT50:DW50) -> 0 | DY50: 0 | DZ50: 0 | EA50: 0 | EB50: 0 | EC50: =+SUM(DY50:EB50) -> 0 | ED50: 0 | EE50: 0 | EF50: 0 | EG50: 0 | EH50: =+SUM(ED50:EG50) -> 0 | EI50: 0 | EJ50: 0 | EK50: 0 | EL50: 0 | EM50: =+SUM(EI50:EL50) -> 0 | EN50: 0 | EO50: 0 | EP50: 0 | EQ50: 0 | ER50: =+SUM(EN50:EQ50) -> 0 | ES50: 0 | ET50: 0 | EU50: 0 | EV50: 0 | EW50: =+SUM(ES50:EV50) -> 0 | EX50: 0 | EY50: 0 | EZ50: 0 | FA50: 0 | FB50: =+SUM(EX50:FA50) -> 0 | FC50: 0 | FD50: 0 | FE50: 0 | FF50: 0 | FG50: =+SUM(FC50:FF50) -> 0
B51: Net Income | N51: =+N46-N48 -> 1438 | O51: =+O46-O48 -> 1172 | P51: =+P46-P48 -> 1575 | Q51: =+Q46-Q48 -> 2104 | R51: =+R46-R48 -> 6289 | S51: 2017 | T51: 1780 | U51: 1904 | V51: 2408 | W51: =+W46-W48 -> 8109 | X51: 3038 | Y51: 3518 | Z51: 2899 | AA51: 2670 | AB51: =+AB46-AB48 -> 12125 | AC51: 1099 | AD51: 854 | AE51: 655 | AF51: 998 | AG51: =+AG46-AG48 -> 3606 | AH51: 1022 | AI51: 620 | AJ51: 768 | AK51: =1054 -> 1054 | AL51: =+AL46-AL48 -> 3464 | AM51: =EBT-tax -> 915 | AN51: =EBT-tax -> 896 | AO51: =EBT-tax -> 1657 | AP51: =EBT-tax -> 2170 | AQ51: =+AQ46-AQ48 -> 5638 | AR51: =EBT-tax -> 1730 | AS51: =EBT-tax -> 1757 | AT51: =EBT-tax -> 1906 | AU51: =EBT-tax -> 2123 | AV51: =+AV46-AV48 -> 7516 | AW51: =EBT-tax+eqJv -> 2178 | AX51: =EBT-tax+eqJv -> 2038 | AY51: =EBT-tax+eqJv -> 2341.036 | AZ51: =EBT-tax+eqJv -> 2453 | BA51: =EBT-tax+eqJv -> 9010.036 | BB51: =EBT-tax+eqJv -> 1357 | BC51: =EBT-tax+eqJv -> 885 | BD51: =EBT-tax+eqJv -> 1301 | ... FG51: =EBT-tax+eqJv -> #ERROR!
B53: % Options Expense COGS | BB53: =86/BB56 -> 0.22994652 | BC53: =66/BC56 -> 0.19879518 | BD53: =103/BD56 -> 0.30746269 | BE53: =94/BE56 -> 0.28143713 | BF53: {=SUM(BB53:BE53*BB$57:BE$57)/BF$57} -> 0.25419234 | BG53: =78/BG56 -> 0.27464789 | BH53: =64/BH56 -> 0.27004219 | BI53: =60/BI56 -> 0.26431718 | BJ53: =BI53 -> 0.26431718 | BK53: {=SUM(BG53:BJ53*BG$57:BJ$57)/BK$57} -> 0.2688109 | BL53: =BJ53 -> 0.26431718 | BM53: =BL53 -> 0.26431718 | BN53: =BM53 -> 0.26431718 | BO53: =BN53 -> 0.26431718 | BP53: {=SUM(BL53:BO53*BL$57:BO$57)/BP$57} -> 0.26431718 | BQ53: =BO53 -> 0.26431718 | BR53: =BQ53 -> 0.26431718 | BS53: =BR53 -> 0.26431718 | BT53: =BS53 -> 0.26431718 | BU53: {=SUM(BQ53:BT53*BQ$57:BT$57)/BU$57} -> 0.27417896 | BV53: =BT53 -> 0.26431718 | BW53: =BV53 -> 0.26431718 | BX53: =BW53 -> 0.26431718 | BY53: =BX53 -> 0.26431718 | BZ53: {=SUM(BV53:BY53*BV$57:BY$57)/BZ$57} -> 0.26431718 | CA53: =BY53 -> 0.26431718 | CB53: =CA53 -> 0.26431718 | CC53: =CB53 -> 0.26431718 | CD53: =CC53 -> 0.26431718 | CE53: {=SUM(CA53:CD53*CA$57:CD$57)/CE$57} -> 0.26469555 | CF53: =CD53 -> 0.26431718 | CG53: =CF53 -> 0.26431718 | CH53: =CG53 -> 0.26431718 | CI53: =CH53 -> 0.26431718 | CJ53: {=SUM(CF53:CI53*CF$57:CI$57)/CJ$57} -> 0.26474194 | CK53: =CI53 -> 0.26431718 | CL53: =CK53 -> 0.26431718 | CM53: =CL53 -> 0.26431718 | CN53: =CM53 -> 0.26431718 | CO53: {=SUM(CK53:CN53*CK$57:CN$57)/CO$57} -> 0.26622399 | CP53: =CN53 -> 0.26431718 | CQ53: =CP53 -> 0.26431718 | CR53: =CQ53 -> 0.26431718 | CS53: =CR53 -> 0.26431718 | CT53: {=SUM(CP53:CS53*CP$57:CS$57)/CT$57} -> 0.26235892 | CU53: =CS53 -> 0.26431718 | CV53: =CU53 -> 0.26431718 | CW53: =CV53 -> 0.26431718 | CX53: =CW53 -> 0.26431718 | CY53: {=SUM(CU53:CX53*CU$57:CX$57)/CY$57} -> 0.26414753 | CZ53: =CX53 -> 0.26431718 | DA53: =CZ53 -> 0.26431718 | DB53: =DA53 -> 0.26431718 | DC53: =DB53 -> 0.26431718 | DD53: {=SUM(CZ53:DC53*CZ$57:DC$57)/DD$57} -> 0.26532444 | DE53: =DC53 -> 0.26431718 | DF53: =DE53 -> 0.26431718 | DG53: =DF53 -> 0.26431718 | DH53: =DG53 -> 0.26431718 | DI53: {=SUM(DE53:DH53*DE$57:DH$57)/DI$57} -> 0.28961962 | DJ53: =DH53 -> 0.26431718 | DK53: =DJ53 -> 0.26431718 | DL53: =DK53 -> 0.26431718 | DM53: =DL53 -> 0.26431718 | DN53: {=SUM(DJ53:DM53*DJ$57:DM$57)/DN$57} -> 0.26406971 | DO53: =DM53 -> 0.26431718 | DP53: =DO53 -> 0.26431718 | DQ53: =DP53 -> 0.26431718 | DR53: =DQ53 -> 0.26431718 | DS53: {=SUM(DO53:DR53*DO$57:DR$57)/DS$57} -> 0.26448248 | DT53: =DR53 -> 0.26431718 | DU53: =DT53 -> 0.26431718 | DV53: =DU53 -> 0.26431718 | DW53: =DV53 -> 0.26431718 | DX53: {=SUM(DT53:DW53*DT$57:DW$57)/DX$57} -> 0.26541947 | DY53: =DW53 -> 0.26431718 | DZ53: =DY53 -> 0.26431718 | EA53: =DZ53 -> 0.26431718 | EB53: =EA53 -> 0.26431718 | EC53: {=SUM(DY53:EB53*DY$57:EB$57)/EC$57} -> 0.26247576 | ED53: =EB53 -> 0.26431718 | EE53: =ED53 -> 0.26431718 | EF53: =EE53 -> 0.26431718 | EG53: =EF53 -> 0.26431718 | EH53: {=SUM(ED53:EG53*ED$57:EG$57)/EH$57} -> -0.2167932 | EI53: =EG53 -> 0.26431718 | EJ53: =EI53 -> 0.26431718 | EK53: =EJ53 -> 0.26431718 | EL53: =EK53 -> 0.26431718 | EM53: {=SUM(EI53:EL53*EI$57:EL$57)/EM$57} -> #ERROR! | EN53: =EL53 -> 0.26431718 | EO53: =EN53 -> 0.26431718 | EP53: =EO53 -> 0.26431718 | EQ53: =EP53 -> 0.26431718 | ER53: {=SUM(EN53:EQ53*EN$57:EQ$57)/ER$57} -> #ERROR! | ES53: =EQ53 -> 0.26431718 | ET53: =ES53 -> 0.26431718 | EU53: =ET53 -> 0.26431718 | EV53: =EU53 -> 0.26431718 | EW53: {=SUM(ES53:EV53*ES$57:EV$57)/EW$57} -> #ERROR! | EX53: =EV53 -> 0.26431718 | EY53: =EX53 -> 0.26431718 | EZ53: =EY53 -> 0.26431718 | FA53: =EZ53 -> 0.26431718 | FB53: {=SUM(EX53:FA53*EX$57:FA$57)/FB$57} -> #ERROR! | FC53: =FA53 -> 0.26431718 | FD53: =FC53 -> 0.26431718 | FE53: =FD53 -> 0.26431718 | FF53: =FE53 -> 0.26431718 | FG53: {=SUM(FC53:FF53*FC$57:FF$57)/FG$57} -> #ERROR!
B54: % Options Expense R&D | BB54: =135/BB56 -> 0.36096257 | BC54: =126/BC56 -> 0.37951807 | BD54: =107/BD56 -> 0.31940299 | BE54: =119/BE56 -> 0.35628743 | BF54: {=SUM(BB54:BE54*BB$57:BE$57)/BF$57} -> 0.35389535 | BG54: =114/BG56 -> 0.40140845 | BH54: =94/BH56 -> 0.39662447 | BI54: =93/BI56 -> 0.40969163 | BJ54: =BI54 -> 0.40969163 | BK54: {=SUM(BG54:BJ54*BG$57:BJ$57)/BK$57} -> 0.40394769 | BL54: =BJ54 -> 0.40969163 | BM54: =BL54 -> 0.40969163 | BN54: =BM54 -> 0.40969163 | BO54: =BN54 -> 0.40969163 | BP54: {=SUM(BL54:BO54*BL$57:BO$57)/BP$57} -> 0.40969163 | BQ54: =BO54 -> 0.40969163 | BR54: =BQ54 -> 0.40969163 | BS54: =BR54 -> 0.40969163 | BT54: =BS54 -> 0.40969163 | BU54: {=SUM(BQ54:BT54*BQ$57:BT$57)/BU$57} -> 0.42497738 | BV54: =BT54 -> 0.40969163 | BW54: =BV54 -> 0.40969163 | BX54: =BW54 -> 0.40969163 | BY54: =BX54 -> 0.40969163 | BZ54: {=SUM(BV54:BY54*BV$57:BY$57)/BZ$57} -> 0.40969163 | CA54: =BY54 -> 0.40969163 | CB54: =CA54 -> 0.40969163 | CC54: =CB54 -> 0.40969163 | CD54: =CC54 -> 0.40969163 | CE54: {=SUM(CA54:CD54*CA$57:CD$57)/CE$57} -> 0.4102781 | CF54: =CD54 -> 0.40969163 | CG54: =CF54 -> 0.40969163 | CH54: =CG54 -> 0.40969163 | CI54: =CH54 -> 0.40969163 | CJ54: {=SUM(CF54:CI54*CF$57:CI$57)/CJ$57} -> 0.41035001 | CK54: =CI54 -> 0.40969163 | CL54: =CK54 -> 0.40969163 | CM54: =CL54 -> 0.40969163 | CN54: =CM54 -> 0.40969163 | CO54: {=SUM(CK54:CN54*CK$57:CN$57)/CO$57} -> 0.41264718 | CP54: =CN54 -> 0.40969163 | CQ54: =CP54 -> 0.40969163 | CR54: =CQ54 -> 0.40969163 | CS54: =CR54 -> 0.40969163 | CT54: {=SUM(CP54:CS54*CP$57:CS$57)/CT$57} -> 0.40665633 | CU54: =CS54 -> 0.40969163 | CV54: =CU54 -> 0.40969163 | CW54: =CV54 -> 0.40969163 | CX54: =CW54 -> 0.40969163 | CY54: {=SUM(CU54:CX54*CU$57:CX$57)/CY$57} -> 0.40942868 | CZ54: =CX54 -> 0.40969163 | DA54: =CZ54 -> 0.40969163 | DB54: =DA54 -> 0.40969163 | DC54: =DB54 -> 0.40969163 | DD54: {=SUM(CZ54:DC54*CZ$57:DC$57)/DD$57} -> 0.41125288 | DE54: =DC54 -> 0.40969163 | DF54: =DE54 -> 0.40969163 | DG54: =DF54 -> 0.40969163 | DH54: =DG54 -> 0.40969163 | DI54: {=SUM(DE54:DH54*DE$57:DH$57)/DI$57} -> 0.44891041 | DJ54: =DH54 -> 0.40969163 | DK54: =DJ54 -> 0.40969163 | DL54: =DK54 -> 0.40969163 | DM54: =DL54 -> 0.40969163 | DN54: {=SUM(DJ54:DM54*DJ$57:DM$57)/DN$57} -> 0.40930806 | DO54: =DM54 -> 0.40969163 | DP54: =DO54 -> 0.40969163 | DQ54: =DP54 -> 0.40969163 | DR54: =DQ54 -> 0.40969163 | DS54: {=SUM(DO54:DR54*DO$57:DR$57)/DS$57} -> 0.40994785 | DT54: =DR54 -> 0.40969163 | DU54: =DT54 -> 0.40969163 | DV54: =DU54 -> 0.40969163 | DW54: =DV54 -> 0.40969163 | DX54: {=SUM(DT54:DW54*DT$57:DW$57)/DX$57} -> 0.41140018 | DY54: =DW54 -> 0.40969163 | DZ54: =DY54 -> 0.40969163 | EA54: =DZ54 -> 0.40969163 | EB54: =EA54 -> 0.40969163 | EC54: {=SUM(DY54:EB54*DY$57:EB$57)/EC$57} -> 0.40683743 | ED54: =EB54 -> 0.40969163 | EE54: =ED54 -> 0.40969163 | EF54: =EE54 -> 0.40969163 | EG54: =EF54 -> 0.40969163 | EH54: {=SUM(ED54:EG54*ED$57:EG$57)/EH$57} -> -0.33602946 | EI54: =EG54 -> 0.40969163 | EJ54: =EI54 -> 0.40969163 | EK54: =EJ54 -> 0.40969163 | EL54: =EK54 -> 0.40969163 | EM54: {=SUM(EI54:EL54*EI$57:EL$57)/EM$57} -> #ERROR! | EN54: =EL54 -> 0.40969163 | EO54: =EN54 -> 0.40969163 | EP54: =EO54 -> 0.40969163 | EQ54: =EP54 -> 0.40969163 | ER54: {=SUM(EN54:EQ54*EN$57:EQ$57)/ER$57} -> #ERROR! | ES54: =EQ54 -> 0.40969163 | ET54: =ES54 -> 0.40969163 | EU54: =ET54 -> 0.40969163 | EV54: =EU54 -> 0.40969163 | EW54: {=SUM(ES54:EV54*ES$57:EV$57)/EW$57} -> #ERROR! | EX54: =EV54 -> 0.40969163 | EY54: =EX54 -> 0.40969163 | EZ54: =EY54 -> 0.40969163 | FA54: =EZ54 -> 0.40969163 | FB54: {=SUM(EX54:FA54*EX$57:FA$57)/FB$57} -> #ERROR! | FC54: =FA54 -> 0.40969163 | FD54: =FC54 -> 0.40969163 | FE54: =FD54 -> 0.40969163 | FF54: =FE54 -> 0.40969163 | FG54: {=SUM(FC54:FF54*FC$57:FF$57)/FG$57} -> #ERROR!
B55: % Options Expense MG&A | BB55: =1-BB53-BB54 -> 0.40909091 | BC55: =1-BC53-BC54 -> 0.42168675 | BD55: =1-BD53-BD54 -> 0.37313433 | BE55: =1-BE53-BE54 -> 0.36227545 | BF55: {=SUM(BB55:BE55*BB$57:BE$57)/BF$57} -> 0.39191231 | BG55: =1-BG53-BG54 -> 0.32394366 | BH55: =1-BH53-BH54 -> 0.33333333 | BI55: =1-BI53-BI54 -> 0.32599119 | BJ55: =1-BJ53-BJ54 -> 0.32599119 | BK55: {=SUM(BG55:BJ55*BG$57:BJ$57)/BK$57} -> 0.32724141 | BL55: =1-BL53-BL54 -> 0.32599119 | BM55: =1-BM53-BM54 -> 0.32599119 | BN55: =1-BN53-BN54 -> 0.32599119 | BO55: =1-BO53-BO54 -> 0.32599119 | BP55: {=SUM(BL55:BO55*BL$57:BO$57)/BP$57} -> 0.32599119 | BQ55: =1-BQ53-BQ54 -> 0.32599119 | BR55: =1-BR53-BR54 -> 0.32599119 | BS55: =1-BS53-BS54 -> 0.32599119 | BT55: =1-BT53-BT54 -> 0.32599119 | BU55: {=SUM(BQ55:BT55*BQ$57:BT$57)/BU$57} -> 0.33815404 | BV55: =1-BV53-BV54 -> 0.32599119 | BW55: =1-BW53-BW54 -> 0.32599119 | BX55: =1-BX53-BX54 -> 0.32599119 | BY55: =1-BY53-BY54 -> 0.32599119 | BZ55: {=SUM(BV55:BY55*BV$57:BY$57)/BZ$57} -> 0.32599119 | CA55: =1-CA53-CA54 -> 0.32599119 | CB55: =1-CB53-CB54 -> 0.32599119 | CC55: =1-CC53-CC54 -> 0.32599119 | CD55: =1-CD53-CD54 -> 0.32599119 | CE55: {=SUM(CA55:CD55*CA$57:CD$57)/CE$57} -> 0.32645784 | CF55: =1-CF53-CF54 -> 0.32599119 | CG55: =1-CG53-CG54 -> 0.32599119 | CH55: =1-CH53-CH54 -> 0.32599119 | CI55: =1-CI53-CI54 -> 0.32599119 | CJ55: {=SUM(CF55:CI55*CF$57:CI$57)/CJ$57} -> 0.32651506 | CK55: =1-CK53-CK54 -> 0.32599119 | CL55: =1-CL53-CL54 -> 0.32599119 | CM55: =1-CM53-CM54 -> 0.32599119 | CN55: =1-CN53-CN54 -> 0.32599119 | CO55: {=SUM(CK55:CN55*CK$57:CN$57)/CO$57} -> 0.32834292 | CP55: =1-CP53-CP54 -> 0.32599119 | CQ55: =1-CQ53-CQ54 -> 0.32599119 | CR55: =1-CR53-CR54 -> 0.32599119 | CS55: =1-CS53-CS54 -> 0.32599119 | CT55: {=SUM(CP55:CS55*CP$57:CS$57)/CT$57} -> 0.323576 | CU55: =1-CU53-CU54 -> 0.32599119 | CV55: =1-CV53-CV54 -> 0.32599119 | CW55: =1-CW53-CW54 -> 0.32599119 | CX55: =1-CX53-CX54 -> 0.32599119 | CY55: {=SUM(CU55:CX55*CU$57:CX$57)/CY$57} -> 0.32578196 | CZ55: =1-CZ53-CZ54 -> 0.32599119 | DA55: =1-DA53-DA54 -> 0.32599119 | DB55: =1-DB53-DB54 -> 0.32599119 | DC55: =1-DC53-DC54 -> 0.32599119 | DD55: {=SUM(CZ55:DC55*CZ$57:DC$57)/DD$57} -> 0.32723348 | DE55: =1-DE53-DE54 -> 0.32599119 | DF55: =1-DF53-DF54 -> 0.32599119 | DG55: =1-DG53-DG54 -> 0.32599119 | DH55: =1-DH53-DH54 -> 0.32599119 | DI55: {=SUM(DE55:DH55*DE$57:DH$57)/DI$57} -> 0.35719753 | DJ55: =1-DJ53-DJ54 -> 0.32599119 | DK55: =1-DK53-DK54 -> 0.32599119 | DL55: =1-DL53-DL54 -> 0.32599119 | DM55: =1-DM53-DM54 -> 0.32599119 | DN55: {=SUM(DJ55:DM55*DJ$57:DM$57)/DN$57} -> 0.32568598 | DO55: =1-DO53-DO54 -> 0.32599119 | DP55: =1-DP53-DP54 -> 0.32599119 | DQ55: =1-DQ53-DQ54 -> 0.32599119 | DR55: =1-DR53-DR54 -> 0.32599119 | DS55: {=SUM(DO55:DR55*DO$57:DR$57)/DS$57} -> 0.32619506 | DT55: =1-DT53-DT54 -> 0.32599119 | DU55: =1-DU53-DU54 -> 0.32599119 | DV55: =1-DV53-DV54 -> 0.32599119 | DW55: =1-DW53-DW54 -> 0.32599119 | DX55: {=SUM(DT55:DW55*DT$57:DW$57)/DX$57} -> 0.32735068 | DY55: =1-DY53-DY54 -> 0.32599119 | DZ55: =1-DZ53-DZ54 -> 0.32599119 | EA55: =1-EA53-EA54 -> 0.32599119 | EB55: =1-EB53-EB54 -> 0.32599119 | EC55: {=SUM(DY55:EB55*DY$57:EB$57)/EC$57} -> 0.32372011 | ED55: =1-ED53-ED54 -> 0.32599119 | EE55: =1-EE53-EE54 -> 0.32599119 | EF55: =1-EF53-EF54 -> 0.32599119 | EG55: =1-EG53-EG54 -> 0.32599119 | EH55: {=SUM(ED55:EG55*ED$57:EG$57)/EH$57} -> -0.26737828 | EI55: =1-EI53-EI54 -> 0.32599119 | EJ55: =1-EJ53-EJ54 -> 0.32599119 | EK55: =1-EK53-EK54 -> 0.32599119 | EL55: =1-EL53-EL54 -> 0.32599119 | EM55: {=SUM(EI55:EL55*EI$57:EL$57)/EM$57} -> #ERROR! | EN55: =1-EN53-EN54 -> 0.32599119 | EO55: =1-EO53-EO54 -> 0.32599119 | EP55: =1-EP53-EP54 -> 0.32599119 | EQ55: =1-EQ53-EQ54 -> 0.32599119 | ER55: {=SUM(EN55:EQ55*EN$57:EQ$57)/ER$57} -> #ERROR! | ES55: =1-ES53-ES54 -> 0.32599119 | ET55: =1-ET53-ET54 -> 0.32599119 | EU55: =1-EU53-EU54 -> 0.32599119 | EV55: =1-EV53-EV54 -> 0.32599119 | EW55: {=SUM(ES55:EV55*ES$57:EV$57)/EW$57} -> #ERROR! | EX55: =1-EX53-EX54 -> 0.32599119 | EY55: =1-EY53-EY54 -> 0.32599119 | EZ55: =1-EZ53-EZ54 -> 0.32599119 | FA55: =1-FA53-FA54 -> 0.32599119 | FB55: {=SUM(EX55:FA55*EX$57:FA$57)/FB$57} -> #ERROR! | FC55: =1-FC53-FC54 -> 0.32599119 | FD55: =1-FD53-FD54 -> 0.32599119 | FE55: =1-FE53-FE54 -> 0.32599119 | FF55: =1-FF53-FF54 -> 0.32599119 | FG55: {=SUM(FC55:FF55*FC$57:FF$57)/FG$57} -> #ERROR!
B56: Stock option expense | BB56: =86+135+153 -> 374 | BC56: =66+126+140 -> 332 | BD56: =103+107+125 -> 335 | BE56: =94+119+121 -> 334 | BF56: =SUM(BB56:BE56) -> 1375 | BG56: =78+114+92 -> 284 | BH56: =64+94+79 -> 237 | BI56: =60+93+74 -> 227 | BJ56: =CF!BJ13 -> 204 | BK56: =SUM(BG56:BJ56) -> 952 | BL56: =CF!BL13 -> 219 | BM56: =CF!BM13 -> 243 | BN56: =CF!BN13 -> 197 | BO56: =CF!BO13 -> 192 | BP56: =SUM(BL56:BO56) -> 851 | BQ56: =CF!BQ13 -> 213 | BR56: =CF!BR13 -> 258 | BS56: =CF!BS13 -> 218 | BT56: =CF!BT13 -> 200 | BU56: =SUM(BQ56:BT56) -> 889 | BV56: =CF!BV13 -> 248 | BW56: =CF!BW13 -> 232 | BX56: =CF!BX13 -> 224 | BY56: =CF!BY13 -> 213 | BZ56: =SUM(BV56:BY56) -> 917 | CA56: =CF!CA13 -> 300 | CB56: =CF!CB13 -> 262 | CC56: =CF!CC13 -> 250 | CD56: 241 | CE56: =SUM(CA56:CD56) -> 1053 | CF56: 274 | CG56: 280 | CH56: 276 | CI56: 275 | CJ56: =SUM(CF56:CI56) -> 1105 | CK56: 295 | CL56: =CO56/4 -> 287.5 | CM56: =CO56/4 -> 287.5 | CN56: =CO56-SUM(CK56:CM56) -> 280 | CO56: 1150 | CP56: 283 | CQ56: 303 | CR56: 281 | CS56: =CT56-SUM(CP56:CR56) -> 283 | CT56: =CO56 -> 1150 | CU56: 368 | CV56: 332 | CW56: 309 | CX56: 296 | CY56: =SUM(CU56:CX56) -> 1305 | CZ56: 448 | DA56: 364 | DB56: 324 | DC56: 308 | DD56: =SUM(CZ56:DC56) -> 1444 | DE56: 397 | DF56: 328 | DG56: 350 | DH56: =DG56 -> 350 | DI56: =SUM(DE56:DH56) -> 1425 | DJ56: 433 | DK56: 387 | DL56: 383 | DM56: 343 | DN56: =SUM(DJ56:DM56) -> 1546 | DO56: 389 | DP56: 470 | DQ56: =DQ88 -> 431 | DR56: =DR88 -> 545.643 | DS56: =SUM(DO56:DR56) -> 1835.643 | DT56: =DT88 -> 449 | DU56: =DU88 -> 492 | DV56: =DV88 -> 452 | DW56: =DW88 -> 461 | DX56: =SUM(DT56:DW56) -> 1854 | DY56: =DY88 -> 425 | DZ56: =DZ88 -> 619 | EA56: =EA88 -> 543 | EB56: =EB88 -> 449 | EC56: =SUM(DY56:EB56) -> 2036 | ED56: =ED88 -> 707 | EE56: =EE88 -> 892 | EF56: =EF88 -> 793 | EG56: =EG88 -> 736 | EH56: =SUM(ED56:EG56) -> 3128 | EI56: =EI88 -> #ERROR! | EJ56: =EJ88 -> #ERROR! | EK56: =EK88 -> #ERROR! | EL56: =EL88 -> #ERROR! | EM56: =SUM(EI56:EL56) -> #ERROR! | EN56: =EN88 -> #ERROR! | EO56: =EO88 -> #ERROR! | EP56: =EP88 -> #ERROR! | EQ56: =EQ88 -> #ERROR! | ER56: =SUM(EN56:EQ56) -> #ERROR! | ES56: =ES88 -> #ERROR! | ET56: =ET88 -> #ERROR! | EU56: =EU88 -> #ERROR! | EV56: =EV88 -> #ERROR! | EW56: =SUM(ES56:EV56) -> #ERROR! | EX56: =EX88 -> #ERROR! | EY56: =EY88 -> #ERROR! | EZ56: =EZ88 -> #ERROR! | FA56: =FA88 -> #ERROR! | FB56: =SUM(EX56:FA56) -> #ERROR! | FC56: =FC88 -> #ERROR! | FD56: =FD88 -> #ERROR! | FE56: =FE88 -> #ERROR! | FF56: =FF88 -> #ERROR! | FG56: =SUM(FC56:FF56) -> #ERROR!
B57: Stock based compensation (net of tax) | H57: 111 | I57: =M57/4 -> 52.5 | J57: =M57/4 -> 52.5 | K57: =M57/4 -> 52.5 | L57: =M57/4 -> 52.5 | M57: 210 | N57: =R57/4 -> 78.25 | O57: =R57/4 -> 78.25 | P57: =R57/4 -> 78.25 | Q57: =R57/4 -> 78.25 | R57: 313 | S57: =W57/4 -> 113.5 | T57: =W57/4 -> 113.5 | U57: =W57/4 -> 113.5 | V57: =W57/4 -> 113.5 | W57: 454 | X57: =AB57/4 -> 209 | Y57: =AB57/4 -> 209 | Z57: =AB57/4 -> 209 | AA57: =AB57/4 -> 209 | AB57: 836 | AC57: =AG57/4 -> 259.25 | AD57: =AG57/4 -> 259.25 | AE57: =AG57/4 -> 259.25 | AF57: =AG57/4 -> 259.25 | AG57: 1037 | AH57: 287 | AI57: 309 | AJ57: 274 | AK57: 300 | AL57: =SUM(AH57:AK57) -> 1170 | AM57: 298 | AN57: 290 | AO57: 298 | AP57: 105 | AQ57: =SUM(AM57:AP57) -> 991 | AR57: 288 | AS57: 297 | AT57: 295 | AU57: 391 | AV57: =SUM(AR57:AU57) -> 1271 | AW57: 333 | AX57: 293 | AY57: 291 | AZ57: =BA57-SUM(AW57:AY57) -> 345 | BA57: 1262 | BB57: =BB56-110 -> 264 | BC57: =BC56-93 -> 239 | BD57: =BD56-87 -> 248 | BE57: =BE56-98 -> 236 | BF57: =SUM(BB57:BE57) -> 987 | BG57: =BG56*(1-BG110) -> 198.63321 | BH57: =BH56*(1-BH110) -> 170.03859 | BI57: =BI56*(1-BI110) -> 162.532 | BJ57: =BJ56*(1-BJ110) -> 142.06808 | BK57: =SUM(BG57:BJ57) -> 673.27187 | BL57: =BL56*(1-BL110) -> 145.56287 | BM57: =BM56*(1-BM110) -> 168.19844 | BN57: =BN56*(1-BN110) -> 140.04871 | BO57: =BO56*(1-BO110) -> 136.512 | BP57: =SUM(BL57:BO57) -> 590.32203 | BQ57: =BQ56*(1-BQ110) -> 213 | BR57: =BR56*(1-BR110) -> 193.73085 | BS57: =BS56*(1-BS110) -> 159.79779 | BT57: =BT56*(1-BT110) -> 161.02004 | BU57: =BU56*(1-BU110) -> 701.37993 | BV57: =BV56*(1-BV110) -> 175.74463 | BW57: =BW56*(1-BW110) -> 160.04397 | BX57: =BX56*(1-BX110) -> 155.70924 | BY57: =BY56*(1-BY110) -> 162.70478 | BZ57: =SUM(BV57:BY57) -> 654.20262 | CA57: =CA56*(1-CA110) -> 216.88401 | CB57: =CB56*(1-CB110) -> 196.88324 | CC57: =CC56*(1-CC110) -> 177.22813 | CD57: =CD56*(1-CD110) -> 176.53368 | CE57: =CE56*(1-CE110) -> 766.43192 | CF57: =CF56*(1-CF110) -> 196.69953 | CG57: =CG56*(1-CG110) -> 201.20996 | CH57: =CH56*(1-CH110) -> 209.19969 | ... FG57: =FG56*(1-FG110) -> #ERROR!
B58: Goodwill | N58: 0 | O58: 0 | P58: -16 | Q58: =R58-SUM(N58:P58) -> -1 | R58: =-56+39 -> -17 | S58: -18 | T58: -31 | U58: -121 | V58: =W58-SUM(S58:U58) -> -137 | W58: =-411+104 -> -307 | X58: -313 | Y58: -394 | Z58: -420 | AA58: =AB58-SUM(X58:Z58) -> -183 | AB58: =-1586+276 -> -1310 | AC58: -441 | AD58: -417 | AE58: -447 | AF58: =AG58-SUM(AC58:AE58) -> -307 | AG58: =-1710+98 -> -1612 | AH58: 0 | AI58: 0 | AJ58: 0 | AK58: =AL58-SUM(AH58:AJ58) -> 0 | AL58: 0 | AM58: 0 | AN58: 0 | AO58: 0 | AP58: 0 | AQ58: 0 | AR58: 0 | AS58: 0 | AT58: 0 | AU58: 0 | AV58: 0 | AW58: 0 | AX58: 0 | AY58: 0 | AZ58: 0 | BA58: 0 | BB58: 0 | BC58: 0 | BD58: 0 | BE58: 0 | BF58: 0 | BG58: 0 | BH58: 0 | BI58: 0 | BJ58: 0 | BK58: 0 | BL58: 0 | BM58: 0 | BN58: 0 | BO58: 0 | BP58: 0 | BQ58: 0 | BR58: 0 | BS58: 0 | BT58: 0 | BU58: 0 | BV58: 0 | BW58: 0 | BX58: 0 | BY58: 0 | BZ58: 0 | CA58: 0 | CB58: 0 | CC58: 0 | CD58: 0 | CE58: 0 | CF58: 0 | CG58: 0 | CH58: 0 | CI58: 0 | CJ58: 0 | CK58: 0 | CL58: 0 | CM58: 0 | CN58: 0 | CO58: 0 | CP58: 0 | CQ58: 0 | CR58: 0 | CS58: 0 | CT58: 0 | CU58: 0 | CV58: 0 | CW58: 0 | CX58: 0 | CY58: 0 | CZ58: 0 | DA58: 0 | DB58: 0 | DC58: 0 | DD58: 0 | DE58: 0 | DF58: 0 | DG58: 0 | DH58: 0 | DI58: 0 | DJ58: 0 | DK58: 0 | DL58: 0 | DM58: 0 | DN58: 0 | DO58: 0 | DP58: 0 | DQ58: 0 | DR58: 0 | DS58: 0 | DT58: 0 | DU58: 0 | DV58: 0 | DW58: 0 | DX58: 0 | DY58: 0 | DZ58: 0 | EA58: 0 | EB58: 0 | EC58: 0 | ED58: 0 | EE58: 0 | EF58: 0 | EG58: 0 | EH58: 0 | EI58: 0 | EJ58: 0 | EK58: 0 | EL58: 0 | EM58: 0 | EN58: 0 | EO58: 0 | EP58: 0 | EQ58: 0 | ER58: 0 | ES58: 0 | ET58: 0 | EU58: 0 | EV58: 0 | EW58: 0 | EX58: 0 | EY58: 0 | EZ58: 0 | FA58: 0 | FB58: 0 | FC58: 0 | FD58: 0 | FE58: 0 | FF58: 0 | FG58: 0
B59: Pre tax charges | N59: -165 | O59: 0 | P59: 0 | Q59: =R59-SUM(N59:P59) -> -39 | R59: =-165-39 -> -204 | S59: 0 | T59: 0 | U59: -333 | V59: =W59-SUM(S59:U59) -> -163 | W59: =-392-104 -> -496 | X59: -62 | Y59: -21 | Z59: -8 | AA59: =AB59-SUM(X59:Z59) -> -294 | AB59: =-109-276 -> -385 | AC59: =-144-75 -> -219 | AD59: =-177-123 -> -300 | AE59: -162 | AF59: =AG59-SUM(AC59:AE59) -> -243 | AG59: =-628-198-98 -> -924 | AH59: -111 | AI59: =-229-14 -> -243 | AJ59: =-102-6 -> -108 | AK59: =AL59-SUM(AH59:AJ59) -> -106 | AL59: -568 | AM59: 0 | AN59: 0 | AO59: 0 | AP59: =AQ59-SUM(AM59:AO59) -> -617 | AQ59: -617 | AR59: 0 | AS59: 0 | AT59: 0 | AU59: 0 | AV59: =SUM(AR59:AU59) -> 0 | AW59: 0 | AX59: 0 | AY59: -140 | AZ59: 0 | BA59: =SUM(AW59:AZ59) -> -140 | BB59: 0 | BC59: 0 | BD59: 0 | BE59: 0 | BF59: =SUM(BB59:BE59) -> 0 | BG59: 0 | BH59: 0 | BI59: -113 | BJ59: 0 | BK59: =SUM(BG59:BJ59) -> -113 | BL59: 0 | BM59: 0 | BN59: 0 | BO59: =-762-176 -> -938 | BP59: =SUM(BL59:BO59) -> -938 | BQ59: 0 | BR59: -1447 | BS59: 0 | BT59: -1250 | BU59: =SUM(BQ59:BT59) -> -2697 | BV59: 0 | BW59: 0 | BX59: 0 | BY59: 0 | BZ59: =SUM(BV59:BY59) -> 0 | CA59: 0 | CB59: 0 | CC59: 0 | CD59: 0 | CE59: =SUM(CA59:CD59) -> 0 | CF59: 0 | CG59: 0 | CH59: 0 | CI59: 0 | CJ59: =SUM(CF59:CI59) -> 0 | CK59: 0 | CL59: 0 | CM59: 0 | CN59: 0 | CO59: =SUM(CK59:CN59) -> 0 | CP59: 0 | CQ59: 0 | CR59: 0 | CS59: 0 | CT59: =SUM(CP59:CS59) -> 0 | CU59: 0 | CV59: 0 | CW59: 0 | CX59: 0 | CY59: =SUM(CU59:CX59) -> 0 | CZ59: 0 | DA59: 0 | DB59: 0 | DC59: 0 | DD59: =SUM(CZ59:DC59) -> 0 | DE59: 0 | DF59: 0 | DG59: 0 | DH59: 0 | DI59: =SUM(DE59:DH59) -> 0 | DJ59: 0 | DK59: 0 | DL59: 0 | DM59: 0 | DN59: =SUM(DJ59:DM59) -> 0 | DO59: 0 | DP59: 0 | DQ59: 0 | DR59: 0 | DS59: =SUM(DO59:DR59) -> 0 | DT59: 0 | DU59: 0 | DV59: 0 | DW59: 0 | DX59: =SUM(DT59:DW59) -> 0 | DY59: 0 | DZ59: 0 | EA59: 0 | EB59: 0 | EC59: =SUM(DY59:EB59) -> 0 | ED59: 0 | EE59: 0 | EF59: 0 | EG59: 0 | EH59: =SUM(ED59:EG59) -> 0 | EI59: 0 | EJ59: 0 | EK59: 0 | EL59: 0 | EM59: =SUM(EI59:EL59) -> 0 | EN59: 0 | EO59: 0 | EP59: 0 | EQ59: 0 | ER59: =SUM(EN59:EQ59) -> 0 | ES59: 0 | ET59: 0 | EU59: 0 | EV59: 0 | EW59: =SUM(ES59:EV59) -> 0 | EX59: 0 | EY59: 0 | EZ59: 0 | FA59: 0 | FB59: =SUM(EX59:FA59) -> 0 | FC59: 0 | FD59: 0 | FE59: 0 | FF59: 0 | FG59: =SUM(FC59:FF59) -> 0
B60: GAAP tax | N60: =tax -> 708 | O60: =tax -> 578 | P60: =tax -> 767 | Q60: =tax -> 1016 | R60: =SUM(N60:Q60) -> 3069 | S60: 985 | T60: 861 | U60: 914 | V60: =W60-SUM(S60:U60) -> 1154 | W60: 3914 | X60: 498 | Y60: 1612 | Z60: 1314 | AA60: =AB60-SUM(X60:Z60) -> 1182 | AB60: 4606 | AC60: 421 | AD60: 150 | AE60: 31 | AF60: =AG60-SUM(AC60:AE60) -> 290 | AG60: 892 | AH60: 381 | AI60: 177 | AJ60: 231 | AK60: =AL60-SUM(AH60:AJ60) -> 298 | AL60: 1087 | AM60: =tax -> 401 | AN60: =tax -> 375 | AO60: =tax -> 618 | AP60: =AQ60-SUM(AM60:AO60) -> 407 | AQ60: 1801 | AR60: =tax -> 814 | AS60: =tax -> 663 | AT60: =tax -> 520 | AU60: =tax -> 904 | AV60: =SUM(AR60:AU60) -> 2901 | AW60: =tax -> 973 | AX60: =tax -> 716 | AY60: 1248 | AZ60: =tax -> 1009 | BA60: =SUM(AW60:AZ60) -> 3946 | BB60: =tax -> 517 | BC60: =tax -> 368 | BD60: =tax -> 513 | BE60: =tax -> 626 | BF60: =SUM(BB60:BE60) -> 2024 | BG60: 237 | BH60: 251 | BI60: 712 | BJ60: =tax -> 990 | BK60: =SUM(BG60:BJ60) -> 2190 | BL60: =tax -> 728 | BM60: =tax -> 712 | BN60: =tax -> 819 | BO60: 135 | BP60: =SUM(BL60:BO60) -> 2394 | BQ60: =tax -> 0 | BR60: =BR48 -> 348 | BS60: =tax -> 676 | BT60: 311 | BU60: =SUM(BQ60:BT60) -> 1335 | BV60: =tax -> 1004 | BW60: =tax -> 1298 | BX60: =tax -> 1296 | BY60: =tax -> 983 | BZ60: =SUM(BV60:BY60) -> 4581 | CA60: =tax -> 1211 | CB60: =tax -> 977 | CC60: =tax -> 1424 | CD60: =tax -> 1227 | CE60: =SUM(CA60:CD60) -> 4839 | CF60: =tax -> 1076 | CG60: =tax -> 1107 | CH60: =tax -> 949 | CI60: =tax -> 736 | CJ60: =SUM(CF60:CI60) -> 3868 | CK60: =tax -> 398 | CL60: =tax -> 693 | CM60: =tax -> 974 | CN60: =tax -> 926 | CO60: =SUM(CK60:CN60) -> 2991 | CP60: =tax -> 740 | CQ60: =tax -> 1126 | CR60: =tax -> 1233 | CS60: =tax -> 998 | CT60: =SUM(CP60:CS60) -> 4097 | CU60: =tax -> 681 | CV60: =tax -> 277 | CW60: =tax -> 1144 | CX60: =tax -> 690 | CY60: =SUM(CU60:CX60) -> 2792 | CZ60: =tax -> 462 | DA60: =tax -> 340 | DB60: =tax -> 940 | DC60: =tax -> 878 | DD60: =SUM(CZ60:DC60) -> 2620 | DE60: =tax -> 851 | DF60: =tax -> 1764 | DG60: =tax -> 1414 | DH60: =tax -> 6722 | DI60: =SUM(DE60:DH60) -> 10751 | DJ60: =tax -> 557 | DK60: =tax -> 523 | DL60: =tax -> 744 | DM60: =tax -> 440 | DN60: =SUM(DJ60:DM60) -> 2264 | DO60: =tax -> 573 | DP60: =tax -> 545 | DQ60: =tax -> 729 | DR60: =tax -> 1163 | DS60: =SUM(DO60:DR60) -> 3010 | DT60: =tax -> 953 | DU60: =tax -> 830 | DV60: =tax -> 765 | DW60: =tax -> 1631 | DX60: =SUM(DT60:DW60) -> 4179 | DY60: =tax -> 545 | DZ60: =tax -> 684 | EA60: =tax -> 35 | EB60: =tax -> 571 | EC60: =SUM(DY60:EB60) -> 1835 | ED60: =tax -> 1548 | EE60: =tax -> -455 | EF60: =tax -> -1207 | EG60: =tax -> -135 | EH60: =SUM(ED60:EG60) -> -249 | EI60: =tax -> #ERROR! | EJ60: =tax -> #ERROR! | EK60: =tax -> #ERROR! | EL60: =tax -> #ERROR! | EM60: =SUM(EI60:EL60) -> #ERROR! | EN60: =tax -> #ERROR! | EO60: =tax -> #ERROR! | EP60: =tax -> #ERROR! | EQ60: =tax -> #ERROR! | ER60: =SUM(EN60:EQ60) -> #ERROR! | ES60: =tax -> #ERROR! | ET60: =tax -> #ERROR! | EU60: =tax -> #ERROR! | EV60: =tax -> #ERROR! | EW60: =SUM(ES60:EV60) -> #ERROR! | EX60: =tax -> #ERROR! | EY60: =tax -> #ERROR! | EZ60: =tax -> #ERROR! | FA60: =tax -> #ERROR! | FB60: =SUM(EX60:FA60) -> #ERROR! | FC60: =tax -> #ERROR! | FD60: =tax -> #ERROR! | FE60: =tax -> #ERROR! | FF60: =tax -> #ERROR! | FG60: =SUM(FC60:FF60) -> #ERROR!
B61: Post-tax charges | N61: 0 | O61: 0 | P61: 0 | Q61: 0 | R61: =SUM(N61:Q61) -> 0 | S61: 0 | T61: 0 | U61: 0 | V61: 0 | W61: =SUM(S61:V61) -> 0 | X61: 0 | Y61: 0 | Z61: 0 | AA61: 0 | AB61: =SUM(X61:AA61) -> 0 | AC61: 0 | AD61: 0 | AE61: 0 | AF61: 0 | AG61: =SUM(AC61:AF61) -> 0 | AH61: 0 | AI61: 0 | AJ61: 0 | AK61: 0 | AL61: =SUM(AH61:AK61) -> 0 | AM61: 0 | AN61: 0 | AO61: 0 | AP61: 0 | AQ61: =SUM(AM61:AP61) -> 0 | AR61: 0 | AS61: 0 | AT61: 0 | AU61: 0 | AV61: =SUM(AR61:AU61) -> 0 | AW61: 0 | AX61: 0 | AY61: 0 | AZ61: 0 | BA61: 0 | BB61: 0 | BC61: 0 | BD61: 0 | BE61: 0 | BF61: 0 | BG61: 0 | BH61: 0 | BI61: 0 | BJ61: 0 | BK61: 0 | BL61: 0 | BM61: 0 | BN61: 0 | BO61: 0 | BP61: 0 | BQ61: 0 | BR61: 0 | BS61: 0 | BT61: 0 | BU61: 0 | BV61: 0 | BW61: 0 | BX61: 0 | BY61: 0 | BZ61: 0 | CA61: 0 | CB61: 0 | CC61: 0 | CD61: 0 | CE61: 0 | CF61: 0 | CG61: 0 | CH61: 0 | CI61: 0 | CJ61: 0 | CK61: 0 | CL61: 0 | CM61: 0 | CN61: 0 | CO61: 0 | CP61: 0 | CQ61: 0 | CR61: 0 | CS61: 0 | CT61: 0 | CU61: 0 | CV61: 0 | CW61: 0 | CX61: 0 | CY61: 0 | CZ61: 0 | DA61: 0 | DB61: 0 | DC61: 0 | DD61: =SUM(CZ61:DC61) -> 0 | DE61: 0 | DF61: 0 | DG61: 0 | DH61: 0 | DI61: =SUM(DE61:DH61) -> 0 | DJ61: 0 | DK61: 0 | DL61: 0 | DM61: 0 | DN61: =SUM(DJ61:DM61) -> 0 | DO61: 0 | DP61: 0 | DQ61: 0 | DR61: 0 | DS61: =SUM(DO61:DR61) -> 0 | DT61: 0 | DU61: 0 | DV61: 0 | DW61: 0 | DX61: =SUM(DT61:DW61) -> 0 | DY61: 0 | DZ61: 0 | EA61: 0 | EB61: 0 | EC61: =SUM(DY61:EB61) -> 0 | ED61: 0 | EE61: 0 | EF61: 0 | EG61: 0 | EH61: =SUM(ED61:EG61) -> 0 | EI61: 0 | EJ61: 0 | EK61: 0 | EL61: 0 | EM61: =SUM(EI61:EL61) -> 0 | EN61: 0 | EO61: 0 | EP61: 0 | EQ61: 0 | ER61: =SUM(EN61:EQ61) -> 0 | ES61: 0 | ET61: 0 | EU61: 0 | EV61: 0 | EW61: =SUM(ES61:EV61) -> 0 | EX61: 0 | EY61: 0 | EZ61: 0 | FA61: 0 | FB61: =SUM(EX61:FA61) -> 0 | FC61: 0 | FD61: 0 | FE61: 0 | FF61: 0 | FG61: =SUM(FC61:FF61) -> 0
B62: Extraordinary items (net of tax) | N62: =N58+N59+N61-(N60-N48) -> -165 | O62: =O58+O59+O61-(O60-O48) -> 0 | P62: =P58+P59+P61-(P60-P48) -> -16 | Q62: =Q58+Q59+Q61-(Q60-Q48) -> -40 | R62: =SUM(N62:Q62) -> -221 | S62: =S58+S59+S61-(S60-S48) -> -18 | T62: =T58+T59+T61-(T60-T48) -> -31 | U62: =U58+U59+U61-(U60-U48) -> -446 | V62: =V58+V59+V61-(V60-V48) -> -300 | W62: =SUM(S62:V62) -> -795 | X62: =X58+X59+X61-(X60-X48) -> -342 | Y62: =Y58+Y59+Y61-(Y60-Y48) -> -381 | Z62: =Z58+Z59+Z61-(Z60-Z48) -> -390 | AA62: =AA58+AA59+AA61-(AA60-AA48) -> -477 | AB62: =SUM(X62:AA62) -> -1590 | AC62: =AC58+AC59+AC61-(AC60-AC48) -> -614 | AD62: =AD58+AD59+AD61-(AD60-AD48) -> -658 | AE62: =AE58+AE59+AE61-(AE60-AE48) -> -549 | AF62: =AF58+AF59+AF61-(AF60-AF48) -> -494 | AG62: =SUM(AC62:AF62) -> -2315 | AH62: =AH58+AH59+AH61-(AH60-AH48) -> -86 | AI62: =AI58+AI59+AI61-(AI60-AI48) -> -174 | AJ62: =AJ58+AJ59+AJ61-(AJ60-AJ48) -> -82 | AK62: =AK58+AK59+AK61-(AK60-AK48) -> -5 | AL62: =SUM(AH62:AK62) -> -347 | AM62: =AM59+AM61-(AM60-AM48) -> 0 | AN62: =AN59+AN61-(AN60-AN48) -> 0 | AO62: =AO59+AO61-(AO60-AO48) -> 0 | AP62: =AP59+AP61-(AP60-AP48) -> 3 | AQ62: =SUM(AM62:AP62) -> 3 | AR62: =AR59+AR61-(AR60-AR48) -> 0 | AS62: =AS59+AS61-(AS60-AS48) -> 0 | AT62: =AT59+AT61-(AT60-AT48) -> 0 | AU62: =AU59+AU61-(AU60-AU48) -> 0 | AV62: =SUM(AR62:AU62) -> 0 | AW62: =AW59+AW61-(AW60-AW48) -> 0 | AX62: =AX59+AX61-(AX60-AX48) -> 0 | AY62: =AY59+AY61-(AY60-AY48) -> -346.036 | AZ62: =AZ59+AZ61-(AZ60-AZ48) -> 0 | BA62: =SUM(AW62:AZ62) -> -346.036 | BB62: =BB59+BB61-(BB60-BB48) -> 0 | BC62: =BC59+BC61-(BC60-BC48) -> 0 | BD62: =BD59+BD61-(BD60-BD48) -> 0 | BE62: =BE59+BE61-(BE60-BE48) -> 0 | BF62: =SUM(BB62:BE62) -> 0 | BG62: =BG59+BG61-(BG60-BG48) -> 326 | BH62: =BH59+BH61-(BH60-BH48) -> 181 | BI62: =BI59+BI61-(BI60-BI48) -> -82.056 | BJ62: =BJ59+BJ61-(BJ60-BJ48) -> 0 | BK62: =SUM(BG62:BJ62) -> 424.944 | BL62: =BL59+BL61-(BL60-BL48) -> 0 | BM62: =BM59+BM61-(BM60-BM48) -> 0 | BN62: =BN59+BN61-(BN60-BN48) -> 0 | BO62: =BO59+BO61-(BO60-BO48) -> -695.277 | BP62: =SUM(BL62:BO62) -> -695.277 | BQ62: =BQ59+BQ61-(BQ60-BQ48) -> 0 | BR62: =BR59+BR61-(BR60-BR48) -> -1447 | BS62: =BS59+BS61-(BS60-BS48) -> 0 | BT62: =BT59+BT61-(BT60-BT48) -> -812 | BU62: =SUM(BQ62:BT62) -> -2259 | BV62: =BV59+BV61-(BV60-BV48) -> 0 | BW62: =BW59+BW61-(BW60-BW48) -> 0 | BX62: =BX59+BX61-(BX60-BX48) -> 0 | BY62: =BY59+BY61-(BY60-BY48) -> 0 | BZ62: =SUM(BV62:BY62) -> 0 | CA62: =CA59+CA61-(CA60-CA48) -> 0 | CB62: =CB59+CB61-(CB60-CB48) -> 0 | CC62: =CC59+CC61-(CC60-CC48) -> 0 | CD62: =CD59+CD61-(CD60-CD48) -> 0 | CE62: =SUM(CA62:CD62) -> 0 | CF62: =CF59+CF61-(CF60-CF48) -> 0 | CG62: =CG59+CG61-(CG60-CG48) -> 0 | CH62: =CH59+CH61-(CH60-CH48) -> 0 | CI62: =CI59+CI61-(CI60-CI48) -> 0 | CJ62: =SUM(CF62:CI62) -> 0 | CK62: =CK59+CK61-(CK60-CK48) -> 0 | CL62: =CL59+CL61-(CL60-CL48) -> 0 | CM62: =CM59+CM61-(CM60-CM48) -> 0 | CN62: =CN59+CN61-(CN60-CN48) -> 0 | CO62: =SUM(CK62:CN62) -> 0 | CP62: =CP59+CP61-(CP60-CP48) -> 0 | CQ62: =CQ59+CQ61-(CQ60-CQ48) -> 0 | CR62: =CR59+CR61-(CR60-CR48) -> 0 | CS62: =CS59+CS61-(CS60-CS48) -> 0 | CT62: =SUM(CP62:CS62) -> 0 | CU62: =CU59+CU61-(CU60-CU48) -> 0 | CV62: =CV59+CV61-(CV60-CV48) -> 0 | CW62: =CW59+CW61-(CW60-CW48) -> 0 | CX62: =CX59+CX61-(CX60-CX48) -> 0 | CY62: =SUM(CU62:CX62) -> 0 | DA62: =DA59+DA61-(DA60-DA48) -> 0 | DB62: =DB59+DB61-(DB60-DB48) -> 0 | DC62: =DC59+DC61-(DC60-DC48) -> 0 | DD62: =SUM(CZ62:DC62) -> 0 | DE62: =DE59+DE61-(DE60-DE48) -> 0 | DF62: =DF59+DF61-(DF60-DF48) -> 0 | DG62: =DG59+DG61-(DG60-DG48) -> 0 | DH62: =DH59+DH61-(DH60-DH48) -> 0 | DI62: =SUM(DE62:DH62) -> 0 | DJ62: =DJ59+DJ61-(DJ60-DJ48) -> 0 | DK62: =DK59+DK61-(DK60-DK48) -> 0 | DL62: =DL59+DL61-(DL60-DL48) -> 0 | DM62: =DM59+DM61-(DM60-DM48) -> 0 | DN62: =SUM(DJ62:DM62) -> 0 | DO62: =DO59+DO61-(DO60-DO48) -> 0 | DP62: =DP59+DP61-(DP60-DP48) -> 0 | DQ62: =DQ59+DQ61-(DQ60-DQ48) -> 0 | DR62: =DR59+DR61-(DR60-DR48) -> 0 | DS62: =SUM(DO62:DR62) -> 0 | DT62: =DT59+DT61-(DT60-DT48) -> 0 | DU62: =DU59+DU61-(DU60-DU48) -> 0 | DV62: =DV59+DV61-(DV60-DV48) -> 0 | DW62: =DW59+DW61-(DW60-DW48) -> 0 | DX62: =SUM(DT62:DW62) -> 0 | DY62: =DY59+DY61-(DY60-DY48) -> 0 | DZ62: =DZ59+DZ61-(DZ60-DZ48) -> 0 | EA62: =EA59+EA61-(EA60-EA48) -> 0 | EB62: =EB59+EB61-(EB60-EB48) -> 0 | EC62: =SUM(DY62:EB62) -> 0 | ED62: =ED59+ED61-(ED60-ED48) -> 0 | EE62: =EE59+EE61-(EE60-EE48) -> 0 | EF62: =EF59+EF61-(EF60-EF48) -> 0 | EG62: 0 | EH62: =SUM(ED62:EG62) -> 0 | EI62: =EI59+EI61-(EI60-EI48) -> #ERROR! | EJ62: =EJ59+EJ61-(EJ60-EJ48) -> #ERROR! | EK62: =EK59+EK61-(EK60-EK48) -> #ERROR! | EL62: =EL59+EL61-(EL60-EL48) -> #ERROR! | EM62: =SUM(EI62:EL62) -> #ERROR! | EN62: =EN59+EN61-(EN60-EN48) -> #ERROR! | EO62: =EO59+EO61-(EO60-EO48) -> #ERROR! | EP62: =EP59+EP61-(EP60-EP48) -> #ERROR! | EQ62: =EQ59+EQ61-(EQ60-EQ48) -> #ERROR! | ER62: =SUM(EN62:EQ62) -> #ERROR! | ES62: =ES59+ES61-(ES60-ES48) -> #ERROR! | ET62: =ET59+ET61-(ET60-ET48) -> #ERROR! | EU62: =EU59+EU61-(EU60-EU48) -> #ERROR! | EV62: =EV59+EV61-(EV60-EV48) -> #ERROR! | EW62: =SUM(ES62:EV62) -> #ERROR! | EX62: =EX59+EX61-(EX60-EX48) -> #ERROR! | EY62: =EY59+EY61-(EY60-EY48) -> #ERROR! | EZ62: =EZ59+EZ61-(EZ60-EZ48) -> #ERROR! | FA62: =FA59+FA61-(FA60-FA48) -> #ERROR! | FB62: =SUM(EX62:FA62) -> #ERROR! | FC62: =FC59+FC61-(FC60-FC48) -> #ERROR! | FD62: =FD59+FD61-(FD60-FD48) -> #ERROR! | FE62: =FE59+FE61-(FE60-FE48) -> #ERROR! | FF62: =FF59+FF61-(FF60-FF48) -> #ERROR! | FG62: =SUM(FC62:FF62) -> #ERROR!
B63: GAAP net income | N63: =N51+N62 -> 1273 | O63: =O51+O62 -> 1172 | P63: =P51+P62 -> 1559 | Q63: =Q51+Q62 -> 2064 | R63: =SUM(N63:Q63) -> 6068 | S63: =S51+S62 -> 1999 | T63: =T51+T62 -> 1749 | U63: =U51+U62 -> 1458 | V63: =V51+V62 -> 2108 | W63: =SUM(S63:V63) -> 7314 | X63: =X51+X62 -> 2696 | Y63: =Y51+Y62 -> 3137 | Z63: =Z51+Z62 -> 2509 | AA63: =AA51+AA62 -> 2193 | AB63: =SUM(X63:AA63) -> 10535 | AC63: =AC51+AC62 -> 485 | AD63: =AD51+AD62 -> 196 | AE63: =AE51+AE62 -> 106 | AF63: =AF51+AF62 -> 504 | AG63: =SUM(AC63:AF63) -> 1291 | AH63: =AH51+AH62 -> 936 | AI63: =AI51+AI62 -> 446 | AJ63: =AJ51+AJ62 -> 686 | AK63: =AK51+AK62 -> 1049 | AL63: =SUM(AH63:AK63) -> 3117 | AM63: =AM51+AM62 -> 915 | AN63: =AN51+AN62 -> 896 | AO63: =AO51+AO62 -> 1657 | AP63: =AP51+AP62 -> 2173 | AQ63: =SUM(AM63:AP63) -> 5641 | AR63: =AR51+AR62 -> 1730 | AS63: =AS51+AS62 -> 1757 | AT63: =AT51+AT62 -> 1906 | AU63: =AU51+AU62 -> 2123 | AV63: =SUM(AR63:AU63) -> 7516 | AW63: =AW51+AW62 -> 2178 | AX63: =AX51+AX62 -> 2038 | AY63: =AY51+AY62 -> 1995 | AZ63: =AZ51+AZ62 -> 2453 | BA63: =SUM(AW63:AZ63) -> 8664 | BB63: =BB51+BB62 -> 1357 | BC63: =BC51+BC62 -> 885 | BD63: =BD51+BD62 -> 1301 | BE63: =BE51+BE62 -> 1501 | BF63: =SUM(BB63:BE63) -> 5044 | BG63: =BG51+BG62 -> 1636 | BH63: =BH51+BH62 -> 1278 | BI63: =BI51+BI62 -> 1791 | BJ63: =BJ51+BJ62 -> 2271 | BK63: =SUM(BG63:BJ63) -> 6976 | BL63: =BL51+BL62 -> 1443 | BM63: =BM51+BM62 -> 1601 | BN63: =BN51+BN62 -> 2014 | BO63: =BO51+BO62 -> 234 | BP63: =SUM(BL63:BO63) -> 5292 | BQ63: =BQ51+BQ62 -> 629 | BR63: =BR51+BR62 -> -398 | BS63: =BS51+BS62 -> 1856 | BT63: =BT51+BT62 -> 2282 | BU63: =SUM(BQ63:BT63) -> 4369 | BV63: =BV51+BV62 -> 2442 | BW63: =BW51+BW62 -> 2887 | BX63: =BX51+BX62 -> 2955 | BY63: =BY51+BY62 -> 3180 | BZ63: =SUM(BV63:BY63) -> 11464 | CA63: =CA51+CA62 -> 3160 | CB63: =CB51+CB62 -> 2954 | CC63: =CC51+CC62 -> 3468 | CD63: =CD51+CD62 -> 3360 | CE63: =SUM(CA63:CD63) -> 12942 | CF63: =CF51+CF62 -> 2738 | CG63: =CG51+CG62 -> 2827 | CH63: =CH51+CH62 -> 2972 | CI63: =CI51+CI62 -> 2468 | CJ63: =SUM(CF63:CI63) -> 11005 | CK63: =CK51+CK62 -> 2045 | CL63: =CL51+CL62 -> 2000 | CM63: =CM51+CM62 -> 2950 | CN63: =CN51+CN62 -> 2625 | CO63: =SUM(CK63:CN63) -> 9620 | CP63: =CP51+CP62 -> 1953 | CQ63: =CQ51+CQ62 -> 2796 | CR63: =CR51+CR62 -> 3317 | CS63: =CS51+CS62 -> 3661 | CT63: =SUM(CP63:CS63) -> 11727 | CU63: =CU51+CU62 -> 1992 | CV63: =CV51+CV62 -> 2706 | CW63: =CW51+CW62 -> 3109 | CX63: =CX51+CX62 -> 3613 | CY63: =SUM(CU63:CX63) -> 11420 | CZ63: =CZ51+CZ62 -> 2046 | DA63: =DA51+DA62 -> 1330 | DB63: =DB51+DB62 -> 3378 | DC63: =DC51+DC62 -> 3562 | DD63: =SUM(CZ63:DC63) -> 10316 | DE63: =DE51+DE62 -> 2964 | DF63: =DF51+DF62 -> 2808 | DG63: =DG51+DG62 -> 4516 | DH63: =DH51+DH62 -> -687 | DI63: =SUM(DE63:DH63) -> 9601 | DJ63: =DJ51+DJ62 -> 4454 | DK63: =DK51+DK62 -> 5006 | DL63: =DL51+DL62 -> 6398 | DM63: =DM51+DM62 -> 5195 | DN63: =SUM(DJ63:DM63) -> 21053 | DO63: =DO51+DO62 -> 3974 | DP63: =DP51+DP62 -> 4179 | DQ63: =DQ51+DQ62 -> 5990 | DR63: =DR51+DR62 -> 6905 | DS63: =SUM(DO63:DR63) -> 21048 | DT63: =DT51+DT62 -> 5661 | DU63: =DU51+DU62 -> 5105 | DV63: =DV51+DV62 -> 4276 | DW63: =DW51+DW62 -> 5857 | DX63: =SUM(DT63:DW63) -> 20899 | DY63: =DY51+DY62 -> 3361 | DZ63: =DZ51+DZ62 -> 5061 | EA63: =EA51+EA62 -> 6823 | EB63: =EB51+EB62 -> 4623 | EC63: =SUM(DY63:EB63) -> 19868 | ED63: =ED51+ED62 -> 8113 | EE63: =EE51+EE62 -> -454 | EF63: =EF51+EF62 -> 1019 | EG63: =EG51+EG62 -> -661 | EH63: =SUM(ED63:EG63) -> 8017 | EI63: =EI51+EI62 -> #ERROR! | EJ63: =EJ51+EJ62 -> #ERROR! | EK63: =EK51+EK62 -> #ERROR! | EL63: =EL51+EL62 -> #ERROR! | EM63: =SUM(EI63:EL63) -> #ERROR! | EN63: =EN51+EN62 -> #ERROR! | EO63: =EO51+EO62 -> #ERROR! | EP63: =EP51+EP62 -> #ERROR! | EQ63: =EQ51+EQ62 -> #ERROR! | ER63: =SUM(EN63:EQ63) -> #ERROR! | ES63: =ES51+ES62 -> #ERROR! | ET63: =ET51+ET62 -> #ERROR! | EU63: =EU51+EU62 -> #ERROR! | EV63: =EV51+EV62 -> #ERROR! | EW63: =SUM(ES63:EV63) -> #ERROR! | EX63: =EX51+EX62 -> #ERROR! | EY63: =EY51+EY62 -> #ERROR! | EZ63: =EZ51+EZ62 -> #ERROR! | FA63: =FA51+FA62 -> #ERROR! | FB63: =SUM(EX63:FA63) -> #ERROR! | FC63: =FC51+FC62 -> #ERROR! | FD63: =FD51+FD62 -> #ERROR! | FE63: =FE51+FE62 -> #ERROR! | FF63: =FF51+FF62 -> #ERROR! | FG63: =SUM(FC63:FF63) -> #ERROR!
B64: Non-GAAP net income | CP64: =CP47-CP49 -> 2077 | CQ64: =CQ47-CQ49 -> 2907 | CR64: =CR47-CR49 -> 3352 | CS64: =CS47-CS49 -> 3770 | CT64: =SUM(CP64:CS64) -> 12106 | CU64: =CU47-CU49 -> 2206 | CV64: =CV47-CV49 -> 3055 | CW64: =CW47-CW49 -> 3129 | CX64: =CX47-CX49 -> 3719 | CY64: =SUM(CU64:CX64) -> 12109 | CZ64: =CZ47-CZ49 -> 2629 | DA64: =DA47-DA49 -> 2859 | DB64: =DB47-DB49 -> 3886 | DC64: =DC47-DC49 -> 3865 | DD64: =SUM(CZ64:DC64) -> 13239 | DE64: =DE47-DE49 -> 3218 | DF64: =DF47-DF49 -> 3506.4225 | DG64: =DG47-DG49 -> 4848 | DH64: =DH47-DH49 -> 5181 | DI64: =SUM(DE64:DH64) -> 16753.423 | DJ64: =DJ47-DJ49 -> 4175 | DK64: =DK47-DK49 -> 4940.385 | DL64: =DL47-DL49 -> 6508 | DM64: =DM47-DM49 -> 5902 | DN64: =SUM(DJ64:DM64) -> 21525.385 | DO64: =DO47-DO49 -> 4048 | DP64: =DP47-DP49 -> 4785 | DQ64: =DQ47-DQ49 -> 6289 | DR64: =DR47-DR49 -> 6663 | DS64: =SUM(DO64:DR64) -> 21785 | DT64: =DT47-DT49 -> 6232 | DU64: =DU47-DU49 -> 5278 | DV64: =DV47-DV49 -> 4675 | DW64: =DW47-DW49 -> 6245 | DX64: =SUM(DT64:DW64) -> 22430 | DY64: =DY47-DY49 -> 5695 | DZ64: =DZ47-DZ49 -> 5214 | EA64: =EA47-EA49 -> 6997 | EB64: =EB47-EB49 -> 4451 | EC64: =SUM(DY64:EB64) -> 22357 | ED64: =ED47-ED49 -> 3586 | EE64: =EE47-EE49 -> 1181 | EF64: =EF47-EF49 -> 2432 | EG64: =EG47-EG49 -> 394 | EH64: =SUM(ED64:EG64) -> 7593 | EI64: =EI47-EI49 -> #ERROR! | EJ64: =EJ47-EJ49 -> #ERROR! | EK64: =EK47-EK49 -> #ERROR! | EL64: =EL47-EL49 -> #ERROR! | EM64: =SUM(EI64:EL64) -> #ERROR! | EN64: =EN47-EN49 -> #ERROR! | EO64: =EO47-EO49 -> #ERROR! | EP64: =EP47-EP49 -> #ERROR! | EQ64: =EQ47-EQ49 -> #ERROR! | ER64: =SUM(EN64:EQ64) -> #ERROR! | ES64: =ES47-ES49 -> #ERROR! | ET64: =ET47-ET49 -> #ERROR! | EU64: =EU47-EU49 -> #ERROR! | EV64: =EV47-EV49 -> #ERROR! | EW64: =SUM(ES64:EV64) -> #ERROR! | EX64: =EX47-EX49 -> #ERROR! | EY64: =EY47-EY49 -> #ERROR! | EZ64: =EZ47-EZ49 -> #ERROR! | FA64: =FA47-FA49 -> #ERROR! | FB64: =SUM(EX64:FA64) -> #ERROR! | FC64: =FC47-FC49 -> #ERROR! | FD64: =FD47-FD49 -> #ERROR! | FE64: =FE47-FE49 -> #ERROR! | FF64: =FF47-FF49 -> #ERROR! | FG64: =SUM(FC64:FF64) -> #ERROR!
B67: Basic EPS reported (GAAP) | N67: =proFormaNetInc/shOut -> 0.21907374 | O67: =proFormaNetInc/shOut -> 0.17327025 | P67: =proFormaNetInc/shOut -> 0.23465435 | Q67: =proFormaNetInc/shOut -> 0.31629585 | R67: =proFormaNetInc/shOut -> 0.94259592 | S67: =proFormaNetInc/shOut -> 0.30339952 | T67: =proFormaNetInc/shOut -> 0.26888218 | U67: =proFormaNetInc/shOut -> 0.28631579 | ... FG67: =proFormaNetInc/shOut -> #ERROR!
B68: Diluted EPS reported (GAAP) | N68: =GAAPNetInc/shOutDiluted -> 0.17934629 | O68: =GAAPNetInc/shOutDiluted -> 0.16567713 | P68: =GAAPNetInc/shOutDiluted -> 0.22239658 | Q68: =GAAPNetInc/shOutDiluted -> 0.29740634 | R68: =GAAPNetInc/shOutDiluted -> 0.86266705 | S68: =GAAPNetInc/shOutDiluted -> 0.2873778 | T68: =GAAPNetInc/shOutDiluted -> 0.25377249 | U68: =GAAPNetInc/shOutDiluted -> 0.20999568 | ... BA68: =GAAPNetInc/shOutDiluted -> 1.4023956 | BB68: =(GAAPNetInc+BB$69)/shOutDiluted -> 0.22791401 | BC68: =(GAAPNetInc+BC$69)/shOutDiluted -> 0.150818 | BD68: =(GAAPNetInc+BD$69)/shOutDiluted -> 0.22307956 | BE68: =(GAAPNetInc+BE$69)/shOutDiluted -> 0.25583774 | BF68: =(GAAPNetInc+BF$69)/shOutDiluted -> 0.85782313 | BG68: =(GAAPNetInc+BG$69)/shOutDiluted -> 0.27851549 | BH68: =(GAAPNetInc+BH$69)/shOutDiluted -> 0.21598783 | BI68: =(GAAPNetInc+BI$69)/shOutDiluted -> 0.30015083 | ... FG68: =(GAAPNetInc+FG$69)/shOutDiluted -> #ERROR!
B69: Convertible net addback for diluted EPS | X69: 7.079 | Y69: 6.207 | Z69: 6.41 | AA69: =AB69-SUM(X69:Z69) -> 7.811 | AB69: 27.507
B70: Non-GAAP Income Adjustments (1Q16+) | CZ70: =64+226+235+100-132 -> 493 | DA70: 29 | DB70: 62 | DC70: =232-70 -> 162 | DD70: =SUM(CZ70:DC70) -> 746 | DE70: =209-73 -> 136 | DF70: =198-387+745 -> 556 | DI70: =SUM(DE70:DH70) -> 692 | DN70: =SUM(DJ70:DM70) -> 0 | DS70: =SUM(DO70:DR70) -> 0 | DX70: =SUM(DT70:DW70) -> 0 | EC70: =SUM(DY70:EB70) -> 0 | EH70: =SUM(ED70:EG70) -> 0 | EM70: =SUM(EI70:EL70) -> 0 | ER70: =SUM(EN70:EQ70) -> 0 | EW70: =SUM(ES70:EV70) -> 0 | FB70: =SUM(EX70:FA70) -> 0 | FG70: =SUM(FC70:FF70) -> 0
B71: UBS adjusted diluted EPS | N71: =+N51/N78 -> 0.20259228 | O71: =+O51/O78 -> 0.16567713 | P71: =+P51/P78 -> 0.22467903 | Q71: =+Q51/Q78 -> 0.30317003 | R71: =proFormaNetInc/shOutDiluted -> 0.89408587 | S71: =proFormaNetInc/shOutDiluted -> 0.2899655 | T71: =proFormaNetInc/shOutDiluted -> 0.25827046 | U71: =proFormaNetInc/shOutDiluted -> 0.27423304 | V71: =proFormaNetInc/shOutDiluted -> 0.34553021 | W71: =proFormaNetInc/shOutDiluted -> 1.1684438 | X71: =proFormaNetInc/shOutDiluted -> 0.43431022 | Y71: =proFormaNetInc/shOutDiluted -> 0.50221271 | ... BA71: =proFormaNetInc/shOutDiluted -> 1.4584066 | BB71: =((proFormaNetInc+BB$69)/shOutDiluted) -> 0.22791401 | BC71: =((proFormaNetInc+BC$69)/shOutDiluted) -> 0.150818 | BD71: =((proFormaNetInc+BD$69)/shOutDiluted) -> 0.22307956 | BE71: =((proFormaNetInc+BE$69)/shOutDiluted) -> 0.25583774 | BF71: =((proFormaNetInc+BF$69)/shOutDiluted) -> 0.85782313 | BG71: =((proFormaNetInc+BG$69)/shOutDiluted) -> 0.22301668 | BH71: =((proFormaNetInc+BH$69)/shOutDiluted) -> 0.18539801 | BI71: =((proFormaNetInc+BI$69)/shOutDiluted) -> 0.31390246 | ... FG71: =((proFormaNetInc+FG$69)/shOutDiluted) -> #ERROR!
B72: Non-GAAP diluted EPS (As reported) | N72: =N71-N57/N78 -> 0.19156805 | O72: =O71-O57/O78 -> 0.15461549 | P72: =P71-P57/P78 -> 0.21351641 | Q72: =Q71-Q57/Q78 -> 0.29189481 | R72: =R71-R57/R78 -> 0.84958772 | S72: =S71-S57/S78 -> 0.27364865 | T72: =T71-T57/T78 -> 0.24180209 | U72: =U71-U57/U78 -> 0.25788564 | ... BA72: =BA71-BA57/BA78 -> 1.2541334 | BC72: =BC71 -> 0.150818 | BD72: =BD71 -> 0.22307956 | BE72: =BE71 -> 0.25583774 | BF72: =BF71 -> 0.85782313 | BG72: =BG71 -> 0.22301668 | BH72: =BH71 -> 0.18539801 | BI72: =BI71 -> 0.31390246 | BJ72: =BJ71 -> 0.37925852 | ... CO72: =CO71 -> 1.8872922 | CP72: =CP64/shOutDiluted -> 0.4059019 | CQ72: =CQ64/shOutDiluted -> 0.56744095 | CR72: =CR64/shOutDiluted -> 0.66442022 | CS72: =CS64/shOutDiluted -> 0.76315789 | CT72: =SUM(CP72:CS72) -> 2.400921 | CU72: =CU64/shOutDiluted -> 0.44892145 | CV72: =CV64/shOutDiluted -> 0.62232634 | CW72: =CW64/shOutDiluted -> 0.64171452 | CX72: =CX64/shOutDiluted -> 0.76271534 | CY72: =SUM(CU72:CX72) -> 2.4756776 | CZ72: =CZ64/shOutDiluted -> 0.53928205 | DA72: =DA64/shOutDiluted -> 0.58754624 | DB72: =DB64/shOutDiluted -> 0.79680131 | DC72: =DC64/shOutDiluted -> 0.79184593 | DD72: =SUM(CZ72:DC72) -> 2.7154755 | DE72: =DE64/shOutDiluted -> 0.65929113 | DF72: =DF64/shOutDiluted -> 0.72371981 | DG72: =DG64/shOutDiluted -> 1.0056005 | DH72: =DH64/shOutDiluted -> 1.0816284 | DI72: =DI64/shOutDiluted -> 3.4655681 | DJ72: =DJ64/shOutDiluted -> 0.87160752 | DK72: =DK64/shOutDiluted -> 1.0407384 | DL72: =DL64/shOutDiluted -> 1.4001721 | DM72: =DM64/shOutDiluted -> 1.2777657 | DN72: =DN64/DN78 -> 4.5788949 | DO72: =DO64/shOutDiluted -> 0.88694128 | DP72: =DP64/shOutDiluted -> 1.0579262 | DQ72: =DQ64/shOutDiluted -> 1.4186781 | DR72: =DR64/shOutDiluted -> 1.523668 | DS72: =DS64/shOutDiluted -> 4.8700609 | DT72: =DT64/shOutDiluted -> 1.445269 | DU72: =DU64/shOutDiluted -> 1.2320261 | DV72: =DV64/shOutDiluted -> 1.1101876 | ... FG72: =FG64/shOutDiluted -> #ERROR!
B73: Non -GAAP diluted EPS (Including SBC) | BB73: =BB71+BB57/(BB78-17) -> 0.27238091 | BC73: =BC71+BC57/(BC78+8) -> 0.19149192 | BD73: =BD71+BD57/BD78 -> 0.26560357 | BE73: =BE71+BE57/BE78 -> 0.29606272 | BF73: =BF71+BF57/BF78 -> 1.0256803 | BG73: =BG71+BG57/BG78 -> 0.25683235 | BH73: =BH71+BH57/BH78 -> 0.2141353 | BI73: =BI71+BI57/BI78 -> 0.34114094 | BJ73: =BJ71+BJ57/BJ78 -> 0.40298398 | BK73: =BK71+BK57/BK78 -> 1.2170364 | ... CO73: =CO71+CO57/CO78 -> 2.0593948 | CP73: =CP72 -> 0.4059019 | CQ73: =CQ72 -> 0.56744095 | CR73: =CR72 -> 0.66442022 | CS73: =CS72 -> 0.76315789 | CT73: =CT72 -> 2.400921 | CU73: =CU72 -> 0.44892145 | CV73: =CV72 -> 0.62232634 | CW73: =CW72 -> 0.64171452 | ... EE73: =EE72 -> 0.28804878 | EF73: =(EF47-EF88-EF49)/EF78 -> 0.39733333 | EG73: =(EG47-EG88-EG49)/EG78 -> -0.082748609 | EH73: =SUM(ED73:EG73) -> 1.4757769 | EI73: =(EI47-EI88-EI49)/EI78 -> #ERROR! | EJ73: =(EJ47-EJ88-EJ49)/EJ78 -> #ERROR! | EK73: =(EK47-EK88-EK49)/EK78 -> #ERROR! | EL73: =(EL47-EL88-EL49)/EL78 -> #ERROR! | EM73: =SUM(EI73:EL73) -> #ERROR! | EN73: =(EN47-EN88-EN49)/EN78 -> #ERROR! | EO73: =(EO47-EO88-EO49)/EO78 -> #ERROR! | EP73: =(EP47-EP88-EP49)/EP78 -> #ERROR! | EQ73: =(EQ47-EQ88-EQ49)/EQ78 -> #ERROR! | ER73: =SUM(EN73:EQ73) -> #ERROR! | ES73: =(ES47-ES88-ES49)/ES78 -> #ERROR! | ET73: =(ET47-ET88-ET49)/ET78 -> #ERROR! | EU73: =(EU47-EU88-EU49)/EU78 -> #ERROR! | EV73: =(EV47-EV88-EV49)/EV78 -> #ERROR! | EW73: =SUM(ES73:EV73) -> #ERROR! | EX73: =(EX47-EX88-EX49)/EX78 -> #ERROR! | EY73: =(EY47-EY88-EY49)/EY78 -> #ERROR! | EZ73: =(EZ47-EZ88-EZ49)/EZ78 -> #ERROR! | FA73: =(FA47-FA88-FA49)/FA78 -> #ERROR! | FB73: =SUM(EX73:FA73) -> #ERROR! | FC73: =(FC47-FC88-FC49)/FC78 -> #ERROR! | FD73: =(FD47-FD88-FD49)/FD78 -> #ERROR! | FE73: =(FE47-FE88-FE49)/FE78 -> #ERROR! | FF73: =(FF47-FF88-FF49)/FF78 -> #ERROR! | FG73: =SUM(FC73:FF73) -> #ERROR!
B74: Non -GAAP diluted EPS (excluding SBC) | BB74: =BB72+BB58/(BB79-17) -> 0 | BC74: =BC72+BC58/(BC79+8) -> 0.150818 | BD74: =BD72+BD58/BD79 -> #DIV/0! | BE74: =BE72+BE58/BE79 -> #DIV/0! | BF74: =BF72+BF58/BF79 -> #DIV/0! | BG74: =BG72+BG58/BG79 -> #DIV/0! | BH74: =BH72+BH58/BH79 -> #DIV/0! | BI74: =BI72+BI58/BI79 -> #DIV/0! | BJ74: =BJ72+BJ58/BJ79 -> #DIV/0! | BK74: =BK72+BK58/BK79 -> #DIV/0! | ... CO74: =CO72+CO58/CO79 -> #DIV/0! | CP74: =(CP47+CP88-CP49)/CP78 -> 0.46120774 | CQ74: =(CQ47+CQ88-CQ49)/CQ78 -> 0.62658598 | CR74: =(CR47+CR88-CR49)/CR78 -> 0.72011893 | CS74: =(CS47+CS88-CS49)/CS78 -> 0.82004049 | CT74: =SUM(CP74:CS74) -> 2.6279531 | CU74: =(CU47+CU88-CU49)/CU78 -> 0.52380952 | CV74: =(CV47+CV88-CV49)/CV78 -> 0.68995722 | CW74: =(CW47+CW88-CW49)/CW78 -> 0.70508614 | CX74: =(CX47+CX88-CX49)/CX78 -> 0.82342084 | CY74: =SUM(CU74:CX74) -> 2.7422737 | CZ74: =(CZ47+CZ88-CZ49)/CZ78 -> 0.63117949 | DA74: =(DA47+DA88-DA49)/DA78 -> 0.66235101 | DB74: =(DB47+DB88-DB49)/DB78 -> 0.8632356 | DC74: =(DC47+DC88-DC49)/DC78 -> 0.85494776 | DD74: =SUM(CZ74:DC74) -> 3.0117138 | DE74: =(DE47+DE88-DE49)/DE78 -> 0.74062692 | DF74: =(DF47+DF88-DF49)/DF78 -> 0.79141847 | DG74: =(DG47+DG88-DG49)/DG78 -> 1.0732213 | DH74: =(DH47+DH88-DH49)/DH78 -> 1.1457203 | DI74: =SUM(DE74:DH74) -> 3.750987 | DJ74: =(DJ47+DJ88-DJ49)/DJ78 -> 0.96200418 | DK74: =(DK47+DK88-DK49)/DK78 -> 1.1222635 | DL74: =(DL47+DL88-DL49)/DL78 -> 1.4825731 | DM74: =(DM47+DM88-DM49)/DM78 -> 1.3520242 | DN74: =SUM(DJ74:DM74) -> 4.9188651 | DO74: =(DO47+DO88-DO49)/DO78 -> 0.97217353 | DP74: =(DP47+DP88-DP49)/DP78 -> 1.1618395 | DQ74: =(DQ47+DQ88-DQ49)/DQ78 -> 1.5159035 | DR74: =(DR47+DR88-DR49)/DR78 -> 1.6484434 | DS74: =SUM(DO74:DR74) -> 5.2983599 | DT74: =(DT47+DT88-DT49)/DT78 -> 1.549397 | DU74: =(DU47+DU88-DU49)/DU78 -> 1.3468721 | DV74: =(DV47+DV88-DV49)/DV78 -> 1.2175255 | DW74: =(DW47+DW88-DW49)/DW78 -> 1.6280651 | DX74: =SUM(DT74:DW74) -> 5.7418597 | DY74: =(DY47+DY88-DY49)/DY78 -> 1.4941406 | DZ74: should be 3.58 | EA74: =(EA47+EA88-EA49)/EA78 -> 1.8453255 | EB74: =(EB47+EB88-EB49)/EB78 -> 1.1965812 | EC74: =SUM(DY74:EB74) -> 4.5360473 | ED74: =(ED47+ED88-ED49)/ED78 -> 1.0452885 | EE74: =(EE47+EE88-EE49)/EE78 -> 0.50560976 | EF74: =EF72 -> 0.58957576 | EG74: =EG72 -> 0.095330269 | EH74: =SUM(ED74:EG74) -> 2.2358043 | EI74: =EI72 -> #ERROR! | EJ74: =EJ72 -> #ERROR! | EK74: =EK72 -> #ERROR! | EL74: =EL72 -> #ERROR! | EM74: =SUM(EI74:EL74) -> #ERROR! | EN74: =EN72 -> #ERROR! | EO74: =EO72 -> #ERROR! | EP74: =EP72 -> #ERROR! | EQ74: =EQ72 -> #ERROR! | ER74: =SUM(EN74:EQ74) -> #ERROR! | ES74: =ES72 -> #ERROR! | ET74: =ET72 -> #ERROR! | EU74: =EU72 -> #ERROR! | EV74: =EV72 -> #ERROR! | EW74: =SUM(ES74:EV74) -> #ERROR! | EX74: =EX72 -> #ERROR! | EY74: =EY72 -> #ERROR! | EZ74: =EZ72 -> #ERROR! | FA74: =FA72 -> #ERROR! | FB74: =SUM(EX74:FA74) -> #ERROR! | FC74: =FC72 -> #ERROR! | FD74: =FD72 -> #ERROR! | FE74: =FE72 -> #ERROR! | FF74: =FF72 -> #ERROR! | FG74: =SUM(FC74:FF74) -> #ERROR!
B75: Dividend Per Share | N75: 0.0074649604 | O75: 0.0075399172 | P75: 0.0074493445 | Q75: 0.010072159 | R75: 0.032523981 | S75: 0.010078219 | T75: 0.01510574 | U75: 0.014887218 | V75: 0.014985764 | W75: 0.055054152 | X75: 0.01496334 | Y75: 0.01490313 | Z75: 0.020092276 | AA75: 0.020080321 | AB75: 0.07005515 | AC75: 0.019937509 | AD75: 0.020074349 | AE75: 0.020095266 | AF75: 0.020005972 | AG75: 0.080107207 | AH75: 0.020047876 | AI75: 0.020068893 | AJ75: 0.020012037 | AK75: 0.020006062 | AL75: 0.080138325 | AM75: 0.019981696 | AN75: 0.020076628 | AO75: 0.020101274 | AP75: 0.020116708 | AQ75: 0.080281906 | AR75: 0.039969136 | AS75: 0.040006203 | AT75: 0.039686275 | AU75: 0.040038132 | AV75: 0.1596875 | AW75: 0.080019321 | AX75: 0.080240885 | AY75: 0.080171561 | AZ75: 0.080226365 | BA75: 0.3206682 | BB75: 0.099931671 | BC75: 0.10032753 | BD75: 0.10001733 | BE75: 0.099930604 | BF75: 0.400207 | BG75: 0.11251515 | BH75: 0.11223963 | BI75: 0.11255782 | BJ75: 0.11282315 | BK75: 0.45013755 | BL75: 0.12770002 | BM75: 0.1403755 | BN75: 0.13974656 | BO75: 0.13987774 | BP75: 0.54741303 | BQ75: 0.13978109 | BR75: 0.14012511 | BS75: 0.13924508 | BT75: 0.14016661 | BU75: 0.55929458 | BV75: 0.15735214 | BW75: 0.15764875 | BX75: 0.15730942 | BY75: 0.15826431 | BZ75: 0.63060306 | CA75: 0.18231842 | CB75: 0.18152626 | CC75: 0.21116789 | CD75: 0.211087 | CE75: 0.78519787 | CF75: 0.20984197 | CG75: 0.21047391 | CH75: 0.22518014 | CI75: 0.22524155 | CJ75: 0.87069656 | CK75: 0.22514147 | CL75: 0.22559261 | CM75: 0.22505521 | CN75: 0.22550795 | CO75: 0.90129792 | CP75: 0.22496984 | CQ75: 0.22605902 | CR75: 0.22438525 | CS75: 0.22415601 | CT75: 0.89961232 | CU75: 0.23982282 | CV75: 0.24080689 | CW75: 0.24015167 | CX75: 0.2399407 | CY75: 0.96072539 | CZ75: 0.2600593 | DA75: 0.26073166 | DB75: 0.2600338 | DC75: 0.26040127 | DD75: 1.0412262 | DE75: 0.26021596 | DF75: 0.27324841 | DG75: 0.27261092 | DH75: 0.27290199 | DI75: 1.0789194 | DJ75: =CF!DJ78 -> 0.3 | DK75: =CF!DK78 -> 0.3 | DL75: =CF!DL78 -> 0.3 | DM75: =CF!DM78 -> 0.3 | DN75: =CF!DN78 -> 1.2 | DO75: =CF!DO78 -> 0.315 | DP75: =CF!DP78 -> 0.315 | DQ75: =CF!DQ78 -> 0.315 | ... FG75: =CF!FG78 -> 2.4
B77: Basic shares outstanding | I77: 6552 | J77: 6540 | K77: 6540 | L77: 6532 | M77: =2*3271 -> 6542 | N77: 6564 | O77: 6764 | P77: 6712 | Q77: 6652 | R77: =2*3336 -> 6672 | S77: 6648 | T77: 6620 | U77: 6650 | V77: 6673 | W77: 6648 | X77: 6683 | Y77: 6710 | Z77: 6719 | AA77: 6723 | AB77: 6709 | AC77: 6721 | AD77: 6725 | AE77: 6718 | AF77: 6698 | AG77: 6716 | AH77: 6684 | AI77: 6677 | AJ77: 6646 | AK77: 6598 | AL77: 6651 | AM77: 6556 | AN77: 6525 | AO77: 6517 | AP77: 6512 | AQ77: 6527 | AR77: 6480 | AS77: 6449 | AT77: 6375 | AU77: 6294 | AV77: 6400 | AW77: 6211 | AX77: 6144 | AY77: 6062 | AZ77: 6008 | BA77: 6106 | BB77: 5854 | BC77: 5801 | BD77: 5769 | BE77: 5764 | BF77: 5797 | BG77: 5777 | BH77: 5809 | BI77: 5837 | BJ77: 5841 | BK77: 5816 | BL77: 5787 | BM77: 5699 | BN77: 5603 | BO77: 5562 | BP77: 5663 | BQ77: 5573 | BR77: 5595 | BS77: 5537 | BT77: 5522 | BU77: 5557 | BV77: 5529 | BW77: 5563 | BX77: 5575 | BY77: 5554 | BZ77: 5555 | CA77: 5452 | CB77: 5294 | CC77: 5194 | CD77: 5069 | CE77: 5256 | CF77: 4999 | CG77: 5022 | CH77: 4996 | CI77: 4968 | CJ77: 4996 | CK77: 4948 | CL77: 4978 | CM77: 4981 | CN77: 4971 | CO77: =+AVERAGE(CK77:CN77) -> 4969.5 | CP77: 4974 | CQ77: 4981 | CR77: 4880 | CS77: 4769 | CT77: 4901 | CU77: 4741 | CV77: 4759 | CW77: 4747 | CX77: 4722 | CY77: =+AVERAGE(CU77:CX77) -> 4742.25 | CZ77: 4722 | DA77: 4729 | DB77: 4734 | DC77: 4735 | DD77: =+AVERAGE(CZ77:DC77) -> 4730 | DE77: 4723 | DF77: 4710 | DG77: 4688 | DH77: 4683 | DI77: =+AVERAGE(DE77:DH77) -> 4701 | DJ77: 4674 | DK77: 4649 | DL77: 4574 | DM77: 4549 | DN77: 4611 | DO77: 4492 | DP77: 4466 | DQ77: 4391 | DR77: 4319 | DS77: =+AVERAGE(DO77:DR77) -> 4417 | DT77: 4266 | DU77: 4246 | DV77: 4188 | DW77: 4094 | DX77: =+AVERAGE(DT77:DW77) -> 4198.5 | DY77: 4056 | DZ77: 4049 | EA77: 4061 | EB77: 4069 | EC77: =+AVERAGE(DY77:EB77) -> 4058.75 | ED77: 4079 | EE77: 4100 | EF77: 4118 | EG77: 4133 | EH77: =+AVERAGE(ED77:EG77) -> 4107.5 | EI77: =EG77*1.001+CF!EI77 -> 4137.133 | EJ77: =EI77*1.001+CF!EJ77 -> 4141.2701 | EK77: =EJ77*1.001+CF!EK77 -> 4145.4114 | EL77: =EK77+CF!EL77 -> 4145.4114 | EM77: =+AVERAGE(EI77:EL77) -> 4142.3065 | EN77: =EL77*1.001+CF!EN77 -> 4132.8901 | EO77: =EN77*1.001+CF!EO77 -> 4120.3564 | EP77: =EO77*1.001+CF!EP77 -> 4107.8101 | EQ77: =EP77+CF!EQ77 -> 4091.1434 | ER77: =+AVERAGE(EN77:EQ77) -> 4113.05 | ES77: =EQ77*1.001+CF!ES77 -> 4080.9488 | ET77: =ES77*1.001+CF!ET77 -> 4070.7441 | EU77: =ET77*1.001+CF!EU77 -> 4060.5291 | EV77: =EU77+CF!EV77 -> 4046.2434 | EW77: =+AVERAGE(ES77:EV77) -> 4064.6163 | EX77: =EV77*1.001+CF!EX77 -> 4037.7896 | EY77: =EX77*1.001+CF!EY77 -> 4029.3274 | EZ77: =EY77*1.001+CF!EZ77 -> 4020.8567 | FA77: =EZ77+CF!FA77 -> 4008.3567 | FB77: =+AVERAGE(EX77:FA77) -> 4024.0826 | FC77: =FA77*1.001+CF!FC77 -> 3987.3651 | FD77: =FC77*1.001+CF!FD77 -> 3966.3525 | FE77: =FD77*1.001+CF!FE77 -> 3945.3188 | FF77: =FE77+CF!FF77 -> 3920.3188 | FG77: =+AVERAGE(FC77:FF77) -> 3954.8388
B78: Diluted shares outstanding | I78: 7200 | J78: 7188 | K78: 7188 | L78: 7140 | M78: =2*3590 -> 7180 | N78: 7098 | O78: 7074 | P78: 7010 | Q78: 6940 | R78: 7034 | S78: 6956 | T78: 6892 | U78: 6943 | V78: 6969 | W78: 6940 | X78: 6995 | Y78: 7005 | Z78: 7007 | AA78: 6938 | AB78: 6986 | AC78: 6899 | AD78: 6889 | AE78: 6876 | AF78: 6851 | AG78: 6879 | AH78: 6861 | AI78: 6803 | AJ78: 6712 | AK78: 6660 | AL78: 6759 | AM78: 6610 | AN78: 6580 | AO78: 6625 | AP78: 6671 | AQ78: 6621 | AR78: 6624 | AS78: 6558 | AT78: 6442 | AU78: 6352 | AV78: 6494 | AW78: 6273 | AX78: 6215 | AY78: 6144 | AZ78: 6081 | BA78: 6178 | BB78: 5954 | BC78: 5868 | BD78: 5832 | BE78: 5867 | BF78: 5880 | BG78: 5874 | BH78: 5917 | BI78: 5967 | BJ78: 5988 | BK78: 5936 | BL78: 5879 | BM78: 5800 | BN78: 5692 | BO78: 5623 | BP78: 5748 | BQ78: 5634 | BR78: 5678 | BS78: 5616 | BT78: 5650 | BU78: 5645 | BV78: 5681 | BW78: 5711 | BX78: 5694 | BY78: 5698 | BZ78: 5696 | CA78: 5606 | CB78: 5441 | CC78: 5340 | CD78: 5242 | CE78: 5411 | CF78: 5192 | CG78: 5199 | CH78: 5153 | CI78: 5095 | CJ78: 5160 | CK78: 5080 | CL78: 5106 | CM78: 5100 | CN78: 5103 | CO78: =+AVERAGE(CK78:CN78) -> 5097.25 | CP78: 5117 | CQ78: 5123 | CR78: 5045 | CS78: 4940 | CT78: 5056 | CU78: 4914 | CV78: 4909 | CW78: 4876 | CX78: 4876 | CY78: =+AVERAGE(CU78:CX78) -> 4893.75 | CZ78: 4875 | DA78: 4866 | DB78: 4877 | DC78: 4881 | DD78: =+AVERAGE(CZ78:DC78) -> 4874.75 | DE78: 4881 | DF78: 4845 | DG78: 4821 | DH78: 4790 | DI78: =+AVERAGE(DE78:DH78) -> 4834.25 | DJ78: 4790 | DK78: 4747 | DL78: 4648 | DM78: 4619 | DN78: =+AVERAGE(DJ78:DM78) -> 4701 | DO78: =DO77+53+19 -> 4564 | DP78: 4523 | DQ78: 4433 | DR78: 4373 | DS78: =+AVERAGE(DO78:DR78) -> 4473.25 | DT78: 4312 | DU78: 4284 | DV78: 4211 | DW78: 4119 | DX78: =+AVERAGE(DT78:DW78) -> 4231.5 | DY78: 4096 | DZ78: 4084 | EA78: 4086 | EB78: 4095 | EC78: =+AVERAGE(DY78:EB78) -> 4090.25 | ED78: 4107 | EE78: 4100 | EF78: 4125 | EG78: 4133 | EH78: =+AVERAGE(ED78:EG78) -> 4116.25 | EI78: =EG78*1.001+CF!EI77 -> 4137.133 | EJ78: =EI78*1.001+CF!EJ77 -> 4141.2701 | EK78: =EJ78*1.001+CF!EK77 -> 4145.4114 | EL78: =EK78*1.001+CF!EL77 -> 4149.5568 | EM78: =+AVERAGE(EI78:EL78) -> 4143.3428 | EN78: =EL78*1.001+CF!EN77 -> 4137.0397 | EO78: =EN78*1.001+CF!EO77 -> 4124.5101 | EP78: =EO78*1.001+CF!EP77 -> 4111.9679 | EQ78: =EP78*1.001+CF!EQ77 -> 4099.4132 | ER78: =+AVERAGE(EN78:EQ78) -> 4118.2327 | ES78: =EQ78*1.001+CF!ES77 -> 4089.2269 | ET78: =ES78*1.001+CF!ET77 -> 4079.0304 | EU78: =ET78*1.001+CF!EU77 -> 4068.8238 | EV78: =EU78*1.001+CF!EV77 -> 4058.6069 | EW78: =+AVERAGE(ES78:EV78) -> 4073.922 | EX78: =EV78*1.001+CF!EX77 -> 4050.1655 | EY78: =EX78*1.001+CF!EY77 -> 4041.7156 | EZ78: =EY78*1.001+CF!EZ77 -> 4033.2573 | FA78: =EZ78*1.001+CF!FA77 -> 4024.7906 | FB78: =+AVERAGE(EX78:FA78) -> 4037.4823 | FC78: =FA78*1.001+CF!FC77 -> 4003.8154 | FD78: =FC78*1.001+CF!FD77 -> 3982.8192 | FE78: =FD78*1.001+CF!FE77 -> 3961.802 | FF78: =FE78*1.001+CF!FF77 -> 3940.7638 | FG78: =+AVERAGE(FC78:FF78) -> 3972.3001
B79: Diluted shares from convertible debt | DT79: =DT78/DR78-1 -> -0.013949234 | DU79: =DU78/DT78-1 -> -0.0064935065 | DV79: =DV78/DU78-1 -> -0.017040149 | DW79: =DW78/DV78-1 -> -0.021847542 | DX79: =AVERAGE(DT79:DW79) -> -0.014832608 | DY79: =DY78/DW78-1 -> -0.0055838796 | DZ79: =DZ78/DY78-1 -> -0.0029296875 | EA79: =EA78/DZ78-1 -> 0.00048971596 | EB79: =EB78/EA78-1 -> 0.0022026432 | EC79: =AVERAGE(DY79:EB79) -> -0.001455302 | ED79: =ED78/EB78-1 -> 0.0029304029 | EE79: =EE78/ED78-1 -> -0.0017044071 | EF79: =EF78/EE78-1 -> 0.006097561 | EG79: =EG78/EF78-1 -> 0.0019393939
B82: EBIT | CP82: =CP41 -> 2730 | CQ82: =CQ41 -> 3997 | CR82: =CR41 -> 4637 | CS82: =CS41 -> 4582 | CT82: =SUM(CP82:CS82) -> 15946 | CU82: =CU41 -> 2902 | CV82: =CV41 -> 3287 | CW82: =CW41 -> 4274 | CX82: =CX41 -> 4425 | CY82: =SUM(CU82:CX82) -> 14888 | CZ82: =CZ41 -> 3283 | DA82: =DA41 -> 3217 | DB82: =DB41 -> 5143 | DC82: =DC41 -> 4899 | DD82: =SUM(CZ82:DC82) -> 16542 | DE82: =DE41 -> 3926 | DF82: =DF41 -> 4167 | DG82: =DG41 -> 5551 | DH82: =DH41 -> 5933 | DI82: =SUM(DE82:DH82) -> 19577 | DJ82: =DJ41 -> 4795 | DK82: =DK41 -> 5339 | DL82: =DL41 -> 7603 | DM82: =DM41 -> 6553 | DN82: =SUM(DJ82:DM82) -> 24290 | DO82: =DO41 -> 4505 | DP82: =DP41 -> 5138 | DQ82: =DQ41 -> 6889 | DR82: =DR41 -> 7220 | DS82: =SUM(DO82:DR82) -> 23752 | DT82: =DT41 -> 7539 | DU82: =DU41 -> 6058 | DV82: =DV41 -> 5396 | DW82: =DW41 -> 6299 | DX82: =SUM(DT82:DW82) -> 25292 | DY82: =DY41 -> 6096 | DZ82: =DZ41 -> 5856 | EA82: =EA41 -> 5202 | EB82: =EB41 -> 5051 | EC82: =SUM(DY82:EB82) -> 22205 | ED82: =ED41 -> 4241 | EE82: =EE41 -> 1417 | EF82: =EF41 -> 1655 | EG82: =EG41 -> 602 | EH82: =SUM(ED82:EG82) -> 7915 | EI82: =EI41 -> #ERROR! | EJ82: =EJ41 -> #ERROR! | EK82: =EK41 -> #ERROR! | EL82: =EL41 -> #ERROR! | EM82: =SUM(EI82:EL82) -> #ERROR! | EN82: =EN41 -> #ERROR! | EO82: =EO41 -> #ERROR! | EP82: =EP41 -> #ERROR! | EQ82: =EQ41 -> #ERROR! | ER82: =SUM(EN82:EQ82) -> #ERROR! | ES82: =ES41 -> #ERROR! | ET82: =ET41 -> #ERROR! | EU82: =EU41 -> #ERROR! | EV82: =EV41 -> #ERROR! | EW82: =SUM(ES82:EV82) -> #ERROR! | EX82: =EX41 -> #ERROR! | EY82: =EY41 -> #ERROR! | EZ82: =EZ41 -> #ERROR! | FA82: =FA41 -> #ERROR! | FB82: =SUM(EX82:FA82) -> #ERROR! | FC82: =FC41 -> #ERROR! | FD82: =FD41 -> #ERROR! | FE82: =FE41 -> #ERROR! | FF82: =FF41 -> #ERROR! | FG82: =SUM(FC82:FF82) -> #ERROR!
B83: Add: Depreciation | CP83: =CF!CP10 -> 1720 | CQ83: =CF!CQ10 -> 1880 | CR83: =CF!CR10 -> 1891 | CS83: =CF!CS10 -> 1889 | CT83: =SUM(CP83:CS83) -> 7380 | CU83: =CF!CU10 -> 1848 | CV83: =CF!CV10 -> 1977 | CW83: =CF!CW10 -> 2060 | CX83: =CF!CX10 -> 1936 | CY83: =SUM(CU83:CX83) -> 7821 | CZ83: =CF!CZ10 -> 1619 | DA83: =CF!DA10 -> 1522 | DB83: =CF!DB10 -> 1543 | DC83: =CF!DC10 -> 1582 | DD83: =SUM(CZ83:DC83) -> 6266 | DE83: =CF!DE10 -> 1625 | DF83: =CF!DF10 -> 1675 | DG83: =CF!DG10 -> 1690 | DH83: =CF!DH10 -> 1762 | DI83: =SUM(DE83:DH83) -> 6752 | DJ83: =CF!DJ10 -> 1806 | DK83: =CF!DK10 -> 1730 | DL83: =CF!DL10 -> 1884 | DM83: =CF!DM10 -> 2100 | DN83: =SUM(DJ83:DM83) -> 7520 | DO83: =CF!DO10 -> 2229 | DP83: =CF!DP10 -> 2150 | DQ83: =CF!DQ10 -> 2268 | DR83: =CF!DR10 -> 2557 | DS83: =SUM(DO83:DR83) -> 9204 | DT83: =CF!DT10 -> 2623 | DU83: =CF!DU10 -> 2625 | DV83: =CF!DV10 -> 2677 | DW83: =CF!DW10 -> 2557 | DX83: =SUM(DT83:DW83) -> 10482 | DY83: =CF!DY10 -> 2454 | DZ83: =CF!DZ10 -> 2408 | EA83: =CF!EA10 -> 2495 | EB83: =CF!EB10 -> 2596 | EC83: =SUM(DY83:EB83) -> 9953 | ED83: =CF!ED10 -> 2847 | EE83: =CF!EE10 -> 2681 | EF83: =CF!EF10 -> 2781 | EG83: =CF!EG10 -> 2819 | EH83: =SUM(ED83:EG83) -> 11128 | EI83: =CF!EI10 -> 2855.9844 | EJ83: =CF!EJ10 -> 2891.813 | EK83: =CF!EK10 -> 2926.3657 | EL83: =CF!EL10 -> 2959.8387 | EM83: =SUM(EI83:EL83) -> 11634.002 | EN83: =CF!EN10 -> 2977.1093 | EO83: =CF!EO10 -> 3021.184 | EP83: =CF!EP10 -> 3091.2252 | EQ83: =CF!EQ10 -> 3159.0775 | ER83: =SUM(EN83:EQ83) -> 12248.596 | ES83: =CF!ES10 -> 3224.8094 | ET83: =CF!ET10 -> 3288.4873 | EU83: =CF!EU10 -> 3350.1752 | EV83: =CF!EV10 -> 3409.9353 | EW83: =SUM(ES83:EV83) -> 13273.407 | EX83: =CF!EX10 -> 3467.828 | EY83: =CF!EY10 -> 3523.9115 | EZ83: =CF!EZ10 -> 3591.9142 | FA83: =CF!FA10 -> 3657.7919 | FB83: =SUM(EX83:FA83) -> 14241.446 | FC83: =CF!FC10 -> 3707.939 | FD83: =CF!FD10 -> 3756.5191 | FE83: =CF!FE10 -> 3817.2529 | FF83: =CF!FF10 -> 3876.0887 | FG83: =SUM(FC83:FF83) -> 15157.8
B84: Add: Amortization | CP84: =CF!CP11 -> 287 | CQ84: =CF!CQ11 -> 290 | CR84: =CF!CR11 -> 307 | CS84: =CF!CS11 -> 285 | CT84: =SUM(CP84:CS84) -> 1169 | CU84: =CF!CU11 -> 251 | CV84: =CF!CV11 -> 214 | CW84: =CF!CW11 -> 215 | CX84: =CF!CX11 -> 210 | CY84: =SUM(CU84:CX84) -> 890 | CZ84: =CF!CZ11 -> 396 | DA84: =CF!DA11 -> 395 | DB84: =CF!DB11 -> 385 | DC84: =CF!DC11 -> 348 | DD84: =SUM(CZ84:DC84) -> 1524 | DE84: =CF!DE11 -> 321 | DF84: =CF!DF11 -> 313 | DG84: =CF!DG11 -> 365 | DH84: =CF!DH11 -> 378 | DI84: =SUM(DE84:DH84) -> 1377 | DJ84: =CF!DJ11 -> 390 | DK84: =CF!DK11 -> 392 | DL84: =CF!DL11 -> 390 | DM84: =CF!DM11 -> 393 | DN84: =SUM(DJ84:DM84) -> 1565 | DO84: =CF!DO11 -> 396 | DP84: =CF!DP11 -> 404 | DQ84: =CF!DQ11 -> 411 | DR84: =CF!DR11 -> 411 | DS84: =SUM(DO84:DR84) -> 1622 | DT84: =CF!DT11 -> 427 | DU84: =CF!DU11 -> 438 | DV84: =CF!DV11 -> 446 | DW84: =CF!DW11 -> 446 | DX84: =SUM(DT84:DW84) -> 1757 | DY84: =CF!DY11 -> 448 | DZ84: =CF!DZ11 -> 449 | EA84: =CF!EA11 -> 464 | EB84: =CF!EB11 -> 478 | EC84: =SUM(DY84:EB84) -> 1839 | ED84: =CF!ED11 -> 501 | EE84: =CF!EE11 -> 467 | EF84: =CF!EF11 -> 471 | EG84: =CF!EG11 -> 468 | EH84: =SUM(ED84:EG84) -> 1907 | EI84: =CF!EI11 -> 476.75 | EJ84: =CF!EJ11 -> 470.6875 | EK84: =CF!EK11 -> 471.60938 | EL84: =CF!EL11 -> 471.76172 | EM84: =SUM(EI84:EL84) -> 1890.8086 | EN84: =CF!EN11 -> 472.70215 | EO84: =CF!EO11 -> 471.69019 | EP84: =CF!EP11 -> 471.94086 | EQ84: =CF!EQ11 -> 472.02373 | ER84: =SUM(EN84:EQ84) -> 1888.3569 | ES84: =CF!ES11 -> 472.08923 | ET84: =CF!ET11 -> 471.936 | EU84: =CF!EU11 -> 471.99745 | EV84: =CF!EV11 -> 472.0116 | EW84: =SUM(ES84:EV84) -> 1888.0343 | EX84: =CF!EX11 -> 472.00857 | EY84: =CF!EY11 -> 471.98841 | EZ84: =CF!EZ11 -> 472.00151 | FA84: =CF!FA11 -> 472.00252 | FB84: =SUM(EX84:FA84) -> 1888.001 | FC84: =CF!FC11 -> 472.00025 | FD84: =CF!FD11 -> 471.99817 | FE84: =CF!FE11 -> 472.00061 | FF84: =CF!FF11 -> 472.00039 | FG84: =SUM(FC84:FF84) -> 1887.9994
B85: Add: Non Cash Stock Comp. Expense | CP85: =CF!CP13 -> 283 | CQ85: =CF!CQ13 -> 303 | CR85: =CF!CR13 -> 281 | CS85: =CF!CS13 -> 281 | CT85: =SUM(CP85:CS85) -> 1148 | CU85: =CF!CU13 -> 368 | CV85: =CF!CV13 -> 332 | CW85: =CF!CW13 -> 309 | CX85: =CF!CX13 -> 296 | CY85: =SUM(CU85:CX85) -> 1305 | CZ85: =CF!CZ13 -> 448 | DA85: =CF!DA13 -> 364 | DB85: =CF!DB13 -> 324 | DC85: =CF!DC13 -> 308 | DD85: =SUM(CZ85:DC85) -> 1444 | DE85: =CF!DE13 -> 397 | DF85: =CF!DF13 -> 328 | DG85: =CF!DG13 -> 326 | DH85: =CF!DH13 -> 307 | DI85: =SUM(DE85:DH85) -> 1358 | DJ85: =CF!DJ13 -> 433 | DK85: =CF!DK13 -> 387 | DL85: =CF!DL13 -> 383 | DM85: =CF!DM13 -> 343 | DN85: =SUM(DJ85:DM85) -> 1546 | DO85: =CF!DO13 -> 389 | DP85: =CF!DP13 -> 470 | DQ85: =CF!DQ13 -> 431 | DR85: =CF!DR13 -> 415 | DS85: =SUM(DO85:DR85) -> 1705 | DT85: =CF!DT13 -> 449 | DU85: =CF!DU13 -> 492 | DV85: =CF!DV13 -> 452 | DW85: =CF!DW13 -> 461 | DX85: =SUM(DT85:DW85) -> 1854 | DY85: =CF!DY13 -> 425 | DZ85: =CF!DZ13 -> 619 | EA85: =CF!EA13 -> 543 | EB85: =CF!EB13 -> 449 | EC85: =SUM(DY85:EB85) -> 2036 | ED85: =CF!ED13 -> 707 | EE85: =CF!EE13 -> 892 | EF85: =CF!EF13 -> 793 | EG85: =CF!EG13 -> 736 | EH85: =SUM(ED85:EG85) -> 3128 | EI85: =CF!EI13 -> #ERROR! | EJ85: =CF!EJ13 -> #ERROR! | EK85: =CF!EK13 -> #ERROR! | EL85: =CF!EL13 -> #ERROR! | EM85: =SUM(EI85:EL85) -> #ERROR! | EN85: =CF!EN13 -> #ERROR! | EO85: =CF!EO13 -> #ERROR! | EP85: =CF!EP13 -> #ERROR! | EQ85: =CF!EQ13 -> #ERROR! | ER85: =SUM(EN85:EQ85) -> #ERROR! | ES85: =CF!ES13 -> #ERROR! | ET85: =CF!ET13 -> #ERROR! | EU85: =CF!EU13 -> #ERROR! | EV85: =CF!EV13 -> #ERROR! | EW85: =SUM(ES85:EV85) -> #ERROR! | EX85: =CF!EX13 -> #ERROR! | EY85: =CF!EY13 -> #ERROR! | EZ85: =CF!EZ13 -> #ERROR! | FA85: =CF!FA13 -> #ERROR! | FB85: =SUM(EX85:FA85) -> #ERROR! | FC85: =CF!FC13 -> #ERROR! | FD85: =CF!FD13 -> #ERROR! | FE85: =CF!FE13 -> #ERROR! | FF85: =CF!FF13 -> #ERROR! | FG85: =SUM(FC85:FF85) -> #ERROR!
B86: Adjusted EBITDA | CP86: =SUM(CP82:CP85) -> 5020 | CQ86: =SUM(CQ82:CQ85) -> 6470 | CR86: =SUM(CR82:CR85) -> 7116 | CS86: =SUM(CS82:CS85) -> 7037 | CT86: =SUM(CP86:CS86) -> 25643 | CU86: =SUM(CU82:CU85) -> 5369 | CV86: =SUM(CV82:CV85) -> 5810 | CW86: =SUM(CW82:CW85) -> 6858 | CX86: =SUM(CX82:CX85) -> 6867 | CY86: =SUM(CU86:CX86) -> 24904 | CZ86: =SUM(CZ82:CZ85) -> 5746 | DA86: =SUM(DA82:DA85) -> 5498 | DB86: =SUM(DB82:DB85) -> 7395 | DC86: =SUM(DC82:DC85) -> 7137 | DD86: =SUM(CZ86:DC86) -> 25776 | DE86: =SUM(DE82:DE85) -> 6269 | DF86: =SUM(DF82:DF85) -> 6483 | DG86: =SUM(DG82:DG85) -> 7932 | DH86: =SUM(DH82:DH85) -> 8380 | DI86: =SUM(DE86:DH86) -> 29064 | DJ86: =SUM(DJ82:DJ85) -> 7424 | DK86: =SUM(DK82:DK85) -> 7848 | DL86: =SUM(DL82:DL85) -> 10260 | DM86: =SUM(DM82:DM85) -> 9389 | DN86: =SUM(DJ86:DM86) -> 34921 | DO86: =SUM(DO82:DO85) -> 7519 | DP86: =SUM(DP82:DP85) -> 8162 | DQ86: =SUM(DQ82:DQ85) -> 9999 | DR86: =SUM(DR82:DR85) -> 10603 | DS86: =SUM(DO86:DR86) -> 36283 | DT86: =SUM(DT82:DT85) -> 11038 | DU86: =SUM(DU82:DU85) -> 9613 | DV86: =SUM(DV82:DV85) -> 8971 | DW86: =SUM(DW82:DW85) -> 9763 | DX86: =SUM(DT86:DW86) -> 39385 | DY86: =SUM(DY82:DY85) -> 9423 | DZ86: =SUM(DZ82:DZ85) -> 9332 | EA86: =SUM(EA82:EA85) -> 8704 | EB86: =SUM(EB82:EB85) -> 8574 | EC86: =SUM(DY86:EB86) -> 36033 | ED86: =SUM(ED82:ED85) -> 8296 | EE86: =SUM(EE82:EE85) -> 5457 | EF86: =SUM(EF82:EF85) -> 5700 | EG86: =SUM(EG82:EG85) -> 4625 | EH86: =SUM(ED86:EG86) -> 24078 | EI86: =SUM(EI82:EI85) -> #ERROR! | EJ86: =SUM(EJ82:EJ85) -> #ERROR! | EK86: =SUM(EK82:EK85) -> #ERROR! | EL86: =SUM(EL82:EL85) -> #ERROR! | EM86: =SUM(EI86:EL86) -> #ERROR! | EN86: =SUM(EN82:EN85) -> #ERROR! | EO86: =SUM(EO82:EO85) -> #ERROR! | EP86: =SUM(EP82:EP85) -> #ERROR! | EQ86: =SUM(EQ82:EQ85) -> #ERROR! | ER86: =SUM(EN86:EQ86) -> #ERROR! | ES86: =SUM(ES82:ES85) -> #ERROR! | ET86: =SUM(ET82:ET85) -> #ERROR! | EU86: =SUM(EU82:EU85) -> #ERROR! | EV86: =SUM(EV82:EV85) -> #ERROR! | EW86: =SUM(ES86:EV86) -> #ERROR! | EX86: =SUM(EX82:EX85) -> #ERROR! | EY86: =SUM(EY82:EY85) -> #ERROR! | EZ86: =SUM(EZ82:EZ85) -> #ERROR! | FA86: =SUM(FA82:FA85) -> #ERROR! | FB86: =SUM(EX86:FA86) -> #ERROR! | FC86: =SUM(FC82:FC85) -> #ERROR! | FD86: =SUM(FD82:FD85) -> #ERROR! | FE86: =SUM(FE82:FE85) -> #ERROR! | FF86: =SUM(FF82:FF85) -> #ERROR! | FG86: =SUM(FC86:FF86) -> #ERROR!
B88: Stock Based Compensation | CP88: =CF!CP13 -> 283 | CQ88: =CF!CQ13 -> 303 | CR88: =CF!CR13 -> 281 | CS88: =CF!CS13 -> 281 | CT88: =SUM(CP88:CS88) -> 1148 | CU88: =CF!CU13 -> 368 | CV88: =CF!CV13 -> 332 | CW88: =CF!CW13 -> 309 | CX88: =CF!CX13 -> 296 | CY88: =SUM(CU88:CX88) -> 1305 | CZ88: =CF!CZ13 -> 448 | DA88: =CF!DA13 -> 364 | DB88: =CF!DB13 -> 324 | DC88: =CF!DC13 -> 308 | DD88: =SUM(CZ88:DC88) -> 1444 | DE88: =CF!DE13 -> 397 | DF88: =CF!DF13 -> 328 | DG88: =CF!DG13 -> 326 | DH88: =CF!DH13 -> 307 | DI88: =SUM(DE88:DH88) -> 1358 | DJ88: =CF!DJ13 -> 433 | DK88: =CF!DK13 -> 387 | DL88: =CF!DL13 -> 383 | DM88: =CF!DM13 -> 343 | DN88: =SUM(DJ88:DM88) -> 1546 | DO88: =CF!DO13 -> 389 | DP88: =CF!DP13 -> 470 | DQ88: =CF!DQ13 -> 431 | DR88: =DR89*DR12 -> 545.643 | DS88: =SUM(DO88:DR88) -> 1835.643 | DT88: =CF!DT13 -> 449 | DU88: =CF!DU13 -> 492 | DV88: =CF!DV13 -> 452 | DW88: =CF!DW13 -> 461 | DX88: =SUM(DT88:DW88) -> 1854 | DY88: =CF!DY13 -> 425 | DZ88: =CF!DZ13 -> 619 | EA88: =CF!EA13 -> 543 | EB88: =CF!EB13 -> 449 | EC88: =SUM(DY88:EB88) -> 2036 | ED88: =CF!ED13 -> 707 | EE88: =CF!EE13 -> 892 | EF88: =CF!EF13 -> 793 | EG88: =CF!EG13 -> 736 | EH88: =SUM(ED88:EG88) -> 3128 | EI88: =EI89*EI12 -> #ERROR! | EJ88: =EJ89*EJ12 -> #ERROR! | EK88: =EK89*EK12 -> #ERROR! | EL88: =EL89*EL12 -> #ERROR! | EM88: =SUM(EI88:EL88) -> #ERROR! | EN88: =EN89*EN12 -> #ERROR! | EO88: =EO89*EO12 -> #ERROR! | EP88: =EP89*EP12 -> #ERROR! | EQ88: =EQ89*EQ12 -> #ERROR! | ER88: =SUM(EN88:EQ88) -> #ERROR! | ES88: =ES89*ES12 -> #ERROR! | ET88: =ET89*ET12 -> #ERROR! | EU88: =EU89*EU12 -> #ERROR! | EV88: =EV89*EV12 -> #ERROR! | EW88: =SUM(ES88:EV88) -> #ERROR! | EX88: =EX89*EX12 -> #ERROR! | EY88: =EY89*EY12 -> #ERROR! | EZ88: =EZ89*EZ12 -> #ERROR! | FA88: =FA89*FA12 -> #ERROR! | FB88: =SUM(EX88:FA88) -> #ERROR! | FC88: =FC89*FC12 -> #ERROR! | FD88: =FD89*FD12 -> #ERROR! | FE88: =FE89*FE12 -> #ERROR! | FF88: =FF89*FF12 -> #ERROR! | FG88: =SUM(FC88:FF88) -> #ERROR!
B89: % of Revenues | CP89: =CP88/CP12 -> 0.022171733 | CQ89: =CQ88/CQ12 -> 0.02190731 | CR89: =CR88/CR12 -> 0.019307407 | CS89: =CS88/CS12 -> 0.019088377 | CT89: =CT88/CT12 -> 0.0205477 | CU89: =CU88/CU12 -> 0.028792739 | CV89: =CV88/CV12 -> 0.025161046 | CW89: =CW88/CW12 -> 0.021361908 | ... DQ89: =DQ88/DQ12 -> 0.022459614 | DR89: 0.027 | DS89: =DS88/DS12 -> 0.025507441 | DT89: 0.027 | DU89: 0.027 | DV89: 0.02 | DW89: 0.018 | DX89: =DX88/DX12 -> 0.02380983 | DY89: 0.027 | DZ89: =DZ88/DZ12 -> 0.033399881 | EA89: =EA88/EA12 -> 0.030021562 | EB89: =EB88/EB12 -> 0.022987917 | EC89: =EC88/EC12 -> 0.027249123 | ED89: =ED88/ED12 -> 0.038522312 | EE89: =EE88/EE12 -> 0.058220743 | EF89: =EF88/EF12 -> 0.051701656 | EG89: =EG88/EG12 -> 0.052414186 | EH89: =EH88/EH12 -> 0.049608272 | EI89: 0.045 | EJ89: 0.04 | EK89: 0.039 | EL89: 0.039 | EM89: =EM88/EM12 -> #ERROR! | EN89: 0.039 | EO89: 0.037 | EP89: 0.035 | EQ89: 0.035 | ER89: =ER88/ER12 -> #ERROR! | ES89: 0.03 | ET89: 0.03 | EU89: 0.03 | EV89: 0.03 | EW89: =EW88/EW12 -> #ERROR! | EX89: 0.03 | EY89: 0.03 | EZ89: 0.03 | FA89: 0.03 | FB89: =FB88/FB12 -> #ERROR! | FC89: 0.03 | FD89: 0.03 | FE89: 0.03 | FF89: 0.03 | FG89: =FG88/FG12 -> #ERROR!
B95: Consensus Revenues | AT95: 8444 | AU95: 9598 | AV95: 34209 | AW95: 9434 | AX95: 9231 | AY95: 9960 | AZ95: 10201 | BA95: 38826 | BB95: 8940 | BC95: 8009 | BD95: 8739 | BE95: 9694 | BF95: 35382 | BG95: 8852 | BH95: 8680 | BI95: 8539.11 | BJ95: 9037.09 | BK95: 32671.9 | BL95: 8424.21 | BM95: 8340.37 | BN95: 8994.01 | BO95: 9593 | BP95: 35269.83 | BQ95: 8424.21 | BR95: 8340.37 | BS95: 8994.01 | BT95: 9593 | BU95: 35269.83 | BV95: 8424.21 | BW95: 8340.37 | BX95: 8994.01 | BY95: 9593 | BZ95: 35269.83 | CU95: =CU1334 -> 12824 | CV95: =CV1334 -> 13131 | CW95: =CW1334 -> 14249 | CX95: =CX1334 -> 15004 | CY95: =CY1334 -> 55229 | CZ95: =CZ1334 -> 13729 | DA95: =DA1334 -> 14213 | DB95: =DB1334 -> 15606 | ... DD95: =DD1334 -> 58887
B96: Consensus EPS | AT96: 1.18 | AU96: 0.33 | AV96: 1.16 | AW96: 0.34 | AX96: 0.33 | AY96: 0.32 | AZ96: 0.4 | BA96: 1.4 | BB96: 0.23 | BC96: 0.15 | BD96: 0.22 | BE96: 0.26 | BF96: 0.86 | BG96: 0.27851549 | BH96: 0.21598783 | BI96: 0.22 | BJ96: 0.29 | BK96: 0.57 | BL96: 0.24 | BM96: 0.23 | BN96: 0.29 | BO96: 0.35 | BP96: 1.11 | BQ96: 0.24 | BR96: 0.23 | BS96: 0.29 | BT96: 0.35 | BU96: 1.11 | BV96: 0.24 | BW96: 0.23 | BX96: 0.29 | BY96: 0.35 | BZ96: 1.11 | CU96: =CU1343 -> 0.42 | CV96: =CV1343 -> 0.53 | CW96: =CW1343 -> 0.6 | CX96: =CX1343 -> 0.67 | CY96: =CY1343 -> 2.21 | CZ96: =CZ1343 -> 0.48 | DA96: =DA1343 -> 0.55 | DB96: =DB1343 -> 0.77 | ... DD96: =DD1343 -> 2.67
B97: Percentage of Revenues
B98: Gross profits ex dep | N98: =1-cashCOGS/Sales -> 0.64689218 | O98: =1-cashCOGS/Sales -> 0.60300321 | P98: =1-cashCOGS/Sales -> 0.63720101 | Q98: =1-cashCOGS/Sales -> 0.6891253 | R98: =1-cashCOGS/Sales -> 0.64674761 | S98: =1-cashCOGS/Sales -> 0.7040687 | T98: =1-cashCOGS/Sales -> 0.71108805 | U98: =1-cashCOGS/Sales -> 0.71329148 | ... FG98: =1-cashCOGS/Sales -> #ERROR!
B99: Inc. gross profits ex dep | O99: =1-(O19-N19)/(O12-N12) -> 4.1621622 | P99: =1-(P19-O19)/(P12-O12) -> 0.88930348 | Q99: =1-(Q19-P19)/(Q12-P12) -> 1.0849377 | S99: =1-(S19-Q19)/(S12-Q12) -> 0.481409 | T99: =1-(T19-S19)/(T12-S12) -> 0.57142857 | U99: =1-(U19-T19)/(U12-T12) -> 0.73883162 | V99: =1-(V19-U19)/(V12-U12) -> 1.0158371 | W99: =1-(W19-R19)/(W12-R12) -> 1.3344031 | X99: =1-(X19-V19)/(X12-V12) -> -0.40639269 | Y99: =1-(Y19-X19)/(Y12-X12) -> -0.12703583 | Z99: =1-(Z19-Y19)/(Z12-Y12) -> 1.4617169 | AA99: =1-(AA19-Z19)/(AA12-Z12) -> 3.0344828 | AB99: =1-(AB19-W19)/(AB12-W12) -> 1.0977634 | AC99: =1-(AC19-AA19)/(AC12-AA12) -> 0.86222222 | AD99: =1-(AD19-AC19)/(AD12-AC12) -> 0.87463557 | AE99: =1-(AE19-AD19)/(AE12-AD12) -> -0.075829384 | AF99: =1-(AF19-AE19)/(AF12-AE12) -> 1.2990868 | AG99: =1-(AG19-AB19)/(AG12-AB12) -> 0.88910533 | AH99: =1-(AH19-AF19)/(AH12-AF12) -> 2.2178218 | AI99: =1-(AI19-AH19)/(AI12-AH12) -> 0.89393939 | AJ99: =1-(AJ19-AI19)/(AJ12-AI12) -> 0.42162162 | AK99: =1-(AK19-AJ19)/(AK12-AJ12) -> 0.97713415 | AL99: =1-(AL19-AG19)/(AL12-AG12) -> -3.8177778 | AM99: =1-(AM19-AK19)/(AM12-AK12) -> 0.74816626 | AN99: =1-(AN19-AM19)/(AN12-AM12) -> -0.50769231 | AO99: =1-(AO19-AN19)/(AO12-AN12) -> 1.0580138 | AP99: =1-(AP19-AO19)/(AP12-AO12) -> 1.1090308 | AQ99: =1-(AQ19-AL19)/(AQ12-AL12) -> 1.0370151 | AR99: =1-(AR19-AP19)/(AR12-AP12) -> 1.1123077 | AS99: =1-(AS19-AR19)/(AS12-AR12) -> 2.3333333 | AT99: =1-(AT19-AS19)/(AT12-AS12) -> -0.1563981 | AU99: =1-(AU19-AT19)/(AU12-AT12) -> 0.57586513 | AV99: =1-(AV19-AQ19)/(AV12-AQ12) -> 0.6074238 | AW99: =1-(AW19-AU19)/(AW12-AU12) -> -1.6219512 | AX99: =1-(AX19-AV19)/(AX12-AV12) -> 0.73324526 | AY99: =1-(AY19-AX19)/(AY12-AX12) -> 1.2098765 | AZ99: =1-(AZ19-AY19)/(AZ12-AY12) -> 0.85477178 | BA99: =1-(BA19-AV19)/(BA12-AV12) -> 0.68204462 | BB99: =1-(BB19-AZ19)/(BB12-AZ12) -> 0.99206979 | BC99: =1-(BC19-BB19)/(BC12-BB12) -> 0.82814178 | BD99: =1-(BD19-BC19)/(BD12-BC12) -> 0.22465753 | BE99: =1-(BE19-BD19)/(BE12-BD12) -> 0.50994764 | BF99: =1-(BF19-BA19)/(BF12-BA12) -> 1.3513357 | BG99: =1-(BG19-BE19)/(BG12-BE12) -> 0.42042755 | BH99: =1-(BH19-BG19)/(BH12-BG12) -> 2.2965116 | BI99: =1-(BI19-BH19)/(BI12-BH12) -> 0.82198582 | BJ99: =1-(BJ19-BI19)/(BJ12-BI12) -> 1.5273312 | BK99: =1-(BK19-BF19)/(BK12-BF12) -> 0.57079946 | BL99: =1-(BL19-BJ19)/(BL12-BJ12) -> 0.98652551 | BM99: =1-(BM19-BL19)/(BM12-BL12) -> 0.088669951 | BN99: =1-(BN19-BM19)/(BN12-BM12) -> 1.060241 | BO99: =1-(BO19-BN19)/(BO12-BN12) -> 0.78252135 | BP99: =1-(BP19-BK19)/(BP12-BK12) -> -0.86229947 | BQ99: =1-(BQ19-BO19)/(BQ12-BO12) -> 0.99907493 | BR99: =1-(BR19-BQ19)/(BR12-BQ12) -> 0.97497156 | BS99: =1-(BS19-BR19)/(BS12-BR12) -> 0.93333333 | BT99: =1-(BT19-BS19)/(BT12-BS12) -> 1.2389831 | BU99: =1-(BU19-BP19)/(BU12-BP12) -> 0.34444896 | BV99: =1-(BV19-BT19)/(BV12-BT12) -> 1.5962963 | BW99: =1-(BW19-BV19)/(BW12-BV12) -> 1.5321888 | BX99: =1-(BX19-BW19)/(BX12-BW12) -> 0.23442136 | BY99: =1-(BY19-BX19)/(BY12-BX12) -> 0.41971831 | BZ99: =1-(BZ19-BU19)/(BZ12-BU12) -> 1.002354 | CA99: =1-(CA19-BY19)/(CA12-BY12) -> 0.51438849 | CB99: =1-(CB19-CA19)/(CB12-CA12) -> 0.42702703 | CC99: =1-(CC19-CB19)/(CC12-CB12) -> 0.95004163 | CD99: =1-(CD19-CC19)/(CD12-CC12) -> 0.01734104 | CE99: =1-(CE19-BZ19)/(CE12-BZ12) -> 0.64494988 | CF99: =1-(CF19-CD19)/(CF12-CD12) -> 0.50050968 | CG99: =1-(CG19-CF19)/(CG12-CF12) -> 0.57647059 | CH99: =1-(CH19-CG19)/(CH12-CG12) -> -0.34090909 | CI99: =1-(CI19-CH19)/(CI12-CH12) -> -29.3 | CJ99: =1-(CJ19-CE19)/(CJ12-CE12) -> -1.2948328 | CK99: =1-(CK19-CI19)/(CK12-CI12) -> 0.77146042 | CL99: =1-(CL19-CK19)/(CL12-CK12) -> 1.4329004 | CM99: =1-(CM19-CL19)/(CM12-CL12) -> 1.4494048 | CN99: =1-(CN19-CM19)/(CN12-CM12) -> 0.26210826 | CO99: =1-(CO19-CJ19)/(CO12-CJ12) -> 1.7693523 | CP99: =1-(CP19-CN19)/(CP12-CN12) -> 0.83551402 | CQ99: =1-(CQ19-CP19)/(CQ12-CP12) -> 1.3626992 | CR99: =1-(CR19-CQ19)/(CR12-CQ12) -> 0.78699862 | CS99: =1-(CS19-CR19)/(CS12-CR12) -> 0.83233533 | CT99: =1-(CT19-CO19)/(CT12-CO12) -> 1.4604681 | CU99: =1-(CU19-CS19)/(CU12-CS12) -> 1.0134021 | CV99: =1-(CV19-CU19)/(CV12-CU12) -> 1.47343 | CW99: =1-(CW19-CV19)/(CW12-CV12) -> 0.74566929 | CX99: =1-(CX19-CW19)/(CX12-CW12) -> 0.77951002 | CY99: =1-(CY19-CT19)/(CY12-CT12) -> 1.5165049 | CZ99: =1-(CZ19-CX19)/(CZ12-CX12) -> 1.3405211 | DA99: =1-(DA19-CZ19)/(DA12-CZ12) -> 1.3208955 | DB99: =1-(DB19-DA19)/(DB12-DA12) -> 0.90022272 | DC99: =1-(DC19-DB19)/(DC12-DB12) -> 0.20805369 | DD99: =1-(DD19-CY19)/(DD12-CY12) -> 0.16702977 | DE99: =1-(DE19-DC19)/(DE12-DC12) -> 0.59695817 | DF99: =1-(DF19-DE19)/(DF12-DE12) -> 0.21212121 | DG99: =1-(DG19-DF19)/(DG12-DF12) -> 0.74025974 | DH99: =1-(DH19-DG19)/(DH12-DG12) -> 0.87942478 | DI99: =1-(DI19-DD19)/(DI12-DD12) -> 0.95206107 | DJ99: =1-(DJ19-DH19)/(DJ12-DH12) -> 0.9929078 | DK99: =1-(DK19-DJ19)/(DK12-DJ12) -> 0.68526786 | DL99: =1-(DL19-DK19)/(DL12-DK12) -> 0.95093139 | DM99: =1-(DM19-DL19)/(DM12-DL12) -> 1.8063241 | DN99: =1-(DN19-DI19)/(DN12-DI12) -> 0.69543712 | DO99: =1-(DO19-DM19)/(DO12-DM12) -> 0.77272727 | DP99: =1-(DP19-DO19)/(DP12-DO12) -> 1.6171171 | DQ99: =1-(DQ19-DP19)/(DQ12-DP12) -> 0.57430168 | DR99: =1-(DR19-DQ19)/(DR12-DQ12) -> 0.85574092 | DS99: =1-(DS19-DN19)/(DS12-DN12) -> 0.12891674 | DT99: =1-(DT19-DR19)/(DT12-DR12) -> -0.57742782 | DU99: =1-(DU19-DT19)/(DU12-DT12) -> 14.96 | DV99: =1-(DV19-DU19)/(DV12-DU12) -> 0.50609319 | DW99: =1-(DW19-DV19)/(DW12-DV12) -> 0.90395137 | DX99: =1-(DX19-DS19)/(DX12-DS12) -> 0.48881735 | DY99: =1-(DY19-DW19)/(DY12-DW12) -> 1.2053824 | DZ99: =1-(DZ19-DY19)/(DZ12-DY12) -> -9.5757576 | EA99: =1-(EA19-DZ19)/(EA12-DZ12) -> 0.81838565 | EB99: =1-(EB19-EA19)/(EB12-EA12) -> 0.33702422 | EC99: =1-(EC19-DX19)/(EC12-DX12) -> 1.4449031 | ED99: =1-(ED19-EB19)/(ED12-EB12) -> 0.41984733 | EE99: =1-(EE19-ED19)/(EE12-ED12) -> 1.2720976 | EF99: =1-(EF19-EE19)/(EF12-EE12) -> 61.882353 | EG99: =1-(EG19-EF19)/(EG12-EF12) -> 0.77160494 | EH99: =1-(EH19-EC19)/(EH12-EC12) -> 0.97736626 | EI99: =1-(EI19-EG19)/(EI12-EG12) -> #ERROR! | EJ99: =1-(EJ19-EI19)/(EJ12-EI12) -> #ERROR! | EK99: =1-(EK19-EJ19)/(EK12-EJ12) -> #ERROR! | EL99: =1-(EL19-EK19)/(EL12-EK12) -> #ERROR! | EM99: =1-(EM19-EH19)/(EM12-EH12) -> #ERROR! | EN99: =1-(EN19-EL19)/(EN12-EL12) -> #ERROR! | EO99: =1-(EO19-EN19)/(EO12-EN12) -> #ERROR! | EP99: =1-(EP19-EO19)/(EP12-EO12) -> #ERROR! | EQ99: =1-(EQ19-EP19)/(EQ12-EP12) -> #ERROR! | ER99: =1-(ER19-EM19)/(ER12-EM12) -> #ERROR! | ES99: =1-(ES19-EQ19)/(ES12-EQ12) -> #ERROR! | ET99: =1-(ET19-ES19)/(ET12-ES12) -> #ERROR! | EU99: =1-(EU19-ET19)/(EU12-ET12) -> #ERROR! | EV99: =1-(EV19-EU19)/(EV12-EU12) -> #ERROR! | EW99: =1-(EW19-ER19)/(EW12-ER12) -> #ERROR! | EX99: =1-(EX19-EV19)/(EX12-EV12) -> #ERROR! | EY99: =1-(EY19-EX19)/(EY12-EX12) -> #ERROR! | EZ99: =1-(EZ19-EY19)/(EZ12-EY12) -> #ERROR! | FA99: =1-(FA19-EZ19)/(FA12-EZ12) -> #ERROR! | FB99: =1-(FB19-EW19)/(FB12-EW12) -> #ERROR! | FC99: =1-(FC19-FA19)/(FC12-FA12) -> #ERROR! | FD99: =1-(FD19-FC19)/(FD12-FC12) -> #ERROR! | FE99: =1-(FE19-FD19)/(FE12-FD12) -> #ERROR! | FF99: =1-(FF19-FE19)/(FF12-FE12) -> #ERROR! | FG99: =1-(FG19-FB19)/(FG12-FB12) -> #ERROR!
B100: Cash COGS y/y change | S100: =S19/N19-1 -> -0.0080226522 | T100: =T19/O19-1 -> -0.17169571 | U100: =U19/P19-1 -> -0.13963964 | V100: =V19/Q19-1 -> -0.1182932 | W100: =W19/R19-1 -> -0.11227238 | X100: =X19/S19-1 -> -0.15366318 | Y100: =Y19/T19-1 -> 0.090302719 | Z100: =Z19/U19-1 -> -0.08329367 | ... FG100: =FG19/FB19-1 -> #ERROR!
